Workbook
Name ch_hrgincppn: '[1]CEK Harga'!$AD$2:$AD$13259
Name ch_hrgincppn: '[2]CEK Harga'!$AD$2:$AD$13259
Name ch_kd: '[1]CEK Harga'!$W$2:$W$13259
Name ch_kd: '[2]CEK Harga'!$W$2:$W$13259
Name TBLHRG: #REF!

Sheet REVISI FAKTUR SC
B1: REKAP REVISI FAKTUR (SC) Per Barang
B2: Per Maret 2023
A4: No | B4: Tanggal Revisi | C4: Tanggal Faktur | D4: No. Faktur | E4: SC | F4: Adm SC | G4: Cust | H4: Nama Barang | I4: Jumlah | J4: Keterangan | K4: Case | L4: Next Step
A5: 1 | B5: 44937 | C5: 44937 | D5: B23000320 | E5: Dannis | F5: Nia | G5: Santani, UD | H5: Kresnadan 3G 10 X 2 kg (edit harga jadi 27.500) | I5: 6875000 | J5: SC salah harga (harga awal 29.500)
A6: 2 | B6: 44938 | C6: 44938 | D6: D23000300 | E6: Yuyun | F6: Nina | G6: Sampurna/Heri (Kemuning) | H6: Ammate 150 EC 20 X 100 ml (FMC) (edit harga jadi 102.000) | I6: 5347000 | J6: SC salah harga (harga awal 99.000)
A7: 1 | B7: 44943 | C7: 44943 | D7: E23000478 | E7: Umi | F7: Nita | G7: Sahabat Tani, UD/Edy | H7: Amolin | I7: 10080000 | J7: Double SO | K7: SO 1 dibuat tanggal 16 (input tgl 16/01/23 jam 15.54, dan SO 2 dibuat tgl 17/01/2022 (input 17/01/2022, jam 9.06). Setiap tutup tanggal SC cek penjualannya, Double SO tersebut diketahui saat SC cek penjualannya, jadi pada saat itu juga 1 nota di Batal, sebelum nota diambil oleh gudang. | L7: Saat SC akan TTD Nota, SC juga cek antara nota dan SO, dan SC Umi sudah melakukannya, sehingga kesalahan bisa terdeteksi sebelum Nota diserahkan ke Gudang
A8: 3 | B8: 44950 | C8: 44949 | D8: C23000519 | E8: Elok | F8: Fani | G8: Barokah Tani/Syaikur | H8: Tali Gawar 989 40 X 600 gr (edit harga jadi 28.500) | I8: 8740000 | J8: SC salah harga (harga awal 38.500) | K8: Salah tulis harga di SO, seharusnya 28.500 | L8: Filter dari Acc lebih ditingkatkan, apabila harga terlalu mahal, tanyakan juga kepada SC
A9: 4 | B9: 44950 | C9: 44950 | D9: B23000779 | E9: Evi | F9: Nia | G9: Alam Tani | H9: Decis 2.5 EC 20 X 500 ml (edit harga jadi 121.500) | I9: 92300000 | J9: SC salah harga (harga awal 112.500) | K9: Salah tulis harga di SO, seharusnya 121.500 | L9: Adm PL menanyakan kepada SC ybs apabila ada acc harga yang meragukan, Revisi SOP
A10: 5 | B10: 44952 | C10: 44952 | D10: E23000777 | E10: Umi | F10: Nita | G10: Al Mubarok/Lutfi | H10: Karimazu 590 EC 20 X 800 ml (edit harga jadi 138.500) | I10: 2770000 | J10: SC salah harga (harga awal 135.000) | K10: Salah liat harga, di PL 138.500 | L10: PL digital
A11: 6 | B11: 44954 | C11: 44954 | D11: C23000675 | E11: Fani | F11: Elok | G11: Setia Hati, Toko | H11: Alfatox 50 EC 50 X 80 ml (AGM) (edit harga jadi 13.500) | I11: 1350000 | J11: SC salah harga (harga awal 18.500) | K11: SC salah harga (harga awal 18.500)
A12: 1 | B12: 44965 | C12: 44965 | D12: D23001098 | E12: Dannis | F12: Nina | G12: Puma Tani | H12: Sprayer Elektrik Joeragan 16 L Battery (edit harga jadi 410.000) | I12: 820000 | J12: SC Salah Harga | K12: SC salah Harga, harga awal 395.000, Hasil konfirmasi dengan SC : SC tidak lihat Data Price List, saat cek harga pertama sudah diingatkan kalau harga terlalu murah, tapi sampai tutup penjualan harga tetap 395.000
A13: 2 | B13: 44965 | C13: 44965 | D13: D23001115 | E13: Zakia | F13: Nina | G13: Alam Tani/Wayan | H13: Trisula 450 SL 20 X 500 ml (edit harga jadi 32.500) | I13: 4120000 | J13: SC Salah Harga | K13: SC Salah Harga, harga awal 54.500 (harga untuk Trisula 1ltr) saat cek harga 1 sudah dikonfirmasi, hasil konfirmasi menurut SC tidak masalah, saat tutup penjualan dikonfirmasi lagi dan ternyata salah harga
A14: 3 | B14: 44977 | C14: 44977 | D14: C23001323 | E14: Elok | F14: Fani | G14: Dino Vita, Toko | H14: Karissnail 6 PL 20 X 500 gr (M2U) (edit harga jadi 57.000) | I14: 2280000 | J14: SC salah harga (harga awal 25.000) | K14: Salah kasih harga yang 200 gr
A15: 1 | B15: 45002 | C15: 45000 | D15: B23002204 | E15: Zakia | F15: Nia | G15: Sukma Tani | H15: Mulsa Ori Universal 0.25 60 cm X 18 kg (Roll) (edit harga jadi 567.000) | I15: 28721550 | J15: SC salah harga (harga awal 603.000) | K15: SC Salah beri harga sama dengan Mulsa Karisma
A31: 1
B34: REVISI FAKTUR BERDASARKAN SC (Salah Harga) | R34: REVISI FAKTUR BERDASARKAN SC (Salah SO)
B35: Periode Januari - Maret 2023 | R35: Periode Januari 2023
B36: SC | C36: Jan | D36: Feb | E36: Mar | F36: Apr | G36: Mei | H36: Jun | I36: Jul | J36: Agst | K36: Sept | L36: Okt | M36: Nov | N36: Des | O36: Total | P36: % | R36: SC | S36: Jan | T36: Feb | U36: Mar | V36: Apr | W36: Mei | X36: Jun | Y36: Jul | Z36: Agst | AA36: Sept | AB36: Okt | AC36: Nov | AD36: Des | AE36: Total | AF36: %
B37: Dannis | C37: 1 | D37: 1 | O37: =SUM(C37:N37) -> 2 | P37: =+O37/#REF! -> #REF! | R37: Dannis | AE37: =SUM(S37:AD37) -> 0 | AF37: =AE37/O49 -> 0
B38: Elok | C38: 2 | D38: 1 | O38: =SUM(C38:N38) -> 3 | P38: =+O38/#REF! -> #REF! | R38: Elok | AE38: =SUM(S38:AD38) -> 0 | AF38: =AE38/O50 -> 0
B39: Evi | C39: 1 | O39: =SUM(C39:N39) -> 1 | P39: =+O39/#REF! -> #REF! | R39: Evi | AE39: =SUM(S39:AD39) -> 0 | AF39: =AE39/O51 -> 0
B40: Faisal | O40: =SUM(C40:N40) -> 0 | P40: =+O40/#REF! -> #REF! | R40: Faisal | AE40: =SUM(S40:AD40) -> 0 | AF40: =AE40/O52 -> 0
B41: Riyan | O41: =SUM(C41:N41) -> 0 | P41: =+O41/#REF! -> #REF! | R41: Riyan | AE41: =SUM(S41:AD41) -> 0 | AF41: =AE41/O53 -> 0
B42: Umi | C42: 1 | O42: =SUM(C42:N42) -> 1 | P42: =+O42/#REF! -> #REF! | R42: Umi | S42: 1 | AE42: =SUM(S42:AD42) -> 1 | AF42: =AE42/O54 -> 0.00039872408
B43: Yuyun | C43: 1 | O43: =SUM(C43:N43) -> 1 | P43: =+O43/#REF! -> #REF! | R43: Yuyun | AE43: =SUM(S43:AD43) -> 0 | AF43: =AE43/O55 -> 0
B44: Zakia | D44: 1 | E44: 1 | O44: =SUM(C44:N44) -> 2 | P44: =+O44/#REF! -> #REF! | R44: Zakia | AE44: =SUM(S44:AD44) -> 0 | AF44: =AE44/O56 -> 0
B45: Grand Total | C45: =SUM(C37:C44) -> 6 | D45: =SUM(D37:D44) -> 3 | E45: =SUM(E37:E44) -> 1 | F45: =SUM(F37:F44) -> 0 | G45: =SUM(G37:G44) -> 0 | H45: =SUM(H37:H44) -> 0 | I45: =SUM(I37:I44) -> 0 | J45: =SUM(J37:J44) -> 0 | ... P45: =SUM(P37:P44) -> #REF! | R45: Grand Total | S45: =SUM(S37:S44) -> 1 | T45: =SUM(T37:T44) -> 0 | U45: =SUM(U37:U44) -> 0 | V45: =SUM(V37:V44) -> 0 | W45: =SUM(W37:W44) -> 0 | X45: =SUM(X37:X44) -> 0 | Y45: =SUM(Y37:Y44) -> 0 | Z45: =SUM(Z37:Z44) -> 0 | ... AE45: =SUM(AE37:AE44) -> 1
B46: JUMLAH Per Barang yang Tertera di SO
B47: JUMLAH Per Barang yang Tertera di SO
B48: SC | C48: Jan | D48: Feb | E48: Mar | F48: Apr | G48: Mei | H48: Jun | I48: Jul | J48: Agst | K48: Sept | L48: Okt | M48: Nov | N48: Des | O48: Total
B49: Dannis | C49: 311 | D49: 316 | E49: 215 | O49: =SUM(C49:N49) -> 842
B50: Elok | C50: 1841 | D50: 1656 | E50: 1270 | O50: =SUM(C50:N50) -> 4767
B51: Evi | C51: 794 | D51: 691 | E51: 479 | O51: =SUM(C51:N51) -> 1964
B52: Faisal | C52: 197 | D52: 168 | E52: 114 | O52: =SUM(C52:N52) -> 479
B53: Riyan | C53: 562 | D53: 620 | E53: 421 | O53: =SUM(C53:N53) -> 1603
B54: Umi | C54: 1021 | D54: 905 | E54: 582 | O54: =SUM(C54:N54) -> 2508
B55: Yuyun | C55: 1387 | D55: 1338 | E55: 1090 | O55: =SUM(C55:N55) -> 3815
B56: Zakia | C56: 1116 | D56: 1085 | E56: 766 | O56: =SUM(C56:N56) -> 2967
B57: Supriyanto/Nadia | C57: 3 | D57: 8 | O57: =SUM(C57:N57) -> 11
B58: Others | O58: =SUM(C58:N58) -> 0
B59: Wira | O59: =SUM(C59:N59) -> 0
B60: Ibnu | O60: =SUM(C60:N60) -> 0
B61: Alpha | O61: =SUM(C61:N61) -> 0
B62: Abd Muhid | O62: =SUM(C62:N62) -> 0
B63: Nugroho | D63: 6 | O63: =SUM(C63:N63) -> 6
B64: TOTAL | C64: =SUM(C49:C63) -> 7232 | D64: =SUM(D49:D63) -> 6793 | E64: =SUM(E49:E63) -> 4937 | F64: =SUM(F49:F63) -> 0 | G64: =SUM(G49:G63) -> 0 | H64: =SUM(H49:H63) -> 0 | I64: =SUM(I49:I63) -> 0 | J64: =SUM(J49:J63) -> 0 | ... O64: =SUM(O49:O63) -> 18962
B66: % REVISI FAKTUR TERHADAP TOTAL BARANG
B67: SC | C67: Jan | D67: Feb | E67: Mar | F67: Apr | G67: Mei | H67: Jun | I67: Jul | J67: Agst | K67: Sept | L67: Okt | M67: Nov | N67: Des | O67: Total
B68: Dannis | C68: =C37/C49 -> 0.0032154341 | D68: =D37/D49 -> 0.003164557 | E68: =E37/E49 -> 0 | F68: =F37/F49 -> #DIV/0! | G68: =G37/G49 -> #DIV/0! | H68: =H37/H49 -> #DIV/0! | I68: =I37/I49 -> #DIV/0! | J68: =J37/J49 -> #DIV/0! | ... O68: =O37/O49 -> 0.0023752969
B69: Elok | C69: =C38/C50 -> 0.0010863661 | D69: =D38/D50 -> 0.00060386473 | E69: =E38/E50 -> 0 | F69: =F38/F50 -> #DIV/0! | G69: =G38/G50 -> #DIV/0! | H69: =H38/H50 -> #DIV/0! | I69: =I38/I50 -> #DIV/0! | J69: =J38/J50 -> #DIV/0! | ... O69: =O38/O50 -> 0.00062932662
B70: Evi | C70: =C39/C51 -> 0.0012594458 | D70: =D39/D51 -> 0 | E70: =E39/E51 -> 0 | F70: =F39/F51 -> #DIV/0! | G70: =G39/G51 -> #DIV/0! | H70: =H39/H51 -> #DIV/0! | I70: =I39/I51 -> #DIV/0! | J70: =J39/J51 -> #DIV/0! | ... O70: =O39/O51 -> 0.00050916497
B71: Faisal | C71: =C40/C52 -> 0 | D71: 0 | E71: =E40/E52 -> 0 | F71: 0 | G71: 0 | H71: 0 | I71: 0 | J71: 0 | K71: =K40/K52 -> #DIV/0! | L71: =L40/L52 -> #DIV/0! | M71: =M40/M52 -> #DIV/0! | N71: =N40/N52 -> #DIV/0! | O71: =O40/O52 -> 0
B72: Riyan | C72: =C41/C53 -> 0 | D72: =D41/D53 -> 0 | E72: =E41/E53 -> 0 | F72: =F41/F53 -> #DIV/0! | G72: =G41/G53 -> #DIV/0! | H72: =H41/H53 -> #DIV/0! | I72: =I41/I53 -> #DIV/0! | J72: =J41/J53 -> #DIV/0! | ... O72: =O41/O53 -> 0
B73: Umi | C73: =C42/C54 -> 0.00097943193 | D73: =D42/D54 -> 0 | E73: =E42/E54 -> 0 | F73: =F42/F54 -> #DIV/0! | G73: =G42/G54 -> #DIV/0! | H73: =H42/H54 -> #DIV/0! | I73: =I42/I54 -> #DIV/0! | J73: =J42/J54 -> #DIV/0! | ... O73: =O42/O54 -> 0.00039872408
B74: Yuyun | C74: =C43/C55 -> 0.00072098053 | D74: =D43/D55 -> 0 | E74: =E43/E55 -> 0 | F74: =F43/F55 -> #DIV/0! | G74: =G43/G55 -> #DIV/0! | H74: =H43/H55 -> #DIV/0! | I74: =I43/I55 -> #DIV/0! | J74: =J43/J55 -> #DIV/0! | ... O74: =O43/O55 -> 0.0002621232
B75: Zakia | C75: =C44/C56 -> 0 | D75: =D44/D56 -> 0.00092165899 | E75: =E44/E56 -> 0.001305483 | F75: =F44/F56 -> #DIV/0! | G75: =G44/G56 -> #DIV/0! | H75: =H44/H56 -> #DIV/0! | I75: =I44/I56 -> #DIV/0! | J75: =J44/J56 -> #DIV/0! | ... O75: =O44/O56 -> 0.00067408156
B76: TOTAL | C76: =C45/C64 -> 0.00082964602 | D76: =D45/D64 -> 0.00044163109 | E76: =E45/E64 -> 0.00020255216 | F76: =SUM(F68:F75) -> #DIV/0! | G76: =SUM(G68:G75) -> #DIV/0! | H76: =SUM(H68:H75) -> #DIV/0! | I76: =SUM(I68:I75) -> #DIV/0! | J76: =SUM(J68:J75) -> #DIV/0! | K76: =SUM(K68:K75) -> #DIV/0! | L76: =SUM(L68:L75) -> #DIV/0! | M76: =SUM(M68:M75) -> #DIV/0! | N76: =SUM(N68:N75) -> #DIV/0! | O76: =O45/O64 -> 0.00052737053

Sheet REVISI Per Brg ADM SC
A2: REKAP REVISI FAKTUR (Admin SC) Berdasarkan Jumlah Barang
A3: Per Maret 2023
A5: No | B5: Tanggal Revisi | C5: Tanggal Faktur | D5: No. Faktur | E5: Admin SC | F5: SC | G5: Cust | H5: Nama Barang | I5: Jumlah | J5: Keterangan | K5: Case | L5: Next Step | M5: Next Step (Saran)
A6: 1 | B6: 44937 | C6: 44937 | D6: D23000279 | E6: Evi | F6: Nina | G6: KIU Cabang | H6: Bionik 400 EC 20 X 500 ml (hapus VAT) | I6: 21813168 | J6: Admin salah input | K6: Salah Input VAT, seharusnya KIU Cabang tanpa VAT
A7: 1 | B7: 44970 | C7: 44970 | D7: C23001070 | E7: Umi | F7: Fani | G7: Sahala/Syaiful | H7: Batal | I7: 9925000 | J7: admin salah input, Cust TL Pajak | K7: Salah input cust Tidak Lapor Pajak seharusnya di nota Z tapi dibukakan nota komersil
A8: 1
B31: REVISI FAKTUR BERDASARKAN ADMIN SC
B32: Periode Januari-Februari 2023
B33: Adm. SC | C33: Jan | D33: Feb | E33: Mar | F33: Apr | G33: Mei | H33: Jun | I33: Jul | J33: Agst | K33: Sept | L33: Okt | M33: Nov | N33: Des | O33: Total
B34: Fani | D34: 2 | O34: =SUM(C34:N34) -> 2
B35: Nia | O35: =SUM(C35:N35) -> 0
B36: Nina | C36: 1 | O36: =SUM(C36:N36) -> 1
B37: Nita | O37: =SUM(C37:N37) -> 0
B38: Grand Total | C38: =SUM(C34:C37) -> 1 | D38: =SUM(D34:D37) -> 2 | E38: =SUM(E34:E37) -> 0 | F38: =SUM(F34:F37) -> 0 | G38: =SUM(G34:G37) -> 0 | H38: =SUM(H34:H37) -> 0 | I38: =SUM(I34:I37) -> 0 | J38: =SUM(J34:J37) -> 0 | ... O38: =SUM(O34:O37) -> 3
B39: JUMLAH INPUT BARANG
B40: Adm. SC | C40: Jan | D40: Feb | E40: Mar | F40: Apr | G40: Mei | H40: Jun | I40: Jul | J40: Agst | K40: Sept | L40: Okt | M40: Nov | N40: Des | O40: Total
B41: Fani | C41: 1420 | D41: 1799 | E41: 1154 | O41: =SUM(C41:N41) -> 4373
B42: Nia | C42: 2113 | D42: 1431 | E42: 1808 | O42: =SUM(C42:N42) -> 5352
B43: Nina | C43: 1702 | D43: 2572 | E43: 1826 | O43: =SUM(C43:N43) -> 6100
B44: Nita | C44: 1801 | D44: 811 | O44: =SUM(C44:N44) -> 2612
B45: Mitra | C45: 192 | D45: 172 | E45: 136 | O45: =SUM(C45:N45) -> 500
B46: Ifa | C46: 4 | D46: 8 | E46: 13 | O46: =SUM(C46:N46) -> 25
B47: Grand | C47: =SUM(C41:C46) -> 7232 | D47: =SUM(D41:D46) -> 6793 | E47: =SUM(E41:E46) -> 4937 | F47: =SUM(F41:F46) -> 0 | G47: =SUM(G41:G46) -> 0 | H47: =SUM(H41:H46) -> 0 | I47: =SUM(I41:I46) -> 0 | J47: =SUM(J41:J46) -> 0 | ... O47: =SUM(O41:O46) -> 18962
B48: % REVISI FAKTUR TERHADAP TOTAL INPUT BARANG
B49: Adm. SC | C49: Jan | D49: Feb | E49: Mar | F49: Apr | G49: Mei | H49: Jun | I49: Jul | J49: Agst | K49: Sept | L49: Okt | M49: Nov | N49: Des | O49: Total
B50: Fani | C50: =+C34/C41 -> 0 | D50: =+D34/D41 -> 0.0011117287 | E50: =+E34/E41 -> 0 | F50: =+F34/F41 -> #DIV/0! | G50: =+G34/G41 -> #DIV/0! | H50: =+H34/H41 -> #DIV/0! | I50: =+I34/I41 -> #DIV/0! | J50: =+J34/J41 -> #DIV/0! | ... O50: =+O34/O41 -> 0.00045735193
B51: Nia | C51: =+C35/C42 -> 0 | D51: =+D35/D42 -> 0 | E51: =+E35/E42 -> 0 | F51: =+F35/F42 -> #DIV/0! | G51: =+G35/G42 -> #DIV/0! | H51: =+H35/H42 -> #DIV/0! | I51: =+I35/I42 -> #DIV/0! | J51: =+J35/J42 -> #DIV/0! | ... O51: =+O35/O42 -> 0
B52: Nina | C52: =+C36/C43 -> 0.00058754407 | D52: =+D36/D43 -> 0 | E52: =+E36/E43 -> 0 | F52: =+F36/F43 -> #DIV/0! | G52: =+G36/G43 -> #DIV/0! | H52: =+H36/H43 -> #DIV/0! | I52: =+I36/I43 -> #DIV/0! | J52: =+J36/J43 -> #DIV/0! | ... O52: =+O36/O43 -> 0.00016393443
B53: Nita | C53: =+C37/C44 -> 0 | D53: =+D37/D44 -> 0 | E53: =+E37/E44 -> #DIV/0! | F53: =+F37/F44 -> #DIV/0! | G53: =+G37/G44 -> #DIV/0! | H53: =+H37/H44 -> #DIV/0! | I53: =+I37/I44 -> #DIV/0! | J53: =+J37/J44 -> #DIV/0! | ... O53: =+O37/O44 -> 0
B54: Grand Total | C54: =+C38/C47 -> 0.00013827434 | D54: =+D38/D47 -> 0.00029442073 | E54: =+E38/E47 -> 0 | F54: =+F38/F47 -> #DIV/0! | G54: =+G38/G47 -> #DIV/0! | H54: =+H38/H47 -> #DIV/0! | I54: =+I38/I47 -> #DIV/0! | J54: =+J38/J47 -> #DIV/0! | ... O54: =+O38/O47 -> 0.00015821116

Sheet REVISI PER FAKTUR ADM SC
A2: REKAP REVISI FAKTUR (Admin SC) Berdasarkan Jumlah Faktur
A3: Per Oktober 2022
A5: No | B5: Tanggal Revisi | C5: Tanggal Faktur | D5: No. Faktur | E5: Admin SC | F5: Cust | G5: Keterangan | H5: Jumlah | I5: Keterangan | J5: Case | K5: Next Step
A6: 1 | B6: 44837 | C6: 44835 | D6: D22007033 | E6: Nina | F6: Sadar Sari/Farid Firdaus | G6: Sprayer 5 lt ganti yg 10 ltr | H6: 0 | I6: Admin salah Input | J6: Salah input barang, | K6: Konfirmasi kepada Adm SC ybc, salah input seharusnya yg 10ltr, memberitahukan progres revisi faktur per 15/10/2022
A7: 2 | B7: 44845 | C7: 44845 | D7: B22007412 | E7: Nia | F7: M. Tajudin Al Fajri/Indotani | G7: Monkey 40 SP 100 X 100 gr (EDIT HARGA JADI 18.500) harga sebelumnya 18.000 | H7: 1850000 | I7: Admin salah Input | J7: Admin konfrimasi via telp, salah input harga
A8: 3 | B8: 44853 | C8: 44853 | D8: D22007471 | E8: Nina | F8: KIU Cabang | G8: Biggrow 20 WP 4 X 75 X 5 gr (edit harga 17.597.61) | H8: 100510775 | I8: Admin salah input VAT | J8: Admin Salah Input nota KIU Cabang Inc PPN, KIU Cabang seharusnya diinput tanpa pajak
E9: Nina | F9: KIU Cabang | G9: Bactocyn 150 AL 50 X 200 ml (edit harga 27.654.04) | H9: 100510775 | I9: Admin salah input VAT
E10: Nina | F10: KIU Cabang | G10: Lem Ajaib 50 X 100 ml (edit harga 41.418.21) | H10: 100510775 | I10: Admin salah input VAT
E11: Nina | F11: KIU Cabang | G11: Karissnail 6 PL 20 X 500 gr (M2U) (edit harga 26.363.64) | H11: 100510775 | I11: Admin salah input VAT
A12: 4 | B12: 44856 | C12: 44855 | D12: B22007566 | E12: Nia | F12: Maju Mandiri/Sunardi | G12: BATAL | H12: 950000 | I12: Admin salah input nama cust | J12: Salah Input nama toko seharusnya Sukses Makmur Sunardi, tapi diinput Maju Mandiri/Sunardi
A13: 5 | B13: 44860 | C13: 44859 | D13: O22000085 | E13: Nita | F13: Trubus Jaya/Deni | G13: BATAL | H13: 136500 | I13: Admin salah input
A14: 6 | B14: 44861 | C14: 44856 | D14: B22007577 | E14: Nia | F14: Febri Catur Nugroho | G14: BATAL | H14: 3300000 | I14: Barang diretur, karena admin salah input | J14: Admin salah input, harusnya Cal. D.diana, 0,01/09/2027
A15: 7 | B15: 44863 | C15: 44858 | D15: C22007261 | E15: Fani | F15: Bimo Rukun Tani II | G15: Timun Renes F1 12 X 15 X 10 gr (edit yg Qty 15 di diskon) | H15: 10860000 | I15: Admin salah input | J15: Nota awal Bonus tidak diberi diskon
B23: REVISI FAKTUR BERDASARKAN ADMIN SC
B24: Periode Januari - 29 Oktober 2022
B25: Adm. SC | C25: Jan | D25: Feb | E25: Mar | F25: Apr | G25: Mei | H25: Jun | I25: Jul | J25: Agst | K25: Sept | L25: Okt | M25: Nov | N25: Des | O25: Total
B26: Fani | C26: 14 | D26: 7 | E26: 12 | F26: 13 | G26: 8 | H26: 5 | I26: 0 | J26: 4 | K26: 1 | L26: 1 | O26: =SUM(C26:N26) -> 65
B27: Naily | C27: 2 | D27: 1 | E27: 0 | F27: 0 | G27: 0 | K27: 0 | O27: =SUM(C27:N27) -> 3
B28: Nia | C28: 3 | D28: 2 | E28: 5 | F28: 0 | G28: 1 | H28: 1 | I28: 0 | J28: 0 | K28: 1 | L28: 3 | O28: =SUM(C28:N28) -> 16
B29: Nina | C29: 4 | D29: 1 | E29: 9 | F29: 2 | G29: 1 | H29: 2 | I29: 3 | J29: 4 | K29: 2 | L29: 2 | O29: =SUM(C29:N29) -> 30
B30: Nita | C30: 3 | D30: 1 | E30: 3 | F30: 7 | G30: 3 | H30: 4 | I30: 4 | J30: 6 | K30: 1 | L30: 1 | O30: =SUM(C30:N30) -> 33
B31: Grand Total | C31: =SUM(C26:C30) -> 26 | D31: =SUM(D26:D30) -> 12 | E31: =SUM(E26:E30) -> 29 | F31: =SUM(F26:F30) -> 22 | G31: =SUM(G26:G30) -> 13 | H31: =SUM(H26:H30) -> 12 | I31: =SUM(I26:I30) -> 7 | J31: =SUM(J26:J30) -> 14 | ... O31: =SUM(O26:O30) -> 147
B32: JUMLAH PRODUKSI FAKTUR
B33: Adm. SC | C33: Jan | D33: Feb | E33: Mar | F33: Apr | G33: Mei | H33: Jun | I33: Jul | J33: Agst | K33: Sept | L33: Okt | M33: Nov | N33: Des | O33: Total
B34: Fani | C34: 634 | D34: 667 | E34: 1048 | F34: 725 | G34: 734 | H34: 896 | I34: 914 | J34: 851 | K34: 881 | L34: 758 | O34: =SUM(C34:N34) -> 8108
B35: Ex Naily | C35: 806 | D35: 458 | E35: 0 | F35: 0 | G35: 0 | H35: 0 | I35: 0 | J35: 0 | O35: =SUM(C35:N35) -> 1264
B36: Nia | C36: 1011 | D36: 844 | E36: 1086 | F36: 640 | G36: 755 | H36: 738 | I36: 935 | J36: 949 | K36: 926 | L36: 575 | O36: =SUM(C36:N36) -> 8459
B37: Nina | C37: 834 | D37: 694 | E37: 1195 | F37: 633 | G37: 729 | H37: 952 | I37: 791 | J37: 948 | K37: 832 | L37: 884 | O37: =SUM(C37:N37) -> 8492
B38: Nita | C38: 810 | D38: 610 | E38: 809 | F38: 1167 | G38: 746 | H38: 1022 | I38: 809 | J38: 1230 | K38: 1002 | L38: 975 | O38: =SUM(C38:N38) -> 9180
B39: Ifa | C39: 4 | E39: 2 | F39: 1 | G39: 1 | H39: 2 | I39: 5 | J39: 6 | K39: 2 | O39: =SUM(C39:N39) -> 23
B40: Diana | F40: 1 | O40: =SUM(C40:N40) -> 1
B41: Grand | C41: =SUM(C34:C40) -> 4099 | D41: =SUM(D34:D40) -> 3273 | E41: =SUM(E34:E40) -> 4140 | F41: =SUM(F34:F40) -> 3167 | G41: =SUM(G34:G40) -> 2965 | H41: =SUM(H34:H40) -> 3610 | I41: =SUM(I34:I40) -> 3454 | J41: =SUM(J34:J40) -> 3984 | K41: =SUM(K34:K40) -> 3643 | L41: =SUM(L34:L38) -> 3192 | M41: =SUM(M34:M38) -> 0 | N41: =SUM(N34:N38) -> 0 | O41: =SUM(O34:O40) -> 35527
B42: % REVISI FAKTUR TERHADAP TOTAL FAKTUR
B43: Adm. SC | C43: Jan | D43: Feb | E43: Mar | F43: Apr | G43: Mei | H43: Jun | I43: Jul | J43: Agst | K43: Sept | L43: Okt | M43: Nov | N43: Des | O43: Total
B44: Fani | C44: =+C26/C34 -> 0.022082019 | D44: =+D26/D34 -> 0.010494753 | E44: =+E26/E34 -> 0.011450382 | F44: =+F26/F34 -> 0.017931034 | G44: =+G26/G34 -> 0.010899183 | H44: =+H26/H34 -> 0.0055803571 | I44: =+I26/I34 -> 0 | J44: =+J26/J34 -> 0.0047003525 | ... O44: =+O26/O34 -> 0.0080167736
B45: Naily | C45: =+C27/C35 -> 0.0024813896 | D45: =+D27/D35 -> 0.0021834061 | E45: 0 | F45: 0 | G45: 0 | H45: 0 | I45: =+I27/I35 -> #DIV/0! | J45: =+J27/J35 -> #DIV/0! | K45: =+K27/K35 -> #DIV/0! | L45: =+L27/L35 -> #DIV/0! | M45: =+M27/M35 -> #DIV/0! | N45: =+N27/N35 -> #DIV/0! | O45: =+O27/O35 -> 0.0023734177
B46: Nia | C46: =+C28/C36 -> 0.0029673591 | D46: =+D28/D36 -> 0.0023696682 | E46: =+E28/E36 -> 0.0046040516 | F46: =+F28/F36 -> 0 | G46: =+G28/G36 -> 0.0013245033 | H46: =+H28/H36 -> 0.0013550136 | I46: =+I28/I36 -> 0 | J46: =+J28/J36 -> 0 | ... O46: =+O28/O36 -> 0.0018914765
B47: Nina | C47: =+C29/C37 -> 0.0047961631 | D47: =+D29/D37 -> 0.0014409222 | E47: =+E29/E37 -> 0.0075313808 | F47: =+F29/F37 -> 0.0031595577 | G47: =+G29/G37 -> 0.0013717421 | H47: =+H29/H37 -> 0.0021008403 | I47: =+I29/I37 -> 0.0037926675 | J47: =+J29/J37 -> 0.0042194093 | ... O47: =+O29/O37 -> 0.0035327367
B48: Nita | C48: =+C30/C38 -> 0.0037037037 | D48: =+D30/D38 -> 0.0016393443 | E48: =+E30/E38 -> 0.0037082818 | F48: =+F30/F38 -> 0.0059982862 | G48: =+G30/G38 -> 0.0040214477 | H48: =+H30/H38 -> 0.0039138943 | I48: =+I30/I38 -> 0.0049443758 | J48: =+J30/J38 -> 0.0048780488 | ... O48: =+O30/O38 -> 0.0035947712
B49: Grand Total | C49: =+C31/C41 -> 0.0063430105 | D49: =+D31/D41 -> 0.0036663611 | E49: =+E31/E41 -> 0.0070048309 | F49: =+F31/F41 -> 0.0069466372 | G49: =+G31/G41 -> 0.0043844857 | H49: =+H31/H41 -> 0.0033240997 | I49: =+I31/I41 -> 0.0020266358 | J49: =+J31/J41 -> 0.0035140562 | ... O49: =+O31/O41 -> 0.0041376981

Sheet REVISI FAKTUR LOG
B1: REKAP REVISI FAKTUR (Logistik)
B2: 2023
A4: No | B4: Tanggal Revisi | C4: Tanggal Faktur | D4: No. Faktur | E4: Cust | F4: Keterangan | G4: Jumlah | H4: Keterangan | I4: Ket P. Bayu/P.Alif | J4: Driver | K4: Helper
B5: 44936 | C5: 44921 | D5: B22009209 | E5: Mitra Tani, UD/Gunawan | F5: batal | G5: 1545000 | H5: terlalu lama kirim

Sheet REKAP (Faktur)
B2: REVISI FAKTUR BERDASARKAN ALASANNYA
B3: Periode Januari - 30 Mei 2026
B4: Klasifikasi | C4: Januari | D4: Februari | E4: Maret | F4: April | G4: Mei | H4: Juni | I4: Juli | J4: Agustus | K4: September | L4: Oktober | M4: November | N4: Desember | O4: Total | Q4: 2025 | R4: Diff
B5: Permintaan Cust (Ganti Kemasan, Ganti Identitas Pajak, Habis Musim, Ganti Qty) | C5: =COUNTIFS('Data (Per Faktur)'!$A:$A,'REKAP (Faktur)'!C$4,'Data (Per Faktur)'!$K:$K,'REKAP (Faktur)'!$B5) -> 2 | D5: =COUNTIFS('Data (Per Faktur)'!$A:$A,'REKAP (Faktur)'!D$4,'Data (Per Faktur)'!$K:$K,'REKAP (Faktur)'!$B5) -> 4 | E5: =COUNTIFS('Data (Per Faktur)'!$A:$A,'REKAP (Faktur)'!E$4,'Data (Per Faktur)'!$K:$K,'REKAP (Faktur)'!$B5) -> 3 | F5: =COUNTIFS('Data (Per Faktur)'!$A:$A,'REKAP (Faktur)'!F$4,'Data (Per Faktur)'!$K:$K,'REKAP (Faktur)'!$B5) -> 5 | G5: =COUNTIFS('Data (Per Faktur)'!$A:$A,'REKAP (Faktur)'!G$4,'Data (Per Faktur)'!$K:$K,'REKAP (Faktur)'!$B5) -> 4 | H5: =COUNTIFS('Data (Per Faktur)'!$A:$A,'REKAP (Faktur)'!H$4,'Data (Per Faktur)'!$K:$K,'REKAP (Faktur)'!$B5) -> 0 | I5: =COUNTIFS('Data (Per Faktur)'!$A:$A,'REKAP (Faktur)'!I$4,'Data (Per Faktur)'!$K:$K,'REKAP (Faktur)'!$B5) -> 0 | J5: =COUNTIFS('Data (Per Faktur)'!$A:$A,'REKAP (Faktur)'!J$4,'Data (Per Faktur)'!$K:$K,'REKAP (Faktur)'!$B5) -> 0 | ... N5: =COUNTIFS('Data (Per Faktur)'!$A:$A,'REKAP (Faktur)'!N$4,'Data (Per Faktur)'!$K:$K,'REKAP (Faktur)'!$B5) -> 0 | O5: =SUM(C5:N5) -> 18 | Q5: 53 | R5: =+O5-Q5 -> -35
B6: Lain - Lain (Acc oleh Direktur, Hpp berubah) | C6: =COUNTIFS('Data (Per Faktur)'!$A:$A,'REKAP (Faktur)'!C$4,'Data (Per Faktur)'!$K:$K,'REKAP (Faktur)'!$B6) -> 1 | D6: =COUNTIFS('Data (Per Faktur)'!$A:$A,'REKAP (Faktur)'!D$4,'Data (Per Faktur)'!$K:$K,'REKAP (Faktur)'!$B6) -> 0 | E6: =COUNTIFS('Data (Per Faktur)'!$A:$A,'REKAP (Faktur)'!E$4,'Data (Per Faktur)'!$K:$K,'REKAP (Faktur)'!$B6) -> 0 | F6: =COUNTIFS('Data (Per Faktur)'!$A:$A,'REKAP (Faktur)'!F$4,'Data (Per Faktur)'!$K:$K,'REKAP (Faktur)'!$B6) -> 0 | G6: =COUNTIFS('Data (Per Faktur)'!$A:$A,'REKAP (Faktur)'!G$4,'Data (Per Faktur)'!$K:$K,'REKAP (Faktur)'!$B6) -> 0 | H6: =COUNTIFS('Data (Per Faktur)'!$A:$A,'REKAP (Faktur)'!H$4,'Data (Per Faktur)'!$K:$K,'REKAP (Faktur)'!$B6) -> 0 | I6: =COUNTIFS('Data (Per Faktur)'!$A:$A,'REKAP (Faktur)'!I$4,'Data (Per Faktur)'!$K:$K,'REKAP (Faktur)'!$B6) -> 0 | J6: =COUNTIFS('Data (Per Faktur)'!$A:$A,'REKAP (Faktur)'!J$4,'Data (Per Faktur)'!$K:$K,'REKAP (Faktur)'!$B6) -> 0 | ... N6: =COUNTIFS('Data (Per Faktur)'!$A:$A,'REKAP (Faktur)'!N$4,'Data (Per Faktur)'!$K:$K,'REKAP (Faktur)'!$B6) -> 0 | O6: =SUM(C6:N6) -> 1 | Q6: 10 | R6: =+O6-Q6 -> -9
B7: Pembatalan Order Oleh Kios | C7: =COUNTIFS('Data (Per Faktur)'!$A:$A,'REKAP (Faktur)'!C$4,'Data (Per Faktur)'!$K:$K,'REKAP (Faktur)'!$B7) -> 2 | D7: =COUNTIFS('Data (Per Faktur)'!$A:$A,'REKAP (Faktur)'!D$4,'Data (Per Faktur)'!$K:$K,'REKAP (Faktur)'!$B7) -> 3 | E7: =COUNTIFS('Data (Per Faktur)'!$A:$A,'REKAP (Faktur)'!E$4,'Data (Per Faktur)'!$K:$K,'REKAP (Faktur)'!$B7) -> 0 | F7: =COUNTIFS('Data (Per Faktur)'!$A:$A,'REKAP (Faktur)'!F$4,'Data (Per Faktur)'!$K:$K,'REKAP (Faktur)'!$B7) -> 2 | G7: =COUNTIFS('Data (Per Faktur)'!$A:$A,'REKAP (Faktur)'!G$4,'Data (Per Faktur)'!$K:$K,'REKAP (Faktur)'!$B7) -> 3 | H7: =COUNTIFS('Data (Per Faktur)'!$A:$A,'REKAP (Faktur)'!H$4,'Data (Per Faktur)'!$K:$K,'REKAP (Faktur)'!$B7) -> 0 | I7: =COUNTIFS('Data (Per Faktur)'!$A:$A,'REKAP (Faktur)'!I$4,'Data (Per Faktur)'!$K:$K,'REKAP (Faktur)'!$B7) -> 0 | J7: =COUNTIFS('Data (Per Faktur)'!$A:$A,'REKAP (Faktur)'!J$4,'Data (Per Faktur)'!$K:$K,'REKAP (Faktur)'!$B7) -> 0 | ... N7: =COUNTIFS('Data (Per Faktur)'!$A:$A,'REKAP (Faktur)'!N$4,'Data (Per Faktur)'!$K:$K,'REKAP (Faktur)'!$B7) -> 0 | O7: =SUM(C7:N7) -> 10 | Q7: 4 | R7: =+O7-Q7 -> 6
B8: Retur | C8: =COUNTIFS('Data (Per Faktur)'!$A:$A,'REKAP (Faktur)'!C$4,'Data (Per Faktur)'!$K:$K,'REKAP (Faktur)'!$B8) -> 6 | D8: =COUNTIFS('Data (Per Faktur)'!$A:$A,'REKAP (Faktur)'!D$4,'Data (Per Faktur)'!$K:$K,'REKAP (Faktur)'!$B8) -> 4 | E8: =COUNTIFS('Data (Per Faktur)'!$A:$A,'REKAP (Faktur)'!E$4,'Data (Per Faktur)'!$K:$K,'REKAP (Faktur)'!$B8) -> 3 | F8: =COUNTIFS('Data (Per Faktur)'!$A:$A,'REKAP (Faktur)'!F$4,'Data (Per Faktur)'!$K:$K,'REKAP (Faktur)'!$B8) -> 5 | G8: =COUNTIFS('Data (Per Faktur)'!$A:$A,'REKAP (Faktur)'!G$4,'Data (Per Faktur)'!$K:$K,'REKAP (Faktur)'!$B8) -> 7 | H8: =COUNTIFS('Data (Per Faktur)'!$A:$A,'REKAP (Faktur)'!H$4,'Data (Per Faktur)'!$K:$K,'REKAP (Faktur)'!$B8) -> 0 | I8: =COUNTIFS('Data (Per Faktur)'!$A:$A,'REKAP (Faktur)'!I$4,'Data (Per Faktur)'!$K:$K,'REKAP (Faktur)'!$B8) -> 0 | J8: =COUNTIFS('Data (Per Faktur)'!$A:$A,'REKAP (Faktur)'!J$4,'Data (Per Faktur)'!$K:$K,'REKAP (Faktur)'!$B8) -> 0 | ... N8: =COUNTIFS('Data (Per Faktur)'!$A:$A,'REKAP (Faktur)'!N$4,'Data (Per Faktur)'!$K:$K,'REKAP (Faktur)'!$B8) -> 0 | O8: =SUM(C8:N8) -> 25 | Q8: 16 | R8: =+O8-Q8 -> 9
B9: Kios Batal TRF/ Tidak Tepat Janji | C9: =COUNTIFS('Data (Per Faktur)'!$A:$A,'REKAP (Faktur)'!C$4,'Data (Per Faktur)'!$K:$K,'REKAP (Faktur)'!$B9) -> 2 | D9: =COUNTIFS('Data (Per Faktur)'!$A:$A,'REKAP (Faktur)'!D$4,'Data (Per Faktur)'!$K:$K,'REKAP (Faktur)'!$B9) -> 1 | E9: =COUNTIFS('Data (Per Faktur)'!$A:$A,'REKAP (Faktur)'!E$4,'Data (Per Faktur)'!$K:$K,'REKAP (Faktur)'!$B9) -> 0 | F9: =COUNTIFS('Data (Per Faktur)'!$A:$A,'REKAP (Faktur)'!F$4,'Data (Per Faktur)'!$K:$K,'REKAP (Faktur)'!$B9) -> 1 | G9: =COUNTIFS('Data (Per Faktur)'!$A:$A,'REKAP (Faktur)'!G$4,'Data (Per Faktur)'!$K:$K,'REKAP (Faktur)'!$B9) -> 1 | H9: =COUNTIFS('Data (Per Faktur)'!$A:$A,'REKAP (Faktur)'!H$4,'Data (Per Faktur)'!$K:$K,'REKAP (Faktur)'!$B9) -> 0 | I9: =COUNTIFS('Data (Per Faktur)'!$A:$A,'REKAP (Faktur)'!I$4,'Data (Per Faktur)'!$K:$K,'REKAP (Faktur)'!$B9) -> 0 | J9: =COUNTIFS('Data (Per Faktur)'!$A:$A,'REKAP (Faktur)'!J$4,'Data (Per Faktur)'!$K:$K,'REKAP (Faktur)'!$B9) -> 0 | ... N9: =COUNTIFS('Data (Per Faktur)'!$A:$A,'REKAP (Faktur)'!N$4,'Data (Per Faktur)'!$K:$K,'REKAP (Faktur)'!$B9) -> 0 | O9: =SUM(C9:N9) -> 5 | Q9: 0 | R9: =+O9-Q9 -> 5
B10: Salah Input Oleh Admin SC | C10: =COUNTIFS('Data (Per Faktur)'!$A:$A,'REKAP (Faktur)'!C$4,'Data (Per Faktur)'!$K:$K,'REKAP (Faktur)'!$B10) -> 0 | D10: =COUNTIFS('Data (Per Faktur)'!$A:$A,'REKAP (Faktur)'!D$4,'Data (Per Faktur)'!$K:$K,'REKAP (Faktur)'!$B10) -> 0 | E10: =COUNTIFS('Data (Per Faktur)'!$A:$A,'REKAP (Faktur)'!E$4,'Data (Per Faktur)'!$K:$K,'REKAP (Faktur)'!$B10) -> 4 | F10: =COUNTIFS('Data (Per Faktur)'!$A:$A,'REKAP (Faktur)'!F$4,'Data (Per Faktur)'!$K:$K,'REKAP (Faktur)'!$B10) -> 1 | G10: =COUNTIFS('Data (Per Faktur)'!$A:$A,'REKAP (Faktur)'!G$4,'Data (Per Faktur)'!$K:$K,'REKAP (Faktur)'!$B10) -> 0 | H10: =COUNTIFS('Data (Per Faktur)'!$A:$A,'REKAP (Faktur)'!H$4,'Data (Per Faktur)'!$K:$K,'REKAP (Faktur)'!$B10) -> 0 | I10: =COUNTIFS('Data (Per Faktur)'!$A:$A,'REKAP (Faktur)'!I$4,'Data (Per Faktur)'!$K:$K,'REKAP (Faktur)'!$B10) -> 0 | J10: =COUNTIFS('Data (Per Faktur)'!$A:$A,'REKAP (Faktur)'!J$4,'Data (Per Faktur)'!$K:$K,'REKAP (Faktur)'!$B10) -> 0 | ... N10: =COUNTIFS('Data (Per Faktur)'!$A:$A,'REKAP (Faktur)'!N$4,'Data (Per Faktur)'!$K:$K,'REKAP (Faktur)'!$B10) -> 0 | O10: =SUM(C10:N10) -> 5 | Q10: 9 | R10: =+O10-Q10 -> -4
B11: Salah harga Oleh SC | C11: =COUNTIFS('Data (Per Faktur)'!$A:$A,'REKAP (Faktur)'!C$4,'Data (Per Faktur)'!$K:$K,'REKAP (Faktur)'!$B11) -> 1 | D11: =COUNTIFS('Data (Per Faktur)'!$A:$A,'REKAP (Faktur)'!D$4,'Data (Per Faktur)'!$K:$K,'REKAP (Faktur)'!$B11) -> 0 | E11: =COUNTIFS('Data (Per Faktur)'!$A:$A,'REKAP (Faktur)'!E$4,'Data (Per Faktur)'!$K:$K,'REKAP (Faktur)'!$B11) -> 0 | F11: =COUNTIFS('Data (Per Faktur)'!$A:$A,'REKAP (Faktur)'!F$4,'Data (Per Faktur)'!$K:$K,'REKAP (Faktur)'!$B11) -> 1 | G11: =COUNTIFS('Data (Per Faktur)'!$A:$A,'REKAP (Faktur)'!G$4,'Data (Per Faktur)'!$K:$K,'REKAP (Faktur)'!$B11) -> 0 | H11: =COUNTIFS('Data (Per Faktur)'!$A:$A,'REKAP (Faktur)'!H$4,'Data (Per Faktur)'!$K:$K,'REKAP (Faktur)'!$B11) -> 0 | I11: =COUNTIFS('Data (Per Faktur)'!$A:$A,'REKAP (Faktur)'!I$4,'Data (Per Faktur)'!$K:$K,'REKAP (Faktur)'!$B11) -> 0 | J11: =COUNTIFS('Data (Per Faktur)'!$A:$A,'REKAP (Faktur)'!J$4,'Data (Per Faktur)'!$K:$K,'REKAP (Faktur)'!$B11) -> 0 | ... N11: =COUNTIFS('Data (Per Faktur)'!$A:$A,'REKAP (Faktur)'!N$4,'Data (Per Faktur)'!$K:$K,'REKAP (Faktur)'!$B11) -> 0 | O11: =SUM(C11:N11) -> 2 | Q11: 7 | R11: =+O11-Q11 -> -5
B12: Harga tidak cocok | C12: =COUNTIFS('Data (Per Faktur)'!$A:$A,'REKAP (Faktur)'!C$4,'Data (Per Faktur)'!$K:$K,'REKAP (Faktur)'!$B12) -> 0 | D12: =COUNTIFS('Data (Per Faktur)'!$A:$A,'REKAP (Faktur)'!D$4,'Data (Per Faktur)'!$K:$K,'REKAP (Faktur)'!$B12) -> 0 | E12: =COUNTIFS('Data (Per Faktur)'!$A:$A,'REKAP (Faktur)'!E$4,'Data (Per Faktur)'!$K:$K,'REKAP (Faktur)'!$B12) -> 0 | F12: =COUNTIFS('Data (Per Faktur)'!$A:$A,'REKAP (Faktur)'!F$4,'Data (Per Faktur)'!$K:$K,'REKAP (Faktur)'!$B12) -> 0 | G12: =COUNTIFS('Data (Per Faktur)'!$A:$A,'REKAP (Faktur)'!G$4,'Data (Per Faktur)'!$K:$K,'REKAP (Faktur)'!$B12) -> 0 | H12: =COUNTIFS('Data (Per Faktur)'!$A:$A,'REKAP (Faktur)'!H$4,'Data (Per Faktur)'!$K:$K,'REKAP (Faktur)'!$B12) -> 0 | I12: =COUNTIFS('Data (Per Faktur)'!$A:$A,'REKAP (Faktur)'!I$4,'Data (Per Faktur)'!$K:$K,'REKAP (Faktur)'!$B12) -> 0 | J12: =COUNTIFS('Data (Per Faktur)'!$A:$A,'REKAP (Faktur)'!J$4,'Data (Per Faktur)'!$K:$K,'REKAP (Faktur)'!$B12) -> 0 | ... N12: =COUNTIFS('Data (Per Faktur)'!$A:$A,'REKAP (Faktur)'!N$4,'Data (Per Faktur)'!$K:$K,'REKAP (Faktur)'!$B12) -> 0 | O12: =SUM(C12:N12) -> 0 | Q12: 0 | R12: =+O12-Q12 -> 0
B13: Salah SO oleh SC | C13: =COUNTIFS('Data (Per Faktur)'!$A:$A,'REKAP (Faktur)'!C$4,'Data (Per Faktur)'!$K:$K,'REKAP (Faktur)'!$B13) -> 2 | D13: =COUNTIFS('Data (Per Faktur)'!$A:$A,'REKAP (Faktur)'!D$4,'Data (Per Faktur)'!$K:$K,'REKAP (Faktur)'!$B13) -> 0 | E13: =COUNTIFS('Data (Per Faktur)'!$A:$A,'REKAP (Faktur)'!E$4,'Data (Per Faktur)'!$K:$K,'REKAP (Faktur)'!$B13) -> 0 | F13: =COUNTIFS('Data (Per Faktur)'!$A:$A,'REKAP (Faktur)'!F$4,'Data (Per Faktur)'!$K:$K,'REKAP (Faktur)'!$B13) -> 0 | G13: =COUNTIFS('Data (Per Faktur)'!$A:$A,'REKAP (Faktur)'!G$4,'Data (Per Faktur)'!$K:$K,'REKAP (Faktur)'!$B13) -> 0 | H13: =COUNTIFS('Data (Per Faktur)'!$A:$A,'REKAP (Faktur)'!H$4,'Data (Per Faktur)'!$K:$K,'REKAP (Faktur)'!$B13) -> 0 | I13: =COUNTIFS('Data (Per Faktur)'!$A:$A,'REKAP (Faktur)'!I$4,'Data (Per Faktur)'!$K:$K,'REKAP (Faktur)'!$B13) -> 0 | J13: =COUNTIFS('Data (Per Faktur)'!$A:$A,'REKAP (Faktur)'!J$4,'Data (Per Faktur)'!$K:$K,'REKAP (Faktur)'!$B13) -> 0 | ... N13: =COUNTIFS('Data (Per Faktur)'!$A:$A,'REKAP (Faktur)'!N$4,'Data (Per Faktur)'!$K:$K,'REKAP (Faktur)'!$B13) -> 0 | O13: =SUM(C13:N13) -> 2 | Q13: 9 | R13: =+O13-Q13 -> -7
B14: Pembagian Barang ke kios Lain | C14: =COUNTIFS('Data (Per Faktur)'!$A:$A,'REKAP (Faktur)'!C$4,'Data (Per Faktur)'!$K:$K,'REKAP (Faktur)'!$B14) -> 0 | D14: =COUNTIFS('Data (Per Faktur)'!$A:$A,'REKAP (Faktur)'!D$4,'Data (Per Faktur)'!$K:$K,'REKAP (Faktur)'!$B14) -> 0 | E14: =COUNTIFS('Data (Per Faktur)'!$A:$A,'REKAP (Faktur)'!E$4,'Data (Per Faktur)'!$K:$K,'REKAP (Faktur)'!$B14) -> 0 | F14: =COUNTIFS('Data (Per Faktur)'!$A:$A,'REKAP (Faktur)'!F$4,'Data (Per Faktur)'!$K:$K,'REKAP (Faktur)'!$B14) -> 1 | G14: =COUNTIFS('Data (Per Faktur)'!$A:$A,'REKAP (Faktur)'!G$4,'Data (Per Faktur)'!$K:$K,'REKAP (Faktur)'!$B14) -> 0 | H14: =COUNTIFS('Data (Per Faktur)'!$A:$A,'REKAP (Faktur)'!H$4,'Data (Per Faktur)'!$K:$K,'REKAP (Faktur)'!$B14) -> 0 | I14: =COUNTIFS('Data (Per Faktur)'!$A:$A,'REKAP (Faktur)'!I$4,'Data (Per Faktur)'!$K:$K,'REKAP (Faktur)'!$B14) -> 0 | J14: =COUNTIFS('Data (Per Faktur)'!$A:$A,'REKAP (Faktur)'!J$4,'Data (Per Faktur)'!$K:$K,'REKAP (Faktur)'!$B14) -> 0 | ... N14: =COUNTIFS('Data (Per Faktur)'!$A:$A,'REKAP (Faktur)'!N$4,'Data (Per Faktur)'!$K:$K,'REKAP (Faktur)'!$B14) -> 0 | O14: =SUM(C14:N14) -> 1 | Q14: 1 | R14: =+O14-Q14 -> 0
B15: Barang Rusak/Cacat/Bocor/Exp | C15: =COUNTIFS('Data (Per Faktur)'!$A:$A,'REKAP (Faktur)'!C$4,'Data (Per Faktur)'!$K:$K,'REKAP (Faktur)'!$B15) -> 0 | D15: =COUNTIFS('Data (Per Faktur)'!$A:$A,'REKAP (Faktur)'!D$4,'Data (Per Faktur)'!$K:$K,'REKAP (Faktur)'!$B15) -> 0 | E15: =COUNTIFS('Data (Per Faktur)'!$A:$A,'REKAP (Faktur)'!E$4,'Data (Per Faktur)'!$K:$K,'REKAP (Faktur)'!$B15) -> 0 | F15: =COUNTIFS('Data (Per Faktur)'!$A:$A,'REKAP (Faktur)'!F$4,'Data (Per Faktur)'!$K:$K,'REKAP (Faktur)'!$B15) -> 0 | G15: =COUNTIFS('Data (Per Faktur)'!$A:$A,'REKAP (Faktur)'!G$4,'Data (Per Faktur)'!$K:$K,'REKAP (Faktur)'!$B15) -> 0 | H15: =COUNTIFS('Data (Per Faktur)'!$A:$A,'REKAP (Faktur)'!H$4,'Data (Per Faktur)'!$K:$K,'REKAP (Faktur)'!$B15) -> 0 | I15: =COUNTIFS('Data (Per Faktur)'!$A:$A,'REKAP (Faktur)'!I$4,'Data (Per Faktur)'!$K:$K,'REKAP (Faktur)'!$B15) -> 0 | J15: =COUNTIFS('Data (Per Faktur)'!$A:$A,'REKAP (Faktur)'!J$4,'Data (Per Faktur)'!$K:$K,'REKAP (Faktur)'!$B15) -> 0 | ... N15: =COUNTIFS('Data (Per Faktur)'!$A:$A,'REKAP (Faktur)'!N$4,'Data (Per Faktur)'!$K:$K,'REKAP (Faktur)'!$B15) -> 0 | O15: =SUM(C15:N15) -> 0 | Q15: 1 | R15: =+O15-Q15 -> -1
B16: Toko Double Order | C16: =COUNTIFS('Data (Per Faktur)'!$A:$A,'REKAP (Faktur)'!C$4,'Data (Per Faktur)'!$K:$K,'REKAP (Faktur)'!$B16) -> 0 | D16: =COUNTIFS('Data (Per Faktur)'!$A:$A,'REKAP (Faktur)'!D$4,'Data (Per Faktur)'!$K:$K,'REKAP (Faktur)'!$B16) -> 0 | E16: =COUNTIFS('Data (Per Faktur)'!$A:$A,'REKAP (Faktur)'!E$4,'Data (Per Faktur)'!$K:$K,'REKAP (Faktur)'!$B16) -> 0 | F16: =COUNTIFS('Data (Per Faktur)'!$A:$A,'REKAP (Faktur)'!F$4,'Data (Per Faktur)'!$K:$K,'REKAP (Faktur)'!$B16) -> 0 | G16: =COUNTIFS('Data (Per Faktur)'!$A:$A,'REKAP (Faktur)'!G$4,'Data (Per Faktur)'!$K:$K,'REKAP (Faktur)'!$B16) -> 0 | H16: =COUNTIFS('Data (Per Faktur)'!$A:$A,'REKAP (Faktur)'!H$4,'Data (Per Faktur)'!$K:$K,'REKAP (Faktur)'!$B16) -> 0 | I16: =COUNTIFS('Data (Per Faktur)'!$A:$A,'REKAP (Faktur)'!I$4,'Data (Per Faktur)'!$K:$K,'REKAP (Faktur)'!$B16) -> 0 | J16: =COUNTIFS('Data (Per Faktur)'!$A:$A,'REKAP (Faktur)'!J$4,'Data (Per Faktur)'!$K:$K,'REKAP (Faktur)'!$B16) -> 0 | ... N16: =COUNTIFS('Data (Per Faktur)'!$A:$A,'REKAP (Faktur)'!N$4,'Data (Per Faktur)'!$K:$K,'REKAP (Faktur)'!$B16) -> 0 | O16: =SUM(C16:N16) -> 0 | Q16: 0 | R16: =+O16-Q16 -> 0
... B28: Ketinggalan Kiriman | C28: =COUNTIFS('Data (Per Faktur)'!$A:$A,'REKAP (Faktur)'!C$4,'Data (Per Faktur)'!$K:$K,'REKAP (Faktur)'!$B28) -> 0 | D28: =COUNTIFS('Data (Per Faktur)'!$A:$A,'REKAP (Faktur)'!D$4,'Data (Per Faktur)'!$K:$K,'REKAP (Faktur)'!$B28) -> 0 | E28: =COUNTIFS('Data (Per Faktur)'!$A:$A,'REKAP (Faktur)'!E$4,'Data (Per Faktur)'!$K:$K,'REKAP (Faktur)'!$B28) -> 0 | F28: =COUNTIFS('Data (Per Faktur)'!$A:$A,'REKAP (Faktur)'!F$4,'Data (Per Faktur)'!$K:$K,'REKAP (Faktur)'!$B28) -> 0 | G28: =COUNTIFS('Data (Per Faktur)'!$A:$A,'REKAP (Faktur)'!G$4,'Data (Per Faktur)'!$K:$K,'REKAP (Faktur)'!$B28) -> 0 | H28: =COUNTIFS('Data (Per Faktur)'!$A:$A,'REKAP (Faktur)'!H$4,'Data (Per Faktur)'!$K:$K,'REKAP (Faktur)'!$B28) -> 0 | I28: =COUNTIFS('Data (Per Faktur)'!$A:$A,'REKAP (Faktur)'!I$4,'Data (Per Faktur)'!$K:$K,'REKAP (Faktur)'!$B28) -> 0 | J28: =COUNTIFS('Data (Per Faktur)'!$A:$A,'REKAP (Faktur)'!J$4,'Data (Per Faktur)'!$K:$K,'REKAP (Faktur)'!$B28) -> 0 | ... N28: =COUNTIFS('Data (Per Faktur)'!$A:$A,'REKAP (Faktur)'!N$4,'Data (Per Faktur)'!$K:$K,'REKAP (Faktur)'!$B28) -> 0 | O28: =SUM(C28:N28) -> 0 | Q28: 0 | R28: =+O28-Q28 -> 0
B29: Salah Harga | C29: =COUNTIFS('Data (Per Faktur)'!$A:$A,'REKAP (Faktur)'!C$4,'Data (Per Faktur)'!$K:$K,'REKAP (Faktur)'!$B29) -> 0 | D29: =COUNTIFS('Data (Per Faktur)'!$A:$A,'REKAP (Faktur)'!D$4,'Data (Per Faktur)'!$K:$K,'REKAP (Faktur)'!$B29) -> 0 | E29: =COUNTIFS('Data (Per Faktur)'!$A:$A,'REKAP (Faktur)'!E$4,'Data (Per Faktur)'!$K:$K,'REKAP (Faktur)'!$B29) -> 0 | O29: =SUM(C29:N29) -> 0 | Q29: 0 | R29: =+O29-Q29 -> 0
B30: Grand Total | C30: =SUM(C5:C28) -> 16 | D30: =SUM(D5:D29) -> 12 | E30: =SUM(E5:E29) -> 13 | F30: =SUM(F5:F29) -> 16 | G30: =SUM(G5:G29) -> 18 | H30: =SUM(H5:H29) -> 0 | I30: =SUM(I5:I29) -> 0 | J30: =SUM(J5:J29) -> 0 | K30: =SUM(K5:K29) -> 0 | ... O30: =SUM(O5:O29) -> 75 | Q30: =SUM(Q5:Q29) -> 112 | R30: =+O30-Q30 -> -37
B31: TARGET : 200 Revisi Faktur sd Desember 2026, Per bulan maksimal 16 Revisi Faktur
A34: Salah harga Oleh SC | B34: REVISI FAKTUR BERDASARKAN SC (Salah Harga) | P34: Salah SO oleh SC | Q34: REVISI FAKTUR BERDASARKAN SC (Salah SO)
B35: Periode Januari 2025 | Q35: Periode Januari 2025
B36: SC | C36: Januari | D36: Februari | E36: Maret | F36: April | G36: Mei | H36: Juni | I36: Juli | J36: Agustus | K36: September | L36: Oktober | M36: November | N36: Desember | O36: Total | Q36: SC | R36: Januari | S36: Februari | T36: Maret | U36: April | V36: Mei | W36: Juni | X36: Juli | Y36: Agustus | Z36: September | AA36: Oktober | AB36: November | AC36: Desember | AD36: Total | AE36: %
B37: Arasyi | O37: =SUM(C37:N37) -> 0 | Q37: Arasyi | R37: =COUNTIFS('Data (Per Faktur)'!$A:$A,'REKAP (Faktur)'!R$36,'Data (Per Faktur)'!$E:$E,'REKAP (Faktur)'!$Q37,'Data (Per Faktur)'!$K:$K,'REKAP (Faktur)'!$P$34) -> 0 | S37: =COUNTIFS('Data (Per Faktur)'!$A:$A,'REKAP (Faktur)'!S$36,'Data (Per Faktur)'!$E:$E,'REKAP (Faktur)'!$Q37,'Data (Per Faktur)'!$K:$K,'REKAP (Faktur)'!$P$34) -> 0 | T37: =COUNTIFS('Data (Per Faktur)'!$A:$A,'REKAP (Faktur)'!T$36,'Data (Per Faktur)'!$E:$E,'REKAP (Faktur)'!$Q37,'Data (Per Faktur)'!$K:$K,'REKAP (Faktur)'!$P$34) -> 0 | U37: =COUNTIFS('Data (Per Faktur)'!$A:$A,'REKAP (Faktur)'!U$36,'Data (Per Faktur)'!$E:$E,'REKAP (Faktur)'!$Q37,'Data (Per Faktur)'!$K:$K,'REKAP (Faktur)'!$P$34) -> 0 | V37: =COUNTIFS('Data (Per Faktur)'!$A:$A,'REKAP (Faktur)'!V$36,'Data (Per Faktur)'!$E:$E,'REKAP (Faktur)'!$Q37,'Data (Per Faktur)'!$K:$K,'REKAP (Faktur)'!$P$34) -> 0 | W37: =COUNTIFS('Data (Per Faktur)'!$A:$A,'REKAP (Faktur)'!W$36,'Data (Per Faktur)'!$E:$E,'REKAP (Faktur)'!$Q37,'Data (Per Faktur)'!$K:$K,'REKAP (Faktur)'!$P$34) -> 0 | X37: =COUNTIFS('Data (Per Faktur)'!$A:$A,'REKAP (Faktur)'!X$36,'Data (Per Faktur)'!$E:$E,'REKAP (Faktur)'!$Q37,'Data (Per Faktur)'!$K:$K,'REKAP (Faktur)'!$P$34) -> 0 | Y37: =COUNTIFS('Data (Per Faktur)'!$A:$A,'REKAP (Faktur)'!Y$36,'Data (Per Faktur)'!$E:$E,'REKAP (Faktur)'!$Q37,'Data (Per Faktur)'!$K:$K,'REKAP (Faktur)'!$P$34) -> 0 | ... AC37: =COUNTIFS('Data (Per Faktur)'!$A:$A,'REKAP (Faktur)'!AC$36,'Data (Per Faktur)'!$E:$E,'REKAP (Faktur)'!$Q37,'Data (Per Faktur)'!$K:$K,'REKAP (Faktur)'!$P$34) -> 0 | AD37: =SUM(R37:AC37) -> 0 | AE37: =AD37/$AD$47 -> #DIV/0!
B38: Evi | O38: =SUM(C38:N38) -> 0 | Q38: Evi | R38: =COUNTIFS('Data (Per Faktur)'!$A:$A,'REKAP (Faktur)'!R$36,'Data (Per Faktur)'!$E:$E,'REKAP (Faktur)'!$Q38,'Data (Per Faktur)'!$K:$K,'REKAP (Faktur)'!$P$34) -> 0 | S38: =COUNTIFS('Data (Per Faktur)'!$A:$A,'REKAP (Faktur)'!S$36,'Data (Per Faktur)'!$E:$E,'REKAP (Faktur)'!$Q38,'Data (Per Faktur)'!$K:$K,'REKAP (Faktur)'!$P$34) -> 0 | T38: =COUNTIFS('Data (Per Faktur)'!$A:$A,'REKAP (Faktur)'!T$36,'Data (Per Faktur)'!$E:$E,'REKAP (Faktur)'!$Q38,'Data (Per Faktur)'!$K:$K,'REKAP (Faktur)'!$P$34) -> 0 | U38: =COUNTIFS('Data (Per Faktur)'!$A:$A,'REKAP (Faktur)'!U$36,'Data (Per Faktur)'!$E:$E,'REKAP (Faktur)'!$Q38,'Data (Per Faktur)'!$K:$K,'REKAP (Faktur)'!$P$34) -> 0 | V38: =COUNTIFS('Data (Per Faktur)'!$A:$A,'REKAP (Faktur)'!V$36,'Data (Per Faktur)'!$E:$E,'REKAP (Faktur)'!$Q38,'Data (Per Faktur)'!$K:$K,'REKAP (Faktur)'!$P$34) -> 0 | W38: =COUNTIFS('Data (Per Faktur)'!$A:$A,'REKAP (Faktur)'!W$36,'Data (Per Faktur)'!$E:$E,'REKAP (Faktur)'!$Q38,'Data (Per Faktur)'!$K:$K,'REKAP (Faktur)'!$P$34) -> 0 | X38: =COUNTIFS('Data (Per Faktur)'!$A:$A,'REKAP (Faktur)'!X$36,'Data (Per Faktur)'!$E:$E,'REKAP (Faktur)'!$Q38,'Data (Per Faktur)'!$K:$K,'REKAP (Faktur)'!$P$34) -> 0 | Y38: =COUNTIFS('Data (Per Faktur)'!$A:$A,'REKAP (Faktur)'!Y$36,'Data (Per Faktur)'!$E:$E,'REKAP (Faktur)'!$Q38,'Data (Per Faktur)'!$K:$K,'REKAP (Faktur)'!$P$34) -> 0 | ... AC38: =COUNTIFS('Data (Per Faktur)'!$A:$A,'REKAP (Faktur)'!AC$36,'Data (Per Faktur)'!$E:$E,'REKAP (Faktur)'!$Q38,'Data (Per Faktur)'!$K:$K,'REKAP (Faktur)'!$P$34) -> 0 | AD38: =SUM(R38:AC38) -> 0 | AE38: =AD38/$AD$47 -> #DIV/0!
B39: Faisal | O39: =SUM(C39:N39) -> 0 | Q39: Faisal | R39: =COUNTIFS('Data (Per Faktur)'!$A:$A,'REKAP (Faktur)'!R$36,'Data (Per Faktur)'!$E:$E,'REKAP (Faktur)'!$Q39,'Data (Per Faktur)'!$K:$K,'REKAP (Faktur)'!$P$34) -> 0 | S39: =COUNTIFS('Data (Per Faktur)'!$A:$A,'REKAP (Faktur)'!S$36,'Data (Per Faktur)'!$E:$E,'REKAP (Faktur)'!$Q39,'Data (Per Faktur)'!$K:$K,'REKAP (Faktur)'!$P$34) -> 0 | T39: =COUNTIFS('Data (Per Faktur)'!$A:$A,'REKAP (Faktur)'!T$36,'Data (Per Faktur)'!$E:$E,'REKAP (Faktur)'!$Q39,'Data (Per Faktur)'!$K:$K,'REKAP (Faktur)'!$P$34) -> 0 | U39: =COUNTIFS('Data (Per Faktur)'!$A:$A,'REKAP (Faktur)'!U$36,'Data (Per Faktur)'!$E:$E,'REKAP (Faktur)'!$Q39,'Data (Per Faktur)'!$K:$K,'REKAP (Faktur)'!$P$34) -> 0 | V39: =COUNTIFS('Data (Per Faktur)'!$A:$A,'REKAP (Faktur)'!V$36,'Data (Per Faktur)'!$E:$E,'REKAP (Faktur)'!$Q39,'Data (Per Faktur)'!$K:$K,'REKAP (Faktur)'!$P$34) -> 0 | W39: =COUNTIFS('Data (Per Faktur)'!$A:$A,'REKAP (Faktur)'!W$36,'Data (Per Faktur)'!$E:$E,'REKAP (Faktur)'!$Q39,'Data (Per Faktur)'!$K:$K,'REKAP (Faktur)'!$P$34) -> 0 | X39: =COUNTIFS('Data (Per Faktur)'!$A:$A,'REKAP (Faktur)'!X$36,'Data (Per Faktur)'!$E:$E,'REKAP (Faktur)'!$Q39,'Data (Per Faktur)'!$K:$K,'REKAP (Faktur)'!$P$34) -> 0 | Y39: =COUNTIFS('Data (Per Faktur)'!$A:$A,'REKAP (Faktur)'!Y$36,'Data (Per Faktur)'!$E:$E,'REKAP (Faktur)'!$Q39,'Data (Per Faktur)'!$K:$K,'REKAP (Faktur)'!$P$34) -> 0 | ... AC39: =COUNTIFS('Data (Per Faktur)'!$A:$A,'REKAP (Faktur)'!AC$36,'Data (Per Faktur)'!$E:$E,'REKAP (Faktur)'!$Q39,'Data (Per Faktur)'!$K:$K,'REKAP (Faktur)'!$P$34) -> 0 | AD39: =SUM(R39:AC39) -> 0 | AE39: =AD39/$AD$47 -> #DIV/0!
B40: Faris | O40: =SUM(C40:N40) -> 0 | Q40: Faris | R40: =COUNTIFS('Data (Per Faktur)'!$A:$A,'REKAP (Faktur)'!R$36,'Data (Per Faktur)'!$E:$E,'REKAP (Faktur)'!$Q40,'Data (Per Faktur)'!$K:$K,'REKAP (Faktur)'!$P$34) -> 0 | S40: =COUNTIFS('Data (Per Faktur)'!$A:$A,'REKAP (Faktur)'!S$36,'Data (Per Faktur)'!$E:$E,'REKAP (Faktur)'!$Q40,'Data (Per Faktur)'!$K:$K,'REKAP (Faktur)'!$P$34) -> 0 | T40: =COUNTIFS('Data (Per Faktur)'!$A:$A,'REKAP (Faktur)'!T$36,'Data (Per Faktur)'!$E:$E,'REKAP (Faktur)'!$Q40,'Data (Per Faktur)'!$K:$K,'REKAP (Faktur)'!$P$34) -> 0 | U40: =COUNTIFS('Data (Per Faktur)'!$A:$A,'REKAP (Faktur)'!U$36,'Data (Per Faktur)'!$E:$E,'REKAP (Faktur)'!$Q40,'Data (Per Faktur)'!$K:$K,'REKAP (Faktur)'!$P$34) -> 0 | V40: =COUNTIFS('Data (Per Faktur)'!$A:$A,'REKAP (Faktur)'!V$36,'Data (Per Faktur)'!$E:$E,'REKAP (Faktur)'!$Q40,'Data (Per Faktur)'!$K:$K,'REKAP (Faktur)'!$P$34) -> 0 | W40: =COUNTIFS('Data (Per Faktur)'!$A:$A,'REKAP (Faktur)'!W$36,'Data (Per Faktur)'!$E:$E,'REKAP (Faktur)'!$Q40,'Data (Per Faktur)'!$K:$K,'REKAP (Faktur)'!$P$34) -> 0 | X40: =COUNTIFS('Data (Per Faktur)'!$A:$A,'REKAP (Faktur)'!X$36,'Data (Per Faktur)'!$E:$E,'REKAP (Faktur)'!$Q40,'Data (Per Faktur)'!$K:$K,'REKAP (Faktur)'!$P$34) -> 0 | Y40: =COUNTIFS('Data (Per Faktur)'!$A:$A,'REKAP (Faktur)'!Y$36,'Data (Per Faktur)'!$E:$E,'REKAP (Faktur)'!$Q40,'Data (Per Faktur)'!$K:$K,'REKAP (Faktur)'!$P$34) -> 0 | ... AC40: =COUNTIFS('Data (Per Faktur)'!$A:$A,'REKAP (Faktur)'!AC$36,'Data (Per Faktur)'!$E:$E,'REKAP (Faktur)'!$Q40,'Data (Per Faktur)'!$K:$K,'REKAP (Faktur)'!$P$34) -> 0 | AD40: =SUM(R40:AC40) -> 0
B41: Hendra | O41: =SUM(C41:N41) -> 0 | Q41: Hendra | R41: =COUNTIFS('Data (Per Faktur)'!$A:$A,'REKAP (Faktur)'!R$36,'Data (Per Faktur)'!$E:$E,'REKAP (Faktur)'!$Q41,'Data (Per Faktur)'!$K:$K,'REKAP (Faktur)'!$P$34) -> 0 | S41: =COUNTIFS('Data (Per Faktur)'!$A:$A,'REKAP (Faktur)'!S$36,'Data (Per Faktur)'!$E:$E,'REKAP (Faktur)'!$Q41,'Data (Per Faktur)'!$K:$K,'REKAP (Faktur)'!$P$34) -> 0 | T41: =COUNTIFS('Data (Per Faktur)'!$A:$A,'REKAP (Faktur)'!T$36,'Data (Per Faktur)'!$E:$E,'REKAP (Faktur)'!$Q41,'Data (Per Faktur)'!$K:$K,'REKAP (Faktur)'!$P$34) -> 0 | U41: =COUNTIFS('Data (Per Faktur)'!$A:$A,'REKAP (Faktur)'!U$36,'Data (Per Faktur)'!$E:$E,'REKAP (Faktur)'!$Q41,'Data (Per Faktur)'!$K:$K,'REKAP (Faktur)'!$P$34) -> 0 | V41: =COUNTIFS('Data (Per Faktur)'!$A:$A,'REKAP (Faktur)'!V$36,'Data (Per Faktur)'!$E:$E,'REKAP (Faktur)'!$Q41,'Data (Per Faktur)'!$K:$K,'REKAP (Faktur)'!$P$34) -> 0 | W41: =COUNTIFS('Data (Per Faktur)'!$A:$A,'REKAP (Faktur)'!W$36,'Data (Per Faktur)'!$E:$E,'REKAP (Faktur)'!$Q41,'Data (Per Faktur)'!$K:$K,'REKAP (Faktur)'!$P$34) -> 0 | X41: =COUNTIFS('Data (Per Faktur)'!$A:$A,'REKAP (Faktur)'!X$36,'Data (Per Faktur)'!$E:$E,'REKAP (Faktur)'!$Q41,'Data (Per Faktur)'!$K:$K,'REKAP (Faktur)'!$P$34) -> 0 | Y41: =COUNTIFS('Data (Per Faktur)'!$A:$A,'REKAP (Faktur)'!Y$36,'Data (Per Faktur)'!$E:$E,'REKAP (Faktur)'!$Q41,'Data (Per Faktur)'!$K:$K,'REKAP (Faktur)'!$P$34) -> 0 | ... AC41: =COUNTIFS('Data (Per Faktur)'!$A:$A,'REKAP (Faktur)'!AC$36,'Data (Per Faktur)'!$E:$E,'REKAP (Faktur)'!$Q41,'Data (Per Faktur)'!$K:$K,'REKAP (Faktur)'!$P$34) -> 0 | AD41: =SUM(R41:AC41) -> 0
B42: Reni | O42: =SUM(C42:N42) -> 0 | Q42: Reni | AD42: =SUM(R42:AC42) -> 0
B43: Riyan | O43: =SUM(C43:N43) -> 0 | Q43: Riyan | R43: =COUNTIFS('Data (Per Faktur)'!$A:$A,'REKAP (Faktur)'!R$36,'Data (Per Faktur)'!$E:$E,'REKAP (Faktur)'!$Q43,'Data (Per Faktur)'!$K:$K,'REKAP (Faktur)'!$P$34) -> 0 | S43: =COUNTIFS('Data (Per Faktur)'!$A:$A,'REKAP (Faktur)'!S$36,'Data (Per Faktur)'!$E:$E,'REKAP (Faktur)'!$Q43,'Data (Per Faktur)'!$K:$K,'REKAP (Faktur)'!$P$34) -> 0 | T43: =COUNTIFS('Data (Per Faktur)'!$A:$A,'REKAP (Faktur)'!T$36,'Data (Per Faktur)'!$E:$E,'REKAP (Faktur)'!$Q43,'Data (Per Faktur)'!$K:$K,'REKAP (Faktur)'!$P$34) -> 0 | U43: =COUNTIFS('Data (Per Faktur)'!$A:$A,'REKAP (Faktur)'!U$36,'Data (Per Faktur)'!$E:$E,'REKAP (Faktur)'!$Q43,'Data (Per Faktur)'!$K:$K,'REKAP (Faktur)'!$P$34) -> 0 | V43: =COUNTIFS('Data (Per Faktur)'!$A:$A,'REKAP (Faktur)'!V$36,'Data (Per Faktur)'!$E:$E,'REKAP (Faktur)'!$Q43,'Data (Per Faktur)'!$K:$K,'REKAP (Faktur)'!$P$34) -> 0 | W43: =COUNTIFS('Data (Per Faktur)'!$A:$A,'REKAP (Faktur)'!W$36,'Data (Per Faktur)'!$E:$E,'REKAP (Faktur)'!$Q43,'Data (Per Faktur)'!$K:$K,'REKAP (Faktur)'!$P$34) -> 0 | X43: =COUNTIFS('Data (Per Faktur)'!$A:$A,'REKAP (Faktur)'!X$36,'Data (Per Faktur)'!$E:$E,'REKAP (Faktur)'!$Q43,'Data (Per Faktur)'!$K:$K,'REKAP (Faktur)'!$P$34) -> 0 | Y43: =COUNTIFS('Data (Per Faktur)'!$A:$A,'REKAP (Faktur)'!Y$36,'Data (Per Faktur)'!$E:$E,'REKAP (Faktur)'!$Q43,'Data (Per Faktur)'!$K:$K,'REKAP (Faktur)'!$P$34) -> 0 | ... AC43: =COUNTIFS('Data (Per Faktur)'!$A:$A,'REKAP (Faktur)'!AC$36,'Data (Per Faktur)'!$E:$E,'REKAP (Faktur)'!$Q43,'Data (Per Faktur)'!$K:$K,'REKAP (Faktur)'!$P$34) -> 0 | AD43: =SUM(R43:AC43) -> 0 | AE43: =AD43/$AD$47 -> #DIV/0!
B44: Umi | O44: =SUM(C44:N44) -> 0 | Q44: Umi | R44: =COUNTIFS('Data (Per Faktur)'!$A:$A,'REKAP (Faktur)'!R$36,'Data (Per Faktur)'!$E:$E,'REKAP (Faktur)'!$Q44,'Data (Per Faktur)'!$K:$K,'REKAP (Faktur)'!$P$34) -> 0 | S44: =COUNTIFS('Data (Per Faktur)'!$A:$A,'REKAP (Faktur)'!S$36,'Data (Per Faktur)'!$E:$E,'REKAP (Faktur)'!$Q44,'Data (Per Faktur)'!$K:$K,'REKAP (Faktur)'!$P$34) -> 0 | T44: =COUNTIFS('Data (Per Faktur)'!$A:$A,'REKAP (Faktur)'!T$36,'Data (Per Faktur)'!$E:$E,'REKAP (Faktur)'!$Q44,'Data (Per Faktur)'!$K:$K,'REKAP (Faktur)'!$P$34) -> 0 | U44: =COUNTIFS('Data (Per Faktur)'!$A:$A,'REKAP (Faktur)'!U$36,'Data (Per Faktur)'!$E:$E,'REKAP (Faktur)'!$Q44,'Data (Per Faktur)'!$K:$K,'REKAP (Faktur)'!$P$34) -> 0 | V44: =COUNTIFS('Data (Per Faktur)'!$A:$A,'REKAP (Faktur)'!V$36,'Data (Per Faktur)'!$E:$E,'REKAP (Faktur)'!$Q44,'Data (Per Faktur)'!$K:$K,'REKAP (Faktur)'!$P$34) -> 0 | W44: =COUNTIFS('Data (Per Faktur)'!$A:$A,'REKAP (Faktur)'!W$36,'Data (Per Faktur)'!$E:$E,'REKAP (Faktur)'!$Q44,'Data (Per Faktur)'!$K:$K,'REKAP (Faktur)'!$P$34) -> 0 | X44: =COUNTIFS('Data (Per Faktur)'!$A:$A,'REKAP (Faktur)'!X$36,'Data (Per Faktur)'!$E:$E,'REKAP (Faktur)'!$Q44,'Data (Per Faktur)'!$K:$K,'REKAP (Faktur)'!$P$34) -> 0 | Y44: =COUNTIFS('Data (Per Faktur)'!$A:$A,'REKAP (Faktur)'!Y$36,'Data (Per Faktur)'!$E:$E,'REKAP (Faktur)'!$Q44,'Data (Per Faktur)'!$K:$K,'REKAP (Faktur)'!$P$34) -> 0 | ... AC44: =COUNTIFS('Data (Per Faktur)'!$A:$A,'REKAP (Faktur)'!AC$36,'Data (Per Faktur)'!$E:$E,'REKAP (Faktur)'!$Q44,'Data (Per Faktur)'!$K:$K,'REKAP (Faktur)'!$P$34) -> 0 | AD44: =SUM(R44:AC44) -> 0 | AE44: =AD44/$AD$47 -> #DIV/0!
B45: Yuyun | O45: =SUM(C45:N45) -> 0 | Q45: Yuyun | R45: =COUNTIFS('Data (Per Faktur)'!$A:$A,'REKAP (Faktur)'!R$36,'Data (Per Faktur)'!$E:$E,'REKAP (Faktur)'!$Q45,'Data (Per Faktur)'!$K:$K,'REKAP (Faktur)'!$P$34) -> 0 | S45: =COUNTIFS('Data (Per Faktur)'!$A:$A,'REKAP (Faktur)'!S$36,'Data (Per Faktur)'!$E:$E,'REKAP (Faktur)'!$Q45,'Data (Per Faktur)'!$K:$K,'REKAP (Faktur)'!$P$34) -> 0 | T45: =COUNTIFS('Data (Per Faktur)'!$A:$A,'REKAP (Faktur)'!T$36,'Data (Per Faktur)'!$E:$E,'REKAP (Faktur)'!$Q45,'Data (Per Faktur)'!$K:$K,'REKAP (Faktur)'!$P$34) -> 0 | U45: =COUNTIFS('Data (Per Faktur)'!$A:$A,'REKAP (Faktur)'!U$36,'Data (Per Faktur)'!$E:$E,'REKAP (Faktur)'!$Q45,'Data (Per Faktur)'!$K:$K,'REKAP (Faktur)'!$P$34) -> 0 | V45: =COUNTIFS('Data (Per Faktur)'!$A:$A,'REKAP (Faktur)'!V$36,'Data (Per Faktur)'!$E:$E,'REKAP (Faktur)'!$Q45,'Data (Per Faktur)'!$K:$K,'REKAP (Faktur)'!$P$34) -> 0 | W45: =COUNTIFS('Data (Per Faktur)'!$A:$A,'REKAP (Faktur)'!W$36,'Data (Per Faktur)'!$E:$E,'REKAP (Faktur)'!$Q45,'Data (Per Faktur)'!$K:$K,'REKAP (Faktur)'!$P$34) -> 0 | X45: =COUNTIFS('Data (Per Faktur)'!$A:$A,'REKAP (Faktur)'!X$36,'Data (Per Faktur)'!$E:$E,'REKAP (Faktur)'!$Q45,'Data (Per Faktur)'!$K:$K,'REKAP (Faktur)'!$P$34) -> 0 | Y45: =COUNTIFS('Data (Per Faktur)'!$A:$A,'REKAP (Faktur)'!Y$36,'Data (Per Faktur)'!$E:$E,'REKAP (Faktur)'!$Q45,'Data (Per Faktur)'!$K:$K,'REKAP (Faktur)'!$P$34) -> 0 | ... AC45: =COUNTIFS('Data (Per Faktur)'!$A:$A,'REKAP (Faktur)'!AC$36,'Data (Per Faktur)'!$E:$E,'REKAP (Faktur)'!$Q45,'Data (Per Faktur)'!$K:$K,'REKAP (Faktur)'!$P$34) -> 0 | AD45: =SUM(R45:AC45) -> 0 | AE45: =AD45/$AD$47 -> #DIV/0!
B46: Zakia | O46: =SUM(C46:N46) -> 0 | Q46: Zakia | R46: =COUNTIFS('Data (Per Faktur)'!$A:$A,'REKAP (Faktur)'!R$36,'Data (Per Faktur)'!$E:$E,'REKAP (Faktur)'!$Q46,'Data (Per Faktur)'!$K:$K,'REKAP (Faktur)'!$P$34) -> 0 | S46: =COUNTIFS('Data (Per Faktur)'!$A:$A,'REKAP (Faktur)'!S$36,'Data (Per Faktur)'!$E:$E,'REKAP (Faktur)'!$Q46,'Data (Per Faktur)'!$K:$K,'REKAP (Faktur)'!$P$34) -> 0 | T46: =COUNTIFS('Data (Per Faktur)'!$A:$A,'REKAP (Faktur)'!T$36,'Data (Per Faktur)'!$E:$E,'REKAP (Faktur)'!$Q46,'Data (Per Faktur)'!$K:$K,'REKAP (Faktur)'!$P$34) -> 0 | U46: =COUNTIFS('Data (Per Faktur)'!$A:$A,'REKAP (Faktur)'!U$36,'Data (Per Faktur)'!$E:$E,'REKAP (Faktur)'!$Q46,'Data (Per Faktur)'!$K:$K,'REKAP (Faktur)'!$P$34) -> 0 | V46: =COUNTIFS('Data (Per Faktur)'!$A:$A,'REKAP (Faktur)'!V$36,'Data (Per Faktur)'!$E:$E,'REKAP (Faktur)'!$Q46,'Data (Per Faktur)'!$K:$K,'REKAP (Faktur)'!$P$34) -> 0 | W46: =COUNTIFS('Data (Per Faktur)'!$A:$A,'REKAP (Faktur)'!W$36,'Data (Per Faktur)'!$E:$E,'REKAP (Faktur)'!$Q46,'Data (Per Faktur)'!$K:$K,'REKAP (Faktur)'!$P$34) -> 0 | X46: =COUNTIFS('Data (Per Faktur)'!$A:$A,'REKAP (Faktur)'!X$36,'Data (Per Faktur)'!$E:$E,'REKAP (Faktur)'!$Q46,'Data (Per Faktur)'!$K:$K,'REKAP (Faktur)'!$P$34) -> 0 | Y46: =COUNTIFS('Data (Per Faktur)'!$A:$A,'REKAP (Faktur)'!Y$36,'Data (Per Faktur)'!$E:$E,'REKAP (Faktur)'!$Q46,'Data (Per Faktur)'!$K:$K,'REKAP (Faktur)'!$P$34) -> 0 | ... AC46: =COUNTIFS('Data (Per Faktur)'!$A:$A,'REKAP (Faktur)'!AC$36,'Data (Per Faktur)'!$E:$E,'REKAP (Faktur)'!$Q46,'Data (Per Faktur)'!$K:$K,'REKAP (Faktur)'!$P$34) -> 0 | AD46: =SUM(R46:AC46) -> 0 | AE46: =AD46/$AD$47 -> #DIV/0!
B47: TOTAL | C47: =SUM(C37:C46) -> 0 | D47: =SUM(D37:D46) -> 0 | E47: =SUM(E37:E46) -> 0 | F47: =SUM(F37:F46) -> 0 | G47: =SUM(G37:G46) -> 0 | H47: =SUM(H37:H46) -> 0 | I47: =SUM(I37:I46) -> 0 | J47: =SUM(J37:J46) -> 0 | ... O47: =SUM(O37:O46) -> 0 | Q47: TOTAL | R47: =SUM(R37:R46) -> 0 | S47: =SUM(S37:S46) -> 0 | T47: =SUM(T37:T46) -> 0 | U47: =SUM(U37:U46) -> 0 | V47: =SUM(V37:V46) -> 0 | W47: =SUM(W37:W46) -> 0 | X47: =SUM(X37:X46) -> 0 | Y47: =SUM(Y37:Y46) -> 0 | ... AE47: =SUM(AE37:AE46) -> #DIV/0!
B49: JUMLAH SO (Per Faktur) | Q49: JUMLAH SO (Per Faktur)
B50: SC | C50: Jan | D50: Feb | E50: Mar | F50: Apr | G50: Mei | H50: Jun | I50: Jul | J50: Agst | K50: Sept | L50: Okt | M50: Nov | N50: Des | O50: Total | Q50: SC | R50: Jan | S50: Feb | T50: Mar | U50: Apr | V50: Mei | W50: Jun | X50: Jul | Y50: Agst | Z50: Sept | AA50: Okt | AB50: Nov | AC50: Des | AD50: Total
B51: Arasyi | O51: =SUM(C51:N51) -> 0 | Q51: Arasyi | AD51: =SUM(R51:AC51) -> 0
B52: Evi | O52: =SUM(C52:N52) -> 0 | Q52: Evi | AD52: =SUM(R52:AC52) -> 0
B53: Faisal | O53: =SUM(C53:N53) -> 0 | Q53: Faisal | AD53: =SUM(R53:AC53) -> 0
B54: Faris | O54: =SUM(C54:N54) -> 0 | Q54: Faris | AD54: =SUM(R54:AC54) -> 0
B55: Hendra | O55: =SUM(C55:N55) -> 0 | Q55: Hendra | AD55: =SUM(R55:AC55) -> 0
B56: Reni | O56: =SUM(C56:N56) -> 0 | Q56: Reni | AD56: =SUM(R56:AC56) -> 0
B57: Riyan | O57: =SUM(C57:N57) -> 0 | Q57: Riyan | AD57: =SUM(R57:AC57) -> 0
B58: Umi | O58: =SUM(C58:N58) -> 0 | Q58: Umi | AD58: =SUM(R58:AC58) -> 0
B59: Yuyun | O59: =SUM(C59:N59) -> 0 | Q59: Yuyun | AD59: =SUM(R59:AC59) -> 0
B60: Zakia | O60: =SUM(C60:N60) -> 0 | Q60: Zakia | AD60: =SUM(R60:AC60) -> 0
B61: Others | O61: =SUM(C61:N61) -> 0 | Q61: Others | AD61: =SUM(R61:AC61) -> 0
B62: Supriyanto/nadia | O62: =SUM(C62:N62) -> 0 | Q62: Supriyanto/nadia | AD62: =SUM(R62:AC62) -> 0
... B65: Anisa | O65: =SUM(C65:N65) -> 0 | Q65: Anisa | AD65: =SUM(R65:AC65) -> 0
B66: Ibnu | Q66: Ibnu
B67: Nugroho | O67: =SUM(C67:N67) -> 0 | Q67: Nugroho | AD67: =SUM(R67:AC67) -> 0
B68: TOTAL | C68: =SUM(C51:C67) -> 0 | D68: =SUM(D51:D67) -> 0 | E68: =SUM(E51:E67) -> 0 | F68: =SUM(F51:F67) -> 0 | G68: =SUM(G51:G67) -> 0 | H68: =SUM(H51:H67) -> 0 | I68: =SUM(I51:I67) -> 0 | J68: =SUM(J51:J67) -> 0 | ... O68: =SUM(O51:O67) -> 0 | Q68: TOTAL | R68: =SUM(R51:R67) -> 0 | S68: =SUM(S51:S67) -> 0 | T68: =SUM(T51:T67) -> 0 | U68: =SUM(U51:U67) -> 0 | V68: =SUM(V51:V67) -> 0 | W68: =SUM(W51:W67) -> 0 | X68: =SUM(X51:X67) -> 0 | Y68: =SUM(Y51:Y67) -> 0 | ... AD68: =SUM(AD51:AD67) -> 0
B70: % REVISI FAKTUR TERHADAP TOTAL FAKTUR | Q70: % REVISI FAKTUR TERHADAP TOTAL FAKTUR
B71: SC | C71: Jan | D71: Feb | E71: Mar | F71: Apr | G71: Mei | H71: Jun | I71: Jul | J71: Agst | K71: Sept | L71: Okt | M71: Nov | N71: Des | O71: Total | Q71: SC | R71: Jan | S71: Feb | T71: Mar | U71: Apr | V71: Mei | W71: Jun | X71: Jul | Y71: Agst | Z71: Sept | AA71: Okt | AB71: Nov | AC71: Des | AD71: Total
B72: Arasyi | C72: =C37/C51 -> #DIV/0! | D72: =D37/D51 -> #DIV/0! | E72: =E37/E51 -> #DIV/0! | F72: =F37/F51 -> #DIV/0! | G72: =G37/G51 -> #DIV/0! | H72: =H37/H51 -> #DIV/0! | I72: =I37/I51 -> #DIV/0! | J72: =J37/J51 -> #DIV/0! | K72: =K37/K51 -> #DIV/0! | O72: =O37/O51 -> #DIV/0! | Q72: Arasyi | R72: =R37/R51 -> #DIV/0! | S72: =S37/S51 -> #DIV/0! | T72: =T37/T51 -> #DIV/0! | U72: =U37/U51 -> #DIV/0! | V72: =V37/V51 -> #DIV/0! | W72: =W37/W51 -> #DIV/0! | X72: =X37/X51 -> #DIV/0! | Y72: =Y37/Y51 -> #DIV/0! | Z72: =Z37/Z51 -> #DIV/0! | AD72: =AD37/AD51 -> #DIV/0!
B73: Evi | C73: =C38/C52 -> #DIV/0! | D73: =D38/D52 -> #DIV/0! | E73: =E38/E52 -> #DIV/0! | F73: =F38/F52 -> #DIV/0! | G73: =G38/G52 -> #DIV/0! | H73: =H38/H52 -> #DIV/0! | I73: =I38/I52 -> #DIV/0! | J73: =J38/J52 -> #DIV/0! | K73: =K38/K52 -> #DIV/0! | O73: =O38/O52 -> #DIV/0! | Q73: Evi | R73: =R38/R52 -> #DIV/0! | S73: =S38/S51 -> #DIV/0! | T73: =T38/T51 -> #DIV/0! | U73: =U38/U51 -> #DIV/0! | V73: =V38/V51 -> #DIV/0! | W73: =W38/W51 -> #DIV/0! | X73: =X38/X51 -> #DIV/0! | Y73: =Y38/Y51 -> #DIV/0! | Z73: =Z38/Z51 -> #DIV/0! | ... AC73: =AC38/AC51 -> #DIV/0! | AD73: =AD38/AD52 -> #DIV/0!
B74: Faisal | C74: =C39/C53 -> #DIV/0! | D74: =D39/D53 -> #DIV/0! | E74: =E39/E53 -> #DIV/0! | F74: =F39/F53 -> #DIV/0! | G74: =G39/G53 -> #DIV/0! | H74: =H39/H53 -> #DIV/0! | I74: =I39/I53 -> #DIV/0! | J74: =J39/J53 -> #DIV/0! | K74: =K39/K53 -> #DIV/0! | O74: =O39/O53 -> #DIV/0! | Q74: Faisal | R74: =R39/R53 -> #DIV/0! | S74: 0 | T74: =T39/T52 -> #DIV/0! | U74: =U39/U52 -> #DIV/0! | V74: =V39/V52 -> #DIV/0! | W74: =W39/W52 -> #DIV/0! | X74: =X39/X52 -> #DIV/0! | Y74: 0 | Z74: =Z39/Z52 -> #DIV/0! | AA74: =AA39/AA52 -> #DIV/0! | AB74: =AB39/AB52 -> #DIV/0! | AC74: =AC39/AC52 -> #DIV/0! | AD74: =AD39/AD53 -> #DIV/0!
B75: Faris | C75: =C40/C54 -> #DIV/0! | D75: =D40/D54 -> #DIV/0! | E75: =E40/E54 -> #DIV/0! | F75: =F40/F54 -> #DIV/0! | G75: =G40/G54 -> #DIV/0! | H75: =H40/H54 -> #DIV/0! | I75: =I40/I54 -> #DIV/0! | J75: =J40/J54 -> #DIV/0! | K75: =K40/K54 -> #DIV/0! | O75: =O40/O54 -> #DIV/0! | Q75: Faris | R75: =R40/R54 -> #DIV/0! | S75: 0 | T75: =T40/T53 -> #DIV/0! | U75: =U40/U53 -> #DIV/0! | V75: =V40/V53 -> #DIV/0! | W75: =W40/W53 -> #DIV/0! | X75: =X40/X53 -> #DIV/0! | Y75: 0 | Z75: =Z40/Z53 -> #DIV/0! | AA75: =AA40/AA53 -> #DIV/0! | AB75: =AB40/AB53 -> #DIV/0! | AC75: =AC40/AC53 -> #DIV/0! | AD75: =AD40/AD54 -> #DIV/0!
B76: Hendra | C76: =C41/C55 -> #DIV/0! | D76: =D41/D55 -> #DIV/0! | E76: =E41/E55 -> #DIV/0! | F76: =F41/F55 -> #DIV/0! | G76: =G41/G55 -> #DIV/0! | H76: =H41/H55 -> #DIV/0! | I76: =I41/I55 -> #DIV/0! | J76: =J41/J55 -> #DIV/0! | K76: =K41/K55 -> #DIV/0! | O76: =O41/O55 -> #DIV/0! | Q76: Hendra | R76: =R41/R55 -> #DIV/0! | S76: 0 | T76: 0 | U76: 0 | V76: 0 | W76: 0 | X76: 0 | Y76: 0 | Z76: 0 | AA76: =AA41/AA53 -> #DIV/0! | AB76: =AB41/AB53 -> #DIV/0! | AD76: =AD41/AD55 -> #DIV/0!
B77: Riyan | C77: =C43/C57 -> #DIV/0! | D77: =D43/D57 -> #DIV/0! | E77: =E43/E57 -> #DIV/0! | F77: =F43/F57 -> #DIV/0! | G77: =G43/G57 -> #DIV/0! | H77: =H43/H57 -> #DIV/0! | I77: =I43/I57 -> #DIV/0! | J77: =J43/J57 -> #DIV/0! | K77: =K43/K57 -> #DIV/0! | O77: =O43/O57 -> #DIV/0! | Q77: Riyan | R77: =R43/R57 -> #DIV/0! | S77: =S43/S55 -> #DIV/0! | T77: =T43/T55 -> #DIV/0! | U77: =U43/U55 -> #DIV/0! | V77: =V43/V55 -> #DIV/0! | W77: =W43/W55 -> #DIV/0! | X77: =X43/X55 -> #DIV/0! | Y77: =Y43/Y55 -> #DIV/0! | Z77: =Z43/Z55 -> #DIV/0! | ... AC77: =AC43/AC55 -> #DIV/0! | AD77: =AD43/AD57 -> #DIV/0!
B78: Umi | C78: =C44/C58 -> #DIV/0! | D78: =D44/D58 -> #DIV/0! | E78: =E44/E58 -> #DIV/0! | F78: =F44/F58 -> #DIV/0! | G78: =G44/G58 -> #DIV/0! | H78: =H44/H58 -> #DIV/0! | I78: =I44/I58 -> #DIV/0! | J78: =J44/J58 -> #DIV/0! | K78: =K44/K58 -> #DIV/0! | O78: =O44/O58 -> #DIV/0! | Q78: Umi | R78: =R44/R58 -> #DIV/0! | S78: =S44/S57 -> #DIV/0! | T78: =T44/T57 -> #DIV/0! | U78: =U44/U57 -> #DIV/0! | V78: =V44/V57 -> #DIV/0! | W78: =W44/W57 -> #DIV/0! | X78: =X44/X57 -> #DIV/0! | Y78: =Y44/Y57 -> #DIV/0! | Z78: =Z44/Z57 -> #DIV/0! | ... AC78: =AC44/AC57 -> #DIV/0! | AD78: =AD44/AD58 -> #DIV/0!
B79: Yuyun | C79: =C45/C59 -> #DIV/0! | D79: =D45/D59 -> #DIV/0! | E79: =E45/E59 -> #DIV/0! | F79: =F45/F59 -> #DIV/0! | G79: =G45/G59 -> #DIV/0! | H79: =H45/H59 -> #DIV/0! | I79: =I45/I59 -> #DIV/0! | J79: =J45/J59 -> #DIV/0! | K79: =K45/K59 -> #DIV/0! | O79: =O45/O59 -> #DIV/0! | Q79: Yuyun | R79: =R45/R59 -> #DIV/0! | S79: =S45/S58 -> #DIV/0! | T79: =T45/T58 -> #DIV/0! | U79: =U45/U58 -> #DIV/0! | V79: =V45/V58 -> #DIV/0! | W79: =W45/W58 -> #DIV/0! | X79: =X45/X58 -> #DIV/0! | Y79: =Y45/Y58 -> #DIV/0! | Z79: =Z45/Z58 -> #DIV/0! | ... AC79: =AC45/AC58 -> #DIV/0! | AD79: =AD45/AD59 -> #DIV/0!
B80: Zakia | C80: =C46/C60 -> #DIV/0! | D80: =D46/D60 -> #DIV/0! | E80: =E46/E60 -> #DIV/0! | F80: =F46/F60 -> #DIV/0! | G80: =G46/G60 -> #DIV/0! | H80: =H46/H60 -> #DIV/0! | I80: =I46/I60 -> #DIV/0! | J80: =J46/J60 -> #DIV/0! | K80: =K46/K60 -> #DIV/0! | O80: =O46/O60 -> #DIV/0! | Q80: Zakia | R80: =R46/R60 -> #DIV/0! | S80: =S46/S59 -> #DIV/0! | T80: =T46/T59 -> #DIV/0! | U80: =U46/U59 -> #DIV/0! | V80: =V46/V59 -> #DIV/0! | W80: =W46/W59 -> #DIV/0! | X80: =X46/X59 -> #DIV/0! | Y80: =Y46/Y59 -> #DIV/0! | Z80: =Z46/Z59 -> #DIV/0! | ... AC80: =AC46/AC59 -> #DIV/0! | AD80: =AD46/AD60 -> #DIV/0!
B81: TOTAL | C81: =C47/C68 -> #DIV/0! | D81: =D47/D68 -> #DIV/0! | E81: =E47/E68 -> #DIV/0! | F81: =F47/F68 -> #DIV/0! | G81: =G47/G68 -> #DIV/0! | H81: =H47/H68 -> #DIV/0! | I81: =I47/I68 -> #DIV/0! | J81: =J47/J68 -> #DIV/0! | ... M81: =M47/M68 -> #DIV/0! | N81: =SUM(N73:N80) -> 0 | O81: =O47/O68 -> #DIV/0! | Q81: TOTAL | R81: =R47/R68 -> #DIV/0! | S81: =S47/S68 -> #DIV/0! | T81: =T47/T68 -> #DIV/0! | U81: =U47/U68 -> #DIV/0! | V81: =V47/V68 -> #DIV/0! | W81: =W47/W68 -> #DIV/0! | X81: =X47/X68 -> #DIV/0! | Y81: =Y47/Y68 -> #DIV/0! | ... AB81: =AB47/AB68 -> #DIV/0! | AC81: =SUM(AC73:AC80) -> #DIV/0! | AD81: =AD47/AD68 -> #DIV/0!
B85: REVISI FAKTUR BERDASARKAN ADMIN SC
B86: Periode Januari 2025
B87: Adm. SC | C87: Januari | D87: Februari | E87: Maret | F87: April | G87: Mei | H87: Juni | I87: Juli | J87: Agustus | K87: September | L87: Oktober | M87: November | N87: Desember | O87: Total
B88: Nia | O88: =SUM(C88:N88) -> 0
B89: Nina | O89: =SUM(C89:N89) -> 0
B90: Nita | O90: =SUM(C90:N90) -> 0
B91: Grand Total | C91: =SUM(C88:C90) -> 0 | D91: =SUM(D88:D90) -> 0 | E91: =SUM(E88:E90) -> 0 | F91: =SUM(F88:F90) -> 0 | G91: =SUM(G88:G90) -> 0 | H91: =SUM(H88:H90) -> 0 | I91: =SUM(I88:I90) -> 0 | J91: =SUM(J88:J90) -> 0 | ... O91: =SUM(O88:O90) -> 0
B92: JUMLAH PRODUKSI FAKTUR
B93: Adm. SC | C93: Jan | D93: Feb | E93: Mar | F93: Apr | G93: Mei | H93: Jun | I93: Jul | J93: Agst | K93: Sept | L93: Okt | M93: Nov | N93: Des | O93: Total
B94: Nia | O94: =SUM(C94:N94) -> 0
B95: Nina | O95: =SUM(C95:N95) -> 0
B96: Nita | O96: =SUM(C96:N96) -> 0
B97: Keuangan | O97: =SUM(C97:N97) -> 0
B98: Grand | C98: =SUM(C94:C97) -> 0 | D98: =SUM(D94:D97) -> 0 | E98: =SUM(E94:E97) -> 0 | F98: =SUM(F94:F97) -> 0 | G98: =SUM(G94:G97) -> 0 | H98: =SUM(H94:H97) -> 0 | I98: =SUM(I94:I97) -> 0 | J98: =SUM(J94:J97) -> 0 | ... O98: =SUM(O94:O97) -> 0
B99: % REVISI FAKTUR TERHADAP TOTAL FAKTUR
B100: Adm. SC | C100: Jan | D100: Feb | E100: Mar | F100: Apr | G100: Mei | H100: Jun | I100: Jul | J100: Agst | K100: Sept | L100: Okt | M100: Nov | N100: Des | O100: Total
B101: Nia | C101: =C88/C94 -> #DIV/0! | D101: =+D88/D94 -> #DIV/0! | E101: =+E88/E94 -> #DIV/0! | F101: =+F88/F94 -> #DIV/0! | G101: =+G88/G94 -> #DIV/0! | H101: =+H88/H94 -> #DIV/0! | I101: =+I88/I94 -> #DIV/0! | J101: =+J88/J94 -> #DIV/0! | K101: =+K88/K94 -> #DIV/0! | ... N101: =+N88/N94 -> #DIV/0! | O101: =O88/O94 -> #DIV/0!
B102: Nina | C102: =C89/C95 -> #DIV/0! | D102: =+D89/D95 -> #DIV/0! | E102: =+E89/E95 -> #DIV/0! | F102: =+F89/F95 -> #DIV/0! | G102: =+G89/G95 -> #DIV/0! | H102: =+H89/H95 -> #DIV/0! | I102: =+I89/I95 -> #DIV/0! | J102: =+J89/J95 -> #DIV/0! | K102: =+K89/K95 -> #DIV/0! | ... N102: =+N89/N95 -> #DIV/0! | O102: =O89/O95 -> #DIV/0!
B103: Nita | C103: =C90/C96 -> #DIV/0! | D103: =+D90/D96 -> #DIV/0! | E103: =+E90/E96 -> #DIV/0! | F103: 0 | G103: =+G90/G96 -> #DIV/0! | H103: =+H90/H96 -> #DIV/0! | I103: =+I90/I96 -> #DIV/0! | J103: =+J90/J96 -> #DIV/0! | K103: =+K90/K96 -> #DIV/0! | L103: =+L90/L96 -> #DIV/0! | M103: =+M90/M96 -> #DIV/0! | N103: =+N90/N96 -> #DIV/0! | O103: =O90/O96 -> #DIV/0!
B104: Grand Total | C104: =+C91/C98 -> #DIV/0! | D104: =+D91/D98 -> #DIV/0! | E104: =+E91/E98 -> #DIV/0! | F104: =+F91/F98 -> #DIV/0! | G104: =+G91/G98 -> #DIV/0! | H104: =+H91/H98 -> #DIV/0! | I104: =+I91/I98 -> #DIV/0! | J104: =+J91/J98 -> #DIV/0! | ... O104: =+O91/O98 -> #DIV/0!

Sheet Data (Per Faktur)
A1: Bulan | B1: Tanggal Revisi | C1: Tanggal Faktur | D1: No. Faktur | E1: SC | F1: Admin SC | G1: Cust | H1: Keterangan | I1: Total | J1: Alasan | K1: Klasifikasi
A2: Januari | B2: 46027 | C2: 46007 | D2: B25016568 | E2: Nanda | F2: Sheila | G2: Nurhanifah | H2: Batal | I2: 2225000 | J2: Kios tidak transfer. | K2: Kios Batal TRF/ Tidak Tepat Janji
A3: Januari | B3: 46027 | C3: 46007 | D3: B25016590 | E3: Nanda | F3: Sheila | G3: Nurhanifah | H3: Batal | I3: 1407500 | J3: Kios tidak transfer. | K3: Kios Batal TRF/ Tidak Tepat Janji
A4: Januari | B4: 46028 | C4: 46013 | D4: A25002336 | E4: Nanda | F4: Sheila | G4: Online Shop Shopee | H4: Batal | I4: 944120 | J4: Retur, Alasan pembeli yg dikirim salah, padahal barang sudah sesuai pesanan | K4: Retur
A5: Januari | B5: 46028 | C5: 46025 | D5: D26000208 | E5: Nina | F5: Faris | G5: Akbar Tani, UD | H5: Karissnail 6 PL 20 X 500 gr (M2U)* (edit qty jadi 5 box 17 pack) | I5: 10419000 | J5: Retur, barang bocor | K5: Retur
A6: Januari | B6: 46030 | C6: 46030 | D6: D26000505 | E6: Nina | F6: Zakia | G6: Tenggulun Tani | H6: Antracol 70 WP 20 X 500 gr (edit harga 79.000) | I6: 33387500 | J6: SC salah harga (harga awal 78.000) | K6: Salah harga Oleh SC
A7: Januari | B7: 46031 | C7: 46024 | D7: A26000002 | E7: Nanda | F7: Sheila | G7: Online Shop Shopee | H7: Batal | I7: 57147 | J7: Shopee tidak dapat memproses krna alamat kirim terdampak banjir, info gudang belum kirim | K7: Lain - Lain (Acc oleh Direktur, Hpp berubah)
A8: Januari | B8: 46032 | C8: 46031 | D8: D26000595 | E8: Nina | F8: Reni | G8: Tani Sejati/Meggie | H8: Curacron 500 EC 40 X 250 ml (edit qty jadi 50box) | I8: 133000000 | J8: Kios merevisi qty order, karena expired pendek. | K8: Permintaan Cust (Ganti Kemasan, Ganti Identitas Pajak, Habis Musim, Ganti Qty)
A9: Januari | B9: 46034 | C9: 46029 | D9: A26000059 | E9: Nanda | F9: Sheila | G9: Online Shop Tik tok | H9: Batal | I9: 85250 | J9: Retur, Pembeli membatalkan pesanan sebelum barang dikirim oleh ekspedisi. | K9: Retur
A10: Januari | B10: 46034 | C10: 46028 | D10: B26000321 | E10: Nanda | F10: Faris | G10: Ahmad Mahsun Fuadi | H10: Batal | I10: 425000 | J10: Kios batal order karena barang belum dikirim, sedangkan hari ini rencana dibawa ke luar pulau. | K10: Pembatalan Order Oleh Kios
A11: Januari | B11: 46035 | C11: 46034 | D11: A26000086 | E11: Nanda | F11: Sheila | G11: Online Shop Shopee | H11: Batal | I11: 158020 | J11: Pembatalan otomatis dari shopee karena customer tidak melakukan pembayaran non COD. | K11: Pembatalan Order Oleh Kios
A12: Januari | B12: 46039 | C12: 46024 | D12: A26000028 | E12: Nanda | F12: Sheila | G12: Online Shop Tik tok | H12: Batal | I12: 70250 | J12: Retur, Pembeli membatalkan pesanan sebelum barang dikirim oleh ekspedisi. | K12: Retur
A13: Januari | B13: 46044 | C13: 46044 | D13: D26001232 | E13: Nina | F13: Ariyani | G13: Tani Maju/Aris | H13: edit transaksi (ganti ke cust Bumi Asih, UD/Hasan, Manohara 10Box bonus 1 Box harga 17.500) | I13: 3500000 | J13: kios awal merevisi orderan. | K13: Permintaan Cust (Ganti Kemasan, Ganti Identitas Pajak, Habis Musim, Ganti Qty)
... A76: Mei | B76: 46168 | C76: 46165 | D76: D26008009 | E76: Nina | F76: Ariyani | G76: Hariyono Sby | H76: Batal | I76: 13200000 | J76: Kios Batal Order karena saat barang sampai disana cust bilang klo stok dia masih ada dan exp 11/26, Barang langsung dikirim ke Damai Samsuri | K76: Pembatalan Order Oleh Kios

Sheet REKAP (Per Barang)
B2: REVISI FAKTUR BERDASARKAN ALASANNYA
B3: Periode Januari - Desember 2026
B4: Klasifikasi | C4: Januari | D4: Februari | E4: Maret | F4: April | G4: Mei | H4: Juni | I4: Juli | J4: Agustus | K4: September | L4: Oktober | M4: November | N4: Desember | O4: Total
B5: Permintaan Cust (Ganti Kemasan, Ganti Identitas Pajak, Habis Musim, Ganti Qty) | C5: =COUNTIFS('DATA (Per Barang)'!$A:$A,'REKAP (Per Barang)'!C$4,'DATA (Per Barang)'!$K:$K,'REKAP (Per Barang)'!$B5) -> 2 | D5: =COUNTIFS('DATA (Per Barang)'!$A:$A,'REKAP (Per Barang)'!D$4,'DATA (Per Barang)'!$K:$K,'REKAP (Per Barang)'!$B5) -> 5 | E5: =COUNTIFS('DATA (Per Barang)'!$A:$A,'REKAP (Per Barang)'!E$4,'DATA (Per Barang)'!$K:$K,'REKAP (Per Barang)'!$B5) -> 3 | F5: =COUNTIFS('DATA (Per Barang)'!$A:$A,'REKAP (Per Barang)'!F$4,'DATA (Per Barang)'!$K:$K,'REKAP (Per Barang)'!$B5) -> 5 | G5: =COUNTIFS('DATA (Per Barang)'!$A:$A,'REKAP (Per Barang)'!G$4,'DATA (Per Barang)'!$K:$K,'REKAP (Per Barang)'!$B5) -> 4 | H5: =COUNTIFS('DATA (Per Barang)'!$A:$A,'REKAP (Per Barang)'!H$4,'DATA (Per Barang)'!$K:$K,'REKAP (Per Barang)'!$B5) -> 0 | I5: =COUNTIFS('DATA (Per Barang)'!$A:$A,'REKAP (Per Barang)'!I$4,'DATA (Per Barang)'!$K:$K,'REKAP (Per Barang)'!$B5) -> 0 | J5: =COUNTIFS('DATA (Per Barang)'!$A:$A,'REKAP (Per Barang)'!J$4,'DATA (Per Barang)'!$K:$K,'REKAP (Per Barang)'!$B5) -> 0 | ... N5: =COUNTIFS('DATA (Per Barang)'!$A:$A,'REKAP (Per Barang)'!N$4,'DATA (Per Barang)'!$K:$K,'REKAP (Per Barang)'!$B5) -> 0 | O5: =SUM(C5:N5) -> 19
B6: Lain - Lain (Acc oleh Direktur, Hpp berubah) | C6: =COUNTIFS('DATA (Per Barang)'!$A:$A,'REKAP (Per Barang)'!C$4,'DATA (Per Barang)'!$K:$K,'REKAP (Per Barang)'!$B6) -> 1 | D6: =COUNTIFS('DATA (Per Barang)'!$A:$A,'REKAP (Per Barang)'!D$4,'DATA (Per Barang)'!$K:$K,'REKAP (Per Barang)'!$B6) -> 0 | E6: =COUNTIFS('DATA (Per Barang)'!$A:$A,'REKAP (Per Barang)'!E$4,'DATA (Per Barang)'!$K:$K,'REKAP (Per Barang)'!$B6) -> 0 | F6: =COUNTIFS('DATA (Per Barang)'!$A:$A,'REKAP (Per Barang)'!F$4,'DATA (Per Barang)'!$K:$K,'REKAP (Per Barang)'!$B6) -> 0 | G6: =COUNTIFS('DATA (Per Barang)'!$A:$A,'REKAP (Per Barang)'!G$4,'DATA (Per Barang)'!$K:$K,'REKAP (Per Barang)'!$B6) -> 0 | H6: =COUNTIFS('DATA (Per Barang)'!$A:$A,'REKAP (Per Barang)'!H$4,'DATA (Per Barang)'!$K:$K,'REKAP (Per Barang)'!$B6) -> 0 | I6: =COUNTIFS('DATA (Per Barang)'!$A:$A,'REKAP (Per Barang)'!I$4,'DATA (Per Barang)'!$K:$K,'REKAP (Per Barang)'!$B6) -> 0 | J6: =COUNTIFS('DATA (Per Barang)'!$A:$A,'REKAP (Per Barang)'!J$4,'DATA (Per Barang)'!$K:$K,'REKAP (Per Barang)'!$B6) -> 0 | ... N6: =COUNTIFS('DATA (Per Barang)'!$A:$A,'REKAP (Per Barang)'!N$4,'DATA (Per Barang)'!$K:$K,'REKAP (Per Barang)'!$B6) -> 0 | O6: =SUM(C6:N6) -> 1
B7: Pembatalan Order Oleh Kios | C7: =COUNTIFS('DATA (Per Barang)'!$A:$A,'REKAP (Per Barang)'!C$4,'DATA (Per Barang)'!$K:$K,'REKAP (Per Barang)'!$B7) -> 2 | D7: =COUNTIFS('DATA (Per Barang)'!$A:$A,'REKAP (Per Barang)'!D$4,'DATA (Per Barang)'!$K:$K,'REKAP (Per Barang)'!$B7) -> 3 | E7: =COUNTIFS('DATA (Per Barang)'!$A:$A,'REKAP (Per Barang)'!E$4,'DATA (Per Barang)'!$K:$K,'REKAP (Per Barang)'!$B7) -> 0 | F7: =COUNTIFS('Data (Per Faktur)'!$A:$A,'REKAP (Faktur)'!F$4,'Data (Per Faktur)'!$K:$K,'REKAP (Faktur)'!$B7) -> 2 | G7: =COUNTIFS('DATA (Per Barang)'!$A:$A,'REKAP (Per Barang)'!G$4,'DATA (Per Barang)'!$K:$K,'REKAP (Per Barang)'!$B7) -> 3 | H7: =COUNTIFS('Data (Per Faktur)'!$A:$A,'REKAP (Faktur)'!H$4,'Data (Per Faktur)'!$K:$K,'REKAP (Faktur)'!$B7) -> 0 | I7: =COUNTIFS('Data (Per Faktur)'!$A:$A,'REKAP (Faktur)'!I$4,'Data (Per Faktur)'!$K:$K,'REKAP (Faktur)'!$B7) -> 0 | J7: =COUNTIFS('Data (Per Faktur)'!$A:$A,'REKAP (Faktur)'!J$4,'Data (Per Faktur)'!$K:$K,'REKAP (Faktur)'!$B7) -> 0 | K7: =COUNTIFS('Data (Per Faktur)'!$A:$A,'REKAP (Faktur)'!K$4,'Data (Per Faktur)'!$K:$K,'REKAP (Faktur)'!$B7) -> 0 | L7: =COUNTIFS('Data (Per Faktur)'!$A:$A,'REKAP (Faktur)'!L$4,'Data (Per Faktur)'!$K:$K,'REKAP (Faktur)'!$B7) -> 0 | M7: =COUNTIFS('Data (Per Faktur)'!$A:$A,'REKAP (Faktur)'!M$4,'Data (Per Faktur)'!$K:$K,'REKAP (Faktur)'!$B7) -> 0 | N7: =COUNTIFS('DATA (Per Barang)'!$A:$A,'REKAP (Per Barang)'!N$4,'DATA (Per Barang)'!$K:$K,'REKAP (Per Barang)'!$B7) -> 0 | O7: =SUM(C7:N7) -> 10
B8: Retur | C8: =COUNTIFS('DATA (Per Barang)'!$A:$A,'REKAP (Per Barang)'!C$4,'DATA (Per Barang)'!$K:$K,'REKAP (Per Barang)'!$B8) -> 6 | D8: =COUNTIFS('DATA (Per Barang)'!$A:$A,'REKAP (Per Barang)'!D$4,'DATA (Per Barang)'!$K:$K,'REKAP (Per Barang)'!$B8) -> 4 | E8: =COUNTIFS('DATA (Per Barang)'!$A:$A,'REKAP (Per Barang)'!E$4,'DATA (Per Barang)'!$K:$K,'REKAP (Per Barang)'!$B8) -> 3 | F8: =COUNTIFS('Data (Per Faktur)'!$A:$A,'REKAP (Faktur)'!F$4,'Data (Per Faktur)'!$K:$K,'REKAP (Faktur)'!$B8) -> 5 | G8: =COUNTIFS('DATA (Per Barang)'!$A:$A,'REKAP (Per Barang)'!G$4,'DATA (Per Barang)'!$K:$K,'REKAP (Per Barang)'!$B8) -> 7 | H8: =COUNTIFS('Data (Per Faktur)'!$A:$A,'REKAP (Faktur)'!H$4,'Data (Per Faktur)'!$K:$K,'REKAP (Faktur)'!$B8) -> 0 | I8: =COUNTIFS('Data (Per Faktur)'!$A:$A,'REKAP (Faktur)'!I$4,'Data (Per Faktur)'!$K:$K,'REKAP (Faktur)'!$B8) -> 0 | J8: =COUNTIFS('Data (Per Faktur)'!$A:$A,'REKAP (Faktur)'!J$4,'Data (Per Faktur)'!$K:$K,'REKAP (Faktur)'!$B8) -> 0 | K8: =COUNTIFS('Data (Per Faktur)'!$A:$A,'REKAP (Faktur)'!K$4,'Data (Per Faktur)'!$K:$K,'REKAP (Faktur)'!$B8) -> 0 | L8: =COUNTIFS('Data (Per Faktur)'!$A:$A,'REKAP (Faktur)'!L$4,'Data (Per Faktur)'!$K:$K,'REKAP (Faktur)'!$B8) -> 0 | M8: =COUNTIFS('Data (Per Faktur)'!$A:$A,'REKAP (Faktur)'!M$4,'Data (Per Faktur)'!$K:$K,'REKAP (Faktur)'!$B8) -> 0 | N8: =COUNTIFS('DATA (Per Barang)'!$A:$A,'REKAP (Per Barang)'!N$4,'DATA (Per Barang)'!$K:$K,'REKAP (Per Barang)'!$B8) -> 0 | O8: =SUM(C8:N8) -> 25
B9: Kios Batal TRF/ Tidak Tepat Janji | C9: =COUNTIFS('DATA (Per Barang)'!$A:$A,'REKAP (Per Barang)'!C$4,'DATA (Per Barang)'!$K:$K,'REKAP (Per Barang)'!$B9) -> 2 | D9: =COUNTIFS('DATA (Per Barang)'!$A:$A,'REKAP (Per Barang)'!D$4,'DATA (Per Barang)'!$K:$K,'REKAP (Per Barang)'!$B9) -> 1 | E9: =COUNTIFS('DATA (Per Barang)'!$A:$A,'REKAP (Per Barang)'!E$4,'DATA (Per Barang)'!$K:$K,'REKAP (Per Barang)'!$B9) -> 0 | F9: =COUNTIFS('Data (Per Faktur)'!$A:$A,'REKAP (Faktur)'!F$4,'Data (Per Faktur)'!$K:$K,'REKAP (Faktur)'!$B9) -> 1 | G9: =COUNTIFS('DATA (Per Barang)'!$A:$A,'REKAP (Per Barang)'!G$4,'DATA (Per Barang)'!$K:$K,'REKAP (Per Barang)'!$B9) -> 1 | H9: =COUNTIFS('Data (Per Faktur)'!$A:$A,'REKAP (Faktur)'!H$4,'Data (Per Faktur)'!$K:$K,'REKAP (Faktur)'!$B9) -> 0 | I9: =COUNTIFS('Data (Per Faktur)'!$A:$A,'REKAP (Faktur)'!I$4,'Data (Per Faktur)'!$K:$K,'REKAP (Faktur)'!$B9) -> 0 | J9: =COUNTIFS('Data (Per Faktur)'!$A:$A,'REKAP (Faktur)'!J$4,'Data (Per Faktur)'!$K:$K,'REKAP (Faktur)'!$B9) -> 0 | K9: =COUNTIFS('Data (Per Faktur)'!$A:$A,'REKAP (Faktur)'!K$4,'Data (Per Faktur)'!$K:$K,'REKAP (Faktur)'!$B9) -> 0 | L9: =COUNTIFS('Data (Per Faktur)'!$A:$A,'REKAP (Faktur)'!L$4,'Data (Per Faktur)'!$K:$K,'REKAP (Faktur)'!$B9) -> 0 | M9: =COUNTIFS('Data (Per Faktur)'!$A:$A,'REKAP (Faktur)'!M$4,'Data (Per Faktur)'!$K:$K,'REKAP (Faktur)'!$B9) -> 0 | N9: =COUNTIFS('DATA (Per Barang)'!$A:$A,'REKAP (Per Barang)'!N$4,'DATA (Per Barang)'!$K:$K,'REKAP (Per Barang)'!$B9) -> 0 | O9: =SUM(C9:N9) -> 5
B10: Salah Input Oleh Admin SC | C10: =COUNTIFS('DATA (Per Barang)'!$A:$A,'REKAP (Per Barang)'!C$4,'DATA (Per Barang)'!$K:$K,'REKAP (Per Barang)'!$B10) -> 0 | D10: =COUNTIFS('DATA (Per Barang)'!$A:$A,'REKAP (Per Barang)'!D$4,'DATA (Per Barang)'!$K:$K,'REKAP (Per Barang)'!$B10) -> 0 | E10: =COUNTIFS('DATA (Per Barang)'!$A:$A,'REKAP (Per Barang)'!E$4,'DATA (Per Barang)'!$K:$K,'REKAP (Per Barang)'!$B10) -> 4 | F10: =COUNTIFS('Data (Per Faktur)'!$A:$A,'REKAP (Faktur)'!F$4,'Data (Per Faktur)'!$K:$K,'REKAP (Faktur)'!$B10) -> 1 | G10: =COUNTIFS('DATA (Per Barang)'!$A:$A,'REKAP (Per Barang)'!G$4,'DATA (Per Barang)'!$K:$K,'REKAP (Per Barang)'!$B10) -> 0 | H10: =COUNTIFS('Data (Per Faktur)'!$A:$A,'REKAP (Faktur)'!H$4,'Data (Per Faktur)'!$K:$K,'REKAP (Faktur)'!$B10) -> 0 | I10: =COUNTIFS('Data (Per Faktur)'!$A:$A,'REKAP (Faktur)'!I$4,'Data (Per Faktur)'!$K:$K,'REKAP (Faktur)'!$B10) -> 0 | J10: =COUNTIFS('Data (Per Faktur)'!$A:$A,'REKAP (Faktur)'!J$4,'Data (Per Faktur)'!$K:$K,'REKAP (Faktur)'!$B10) -> 0 | K10: =COUNTIFS('Data (Per Faktur)'!$A:$A,'REKAP (Faktur)'!K$4,'Data (Per Faktur)'!$K:$K,'REKAP (Faktur)'!$B10) -> 0 | L10: =COUNTIFS('Data (Per Faktur)'!$A:$A,'REKAP (Faktur)'!L$4,'Data (Per Faktur)'!$K:$K,'REKAP (Faktur)'!$B10) -> 0 | M10: =COUNTIFS('Data (Per Faktur)'!$A:$A,'REKAP (Faktur)'!M$4,'Data (Per Faktur)'!$K:$K,'REKAP (Faktur)'!$B10) -> 0 | N10: =COUNTIFS('DATA (Per Barang)'!$A:$A,'REKAP (Per Barang)'!N$4,'DATA (Per Barang)'!$K:$K,'REKAP (Per Barang)'!$B10) -> 0 | O10: =SUM(C10:N10) -> 5
B11: Salah harga Oleh SC | C11: =COUNTIFS('DATA (Per Barang)'!$A:$A,'REKAP (Per Barang)'!C$4,'DATA (Per Barang)'!$K:$K,'REKAP (Per Barang)'!$B11) -> 1 | D11: =COUNTIFS('DATA (Per Barang)'!$A:$A,'REKAP (Per Barang)'!D$4,'DATA (Per Barang)'!$K:$K,'REKAP (Per Barang)'!$B11) -> 0 | E11: =COUNTIFS('DATA (Per Barang)'!$A:$A,'REKAP (Per Barang)'!E$4,'DATA (Per Barang)'!$K:$K,'REKAP (Per Barang)'!$B11) -> 0 | F11: =COUNTIFS('Data (Per Faktur)'!$A:$A,'REKAP (Faktur)'!F$4,'Data (Per Faktur)'!$K:$K,'REKAP (Faktur)'!$B11) -> 1 | G11: =COUNTIFS('DATA (Per Barang)'!$A:$A,'REKAP (Per Barang)'!G$4,'DATA (Per Barang)'!$K:$K,'REKAP (Per Barang)'!$B11) -> 0 | H11: =COUNTIFS('Data (Per Faktur)'!$A:$A,'REKAP (Faktur)'!H$4,'Data (Per Faktur)'!$K:$K,'REKAP (Faktur)'!$B11) -> 0 | I11: =COUNTIFS('Data (Per Faktur)'!$A:$A,'REKAP (Faktur)'!I$4,'Data (Per Faktur)'!$K:$K,'REKAP (Faktur)'!$B11) -> 0 | J11: =COUNTIFS('Data (Per Faktur)'!$A:$A,'REKAP (Faktur)'!J$4,'Data (Per Faktur)'!$K:$K,'REKAP (Faktur)'!$B11) -> 0 | K11: =COUNTIFS('Data (Per Faktur)'!$A:$A,'REKAP (Faktur)'!K$4,'Data (Per Faktur)'!$K:$K,'REKAP (Faktur)'!$B11) -> 0 | L11: =COUNTIFS('Data (Per Faktur)'!$A:$A,'REKAP (Faktur)'!L$4,'Data (Per Faktur)'!$K:$K,'REKAP (Faktur)'!$B11) -> 0 | M11: =COUNTIFS('Data (Per Faktur)'!$A:$A,'REKAP (Faktur)'!M$4,'Data (Per Faktur)'!$K:$K,'REKAP (Faktur)'!$B11) -> 0 | N11: =COUNTIFS('DATA (Per Barang)'!$A:$A,'REKAP (Per Barang)'!N$4,'DATA (Per Barang)'!$K:$K,'REKAP (Per Barang)'!$B11) -> 0 | O11: =SUM(C11:N11) -> 2
B12: Harga tidak cocok | C12: =COUNTIFS('DATA (Per Barang)'!$A:$A,'REKAP (Per Barang)'!C$4,'DATA (Per Barang)'!$K:$K,'REKAP (Per Barang)'!$B12) -> 0 | D12: =COUNTIFS('DATA (Per Barang)'!$A:$A,'REKAP (Per Barang)'!D$4,'DATA (Per Barang)'!$K:$K,'REKAP (Per Barang)'!$B12) -> 0 | E12: =COUNTIFS('DATA (Per Barang)'!$A:$A,'REKAP (Per Barang)'!E$4,'DATA (Per Barang)'!$K:$K,'REKAP (Per Barang)'!$B12) -> 0 | F12: =COUNTIFS('Data (Per Faktur)'!$A:$A,'REKAP (Faktur)'!F$4,'Data (Per Faktur)'!$K:$K,'REKAP (Faktur)'!$B12) -> 0 | G12: =COUNTIFS('DATA (Per Barang)'!$A:$A,'REKAP (Per Barang)'!G$4,'DATA (Per Barang)'!$K:$K,'REKAP (Per Barang)'!$B12) -> 0 | H12: =COUNTIFS('Data (Per Faktur)'!$A:$A,'REKAP (Faktur)'!H$4,'Data (Per Faktur)'!$K:$K,'REKAP (Faktur)'!$B12) -> 0 | I12: =COUNTIFS('Data (Per Faktur)'!$A:$A,'REKAP (Faktur)'!I$4,'Data (Per Faktur)'!$K:$K,'REKAP (Faktur)'!$B12) -> 0 | J12: =COUNTIFS('Data (Per Faktur)'!$A:$A,'REKAP (Faktur)'!J$4,'Data (Per Faktur)'!$K:$K,'REKAP (Faktur)'!$B12) -> 0 | K12: =COUNTIFS('Data (Per Faktur)'!$A:$A,'REKAP (Faktur)'!K$4,'Data (Per Faktur)'!$K:$K,'REKAP (Faktur)'!$B12) -> 0 | L12: =COUNTIFS('Data (Per Faktur)'!$A:$A,'REKAP (Faktur)'!L$4,'Data (Per Faktur)'!$K:$K,'REKAP (Faktur)'!$B12) -> 0 | M12: =COUNTIFS('Data (Per Faktur)'!$A:$A,'REKAP (Faktur)'!M$4,'Data (Per Faktur)'!$K:$K,'REKAP (Faktur)'!$B12) -> 0 | N12: =COUNTIFS('DATA (Per Barang)'!$A:$A,'REKAP (Per Barang)'!N$4,'DATA (Per Barang)'!$K:$K,'REKAP (Per Barang)'!$B12) -> 0 | O12: =SUM(C12:N12) -> 0
B13: Salah SO oleh SC | C13: =COUNTIFS('DATA (Per Barang)'!$A:$A,'REKAP (Per Barang)'!C$4,'DATA (Per Barang)'!$K:$K,'REKAP (Per Barang)'!$B13) -> 2 | D13: =COUNTIFS('DATA (Per Barang)'!$A:$A,'REKAP (Per Barang)'!D$4,'DATA (Per Barang)'!$K:$K,'REKAP (Per Barang)'!$B13) -> 0 | E13: =COUNTIFS('DATA (Per Barang)'!$A:$A,'REKAP (Per Barang)'!E$4,'DATA (Per Barang)'!$K:$K,'REKAP (Per Barang)'!$B13) -> 0 | F13: =COUNTIFS('Data (Per Faktur)'!$A:$A,'REKAP (Faktur)'!F$4,'Data (Per Faktur)'!$K:$K,'REKAP (Faktur)'!$B13) -> 0 | G13: =COUNTIFS('DATA (Per Barang)'!$A:$A,'REKAP (Per Barang)'!G$4,'DATA (Per Barang)'!$K:$K,'REKAP (Per Barang)'!$B13) -> 0 | H13: =COUNTIFS('Data (Per Faktur)'!$A:$A,'REKAP (Faktur)'!H$4,'Data (Per Faktur)'!$K:$K,'REKAP (Faktur)'!$B13) -> 0 | I13: =COUNTIFS('Data (Per Faktur)'!$A:$A,'REKAP (Faktur)'!I$4,'Data (Per Faktur)'!$K:$K,'REKAP (Faktur)'!$B13) -> 0 | J13: =COUNTIFS('Data (Per Faktur)'!$A:$A,'REKAP (Faktur)'!J$4,'Data (Per Faktur)'!$K:$K,'REKAP (Faktur)'!$B13) -> 0 | K13: =COUNTIFS('Data (Per Faktur)'!$A:$A,'REKAP (Faktur)'!K$4,'Data (Per Faktur)'!$K:$K,'REKAP (Faktur)'!$B13) -> 0 | L13: =COUNTIFS('Data (Per Faktur)'!$A:$A,'REKAP (Faktur)'!L$4,'Data (Per Faktur)'!$K:$K,'REKAP (Faktur)'!$B13) -> 0 | M13: =COUNTIFS('Data (Per Faktur)'!$A:$A,'REKAP (Faktur)'!M$4,'Data (Per Faktur)'!$K:$K,'REKAP (Faktur)'!$B13) -> 0 | N13: =COUNTIFS('DATA (Per Barang)'!$A:$A,'REKAP (Per Barang)'!N$4,'DATA (Per Barang)'!$K:$K,'REKAP (Per Barang)'!$B13) -> 0 | O13: =SUM(C13:N13) -> 2
B14: Pembagian Barang ke kios Lain | C14: =COUNTIFS('DATA (Per Barang)'!$A:$A,'REKAP (Per Barang)'!C$4,'DATA (Per Barang)'!$K:$K,'REKAP (Per Barang)'!$B14) -> 0 | D14: =COUNTIFS('DATA (Per Barang)'!$A:$A,'REKAP (Per Barang)'!D$4,'DATA (Per Barang)'!$K:$K,'REKAP (Per Barang)'!$B14) -> 0 | E14: =COUNTIFS('DATA (Per Barang)'!$A:$A,'REKAP (Per Barang)'!E$4,'DATA (Per Barang)'!$K:$K,'REKAP (Per Barang)'!$B14) -> 0 | F14: =COUNTIFS('DATA (Per Barang)'!$A:$A,'REKAP (Per Barang)'!F$4,'DATA (Per Barang)'!$K:$K,'REKAP (Per Barang)'!$B14) -> 1 | G14: =COUNTIFS('DATA (Per Barang)'!$A:$A,'REKAP (Per Barang)'!G$4,'DATA (Per Barang)'!$K:$K,'REKAP (Per Barang)'!$B14) -> 0 | H14: =COUNTIFS('DATA (Per Barang)'!$A:$A,'REKAP (Per Barang)'!H$4,'DATA (Per Barang)'!$K:$K,'REKAP (Per Barang)'!$B14) -> 0 | I14: =COUNTIFS('DATA (Per Barang)'!$A:$A,'REKAP (Per Barang)'!I$4,'DATA (Per Barang)'!$K:$K,'REKAP (Per Barang)'!$B14) -> 0 | J14: =COUNTIFS('DATA (Per Barang)'!$A:$A,'REKAP (Per Barang)'!J$4,'DATA (Per Barang)'!$K:$K,'REKAP (Per Barang)'!$B14) -> 0 | ... N14: =COUNTIFS('DATA (Per Barang)'!$A:$A,'REKAP (Per Barang)'!N$4,'DATA (Per Barang)'!$K:$K,'REKAP (Per Barang)'!$B14) -> 0 | O14: =SUM(C14:N14) -> 1
B15: Barang Rusak/Cacat/Bocor/Exp | C15: =COUNTIFS('DATA (Per Barang)'!$A:$A,'REKAP (Per Barang)'!C$4,'DATA (Per Barang)'!$K:$K,'REKAP (Per Barang)'!$B15) -> 0 | D15: =COUNTIFS('DATA (Per Barang)'!$A:$A,'REKAP (Per Barang)'!D$4,'DATA (Per Barang)'!$K:$K,'REKAP (Per Barang)'!$B15) -> 0 | E15: =COUNTIFS('DATA (Per Barang)'!$A:$A,'REKAP (Per Barang)'!E$4,'DATA (Per Barang)'!$K:$K,'REKAP (Per Barang)'!$B15) -> 0 | F15: =COUNTIFS('Data (Per Faktur)'!$A:$A,'REKAP (Faktur)'!F$4,'Data (Per Faktur)'!$K:$K,'REKAP (Faktur)'!$B15) -> 0 | G15: =COUNTIFS('Data (Per Faktur)'!$A:$A,'REKAP (Faktur)'!G$4,'Data (Per Faktur)'!$K:$K,'REKAP (Faktur)'!$B15) -> 0 | H15: =COUNTIFS('Data (Per Faktur)'!$A:$A,'REKAP (Faktur)'!H$4,'Data (Per Faktur)'!$K:$K,'REKAP (Faktur)'!$B15) -> 0 | I15: =COUNTIFS('Data (Per Faktur)'!$A:$A,'REKAP (Faktur)'!I$4,'Data (Per Faktur)'!$K:$K,'REKAP (Faktur)'!$B15) -> 0 | J15: =COUNTIFS('Data (Per Faktur)'!$A:$A,'REKAP (Faktur)'!J$4,'Data (Per Faktur)'!$K:$K,'REKAP (Faktur)'!$B15) -> 0 | K15: =COUNTIFS('Data (Per Faktur)'!$A:$A,'REKAP (Faktur)'!K$4,'Data (Per Faktur)'!$K:$K,'REKAP (Faktur)'!$B15) -> 0 | L15: =COUNTIFS('Data (Per Faktur)'!$A:$A,'REKAP (Faktur)'!L$4,'Data (Per Faktur)'!$K:$K,'REKAP (Faktur)'!$B15) -> 0 | M15: =COUNTIFS('Data (Per Faktur)'!$A:$A,'REKAP (Faktur)'!M$4,'Data (Per Faktur)'!$K:$K,'REKAP (Faktur)'!$B15) -> 0 | N15: =COUNTIFS('DATA (Per Barang)'!$A:$A,'REKAP (Per Barang)'!N$4,'DATA (Per Barang)'!$K:$K,'REKAP (Per Barang)'!$B15) -> 0 | O15: =SUM(C15:N15) -> 0
B16: Toko Double Order | C16: =COUNTIFS('DATA (Per Barang)'!$A:$A,'REKAP (Per Barang)'!C$4,'DATA (Per Barang)'!$K:$K,'REKAP (Per Barang)'!$B16) -> 0 | D16: =COUNTIFS('DATA (Per Barang)'!$A:$A,'REKAP (Per Barang)'!D$4,'DATA (Per Barang)'!$K:$K,'REKAP (Per Barang)'!$B16) -> 0 | E16: =COUNTIFS('DATA (Per Barang)'!$A:$A,'REKAP (Per Barang)'!E$4,'DATA (Per Barang)'!$K:$K,'REKAP (Per Barang)'!$B16) -> 0 | F16: =COUNTIFS('Data (Per Faktur)'!$A:$A,'REKAP (Faktur)'!F$4,'Data (Per Faktur)'!$K:$K,'REKAP (Faktur)'!$B16) -> 0 | G16: =COUNTIFS('Data (Per Faktur)'!$A:$A,'REKAP (Faktur)'!G$4,'Data (Per Faktur)'!$K:$K,'REKAP (Faktur)'!$B16) -> 0 | H16: =COUNTIFS('Data (Per Faktur)'!$A:$A,'REKAP (Faktur)'!H$4,'Data (Per Faktur)'!$K:$K,'REKAP (Faktur)'!$B16) -> 0 | I16: =COUNTIFS('Data (Per Faktur)'!$A:$A,'REKAP (Faktur)'!I$4,'Data (Per Faktur)'!$K:$K,'REKAP (Faktur)'!$B16) -> 0 | J16: =COUNTIFS('Data (Per Faktur)'!$A:$A,'REKAP (Faktur)'!J$4,'Data (Per Faktur)'!$K:$K,'REKAP (Faktur)'!$B16) -> 0 | K16: =COUNTIFS('Data (Per Faktur)'!$A:$A,'REKAP (Faktur)'!K$4,'Data (Per Faktur)'!$K:$K,'REKAP (Faktur)'!$B16) -> 0 | L16: =COUNTIFS('Data (Per Faktur)'!$A:$A,'REKAP (Faktur)'!L$4,'Data (Per Faktur)'!$K:$K,'REKAP (Faktur)'!$B16) -> 0 | M16: =COUNTIFS('Data (Per Faktur)'!$A:$A,'REKAP (Faktur)'!M$4,'Data (Per Faktur)'!$K:$K,'REKAP (Faktur)'!$B16) -> 0 | N16: =COUNTIFS('DATA (Per Barang)'!$A:$A,'REKAP (Per Barang)'!N$4,'DATA (Per Barang)'!$K:$K,'REKAP (Per Barang)'!$B16) -> 0 | O16: =SUM(C16:N16) -> 0
B17: Pengiriman Terlalu lama | C17: =COUNTIFS('DATA (Per Barang)'!$A:$A,'REKAP (Per Barang)'!C$4,'DATA (Per Barang)'!$K:$K,'REKAP (Per Barang)'!$B17) -> 0 | D17: =COUNTIFS('DATA (Per Barang)'!$A:$A,'REKAP (Per Barang)'!D$4,'DATA (Per Barang)'!$K:$K,'REKAP (Per Barang)'!$B17) -> 0 | E17: =COUNTIFS('DATA (Per Barang)'!$A:$A,'REKAP (Per Barang)'!E$4,'DATA (Per Barang)'!$K:$K,'REKAP (Per Barang)'!$B17) -> 0 | F17: =COUNTIFS('Data (Per Faktur)'!$A:$A,'REKAP (Faktur)'!F$4,'Data (Per Faktur)'!$K:$K,'REKAP (Faktur)'!$B17) -> 0 | G17: =COUNTIFS('Data (Per Faktur)'!$A:$A,'REKAP (Faktur)'!G$4,'Data (Per Faktur)'!$K:$K,'REKAP (Faktur)'!$B17) -> 0 | H17: =COUNTIFS('Data (Per Faktur)'!$A:$A,'REKAP (Faktur)'!H$4,'Data (Per Faktur)'!$K:$K,'REKAP (Faktur)'!$B17) -> 0 | I17: =COUNTIFS('Data (Per Faktur)'!$A:$A,'REKAP (Faktur)'!I$4,'Data (Per Faktur)'!$K:$K,'REKAP (Faktur)'!$B17) -> 0 | J17: =COUNTIFS('Data (Per Faktur)'!$A:$A,'REKAP (Faktur)'!J$4,'Data (Per Faktur)'!$K:$K,'REKAP (Faktur)'!$B17) -> 0 | K17: =COUNTIFS('Data (Per Faktur)'!$A:$A,'REKAP (Faktur)'!K$4,'Data (Per Faktur)'!$K:$K,'REKAP (Faktur)'!$B17) -> 0 | L17: =COUNTIFS('Data (Per Faktur)'!$A:$A,'REKAP (Faktur)'!L$4,'Data (Per Faktur)'!$K:$K,'REKAP (Faktur)'!$B17) -> 0 | M17: =COUNTIFS('Data (Per Faktur)'!$A:$A,'REKAP (Faktur)'!M$4,'Data (Per Faktur)'!$K:$K,'REKAP (Faktur)'!$B17) -> 0 | N17: =COUNTIFS('DATA (Per Barang)'!$A:$A,'REKAP (Per Barang)'!N$4,'DATA (Per Barang)'!$K:$K,'REKAP (Per Barang)'!$B17) -> 0 | O17: =SUM(C17:N17) -> 0
B18: Kurang naikkan Barang | C18: =COUNTIFS('DATA (Per Barang)'!$A:$A,'REKAP (Per Barang)'!C$4,'DATA (Per Barang)'!$K:$K,'REKAP (Per Barang)'!$B18) -> 0 | D18: =COUNTIFS('DATA (Per Barang)'!$A:$A,'REKAP (Per Barang)'!D$4,'DATA (Per Barang)'!$K:$K,'REKAP (Per Barang)'!$B18) -> 0 | E18: =COUNTIFS('DATA (Per Barang)'!$A:$A,'REKAP (Per Barang)'!E$4,'DATA (Per Barang)'!$K:$K,'REKAP (Per Barang)'!$B18) -> 0 | F18: =COUNTIFS('Data (Per Faktur)'!$A:$A,'REKAP (Faktur)'!F$4,'Data (Per Faktur)'!$K:$K,'REKAP (Faktur)'!$B18) -> 0 | G18: =COUNTIFS('Data (Per Faktur)'!$A:$A,'REKAP (Faktur)'!G$4,'Data (Per Faktur)'!$K:$K,'REKAP (Faktur)'!$B18) -> 0 | H18: =COUNTIFS('Data (Per Faktur)'!$A:$A,'REKAP (Faktur)'!H$4,'Data (Per Faktur)'!$K:$K,'REKAP (Faktur)'!$B18) -> 0 | I18: =COUNTIFS('Data (Per Faktur)'!$A:$A,'REKAP (Faktur)'!I$4,'Data (Per Faktur)'!$K:$K,'REKAP (Faktur)'!$B18) -> 0 | J18: =COUNTIFS('Data (Per Faktur)'!$A:$A,'REKAP (Faktur)'!J$4,'Data (Per Faktur)'!$K:$K,'REKAP (Faktur)'!$B18) -> 0 | K18: =COUNTIFS('Data (Per Faktur)'!$A:$A,'REKAP (Faktur)'!K$4,'Data (Per Faktur)'!$K:$K,'REKAP (Faktur)'!$B18) -> 0 | L18: =COUNTIFS('Data (Per Faktur)'!$A:$A,'REKAP (Faktur)'!L$4,'Data (Per Faktur)'!$K:$K,'REKAP (Faktur)'!$B18) -> 0 | M18: =COUNTIFS('Data (Per Faktur)'!$A:$A,'REKAP (Faktur)'!M$4,'Data (Per Faktur)'!$K:$K,'REKAP (Faktur)'!$B18) -> 0 | N18: =COUNTIFS('DATA (Per Barang)'!$A:$A,'REKAP (Per Barang)'!N$4,'DATA (Per Barang)'!$K:$K,'REKAP (Per Barang)'!$B18) -> 0 | O18: =SUM(C18:N18) -> 0
B19: Mecah Faktur krn mobil tidak muat | C19: =COUNTIFS('DATA (Per Barang)'!$A:$A,'REKAP (Per Barang)'!C$4,'DATA (Per Barang)'!$K:$K,'REKAP (Per Barang)'!$B19) -> 0 | D19: =COUNTIFS('DATA (Per Barang)'!$A:$A,'REKAP (Per Barang)'!D$4,'DATA (Per Barang)'!$K:$K,'REKAP (Per Barang)'!$B19) -> 0 | E19: =COUNTIFS('DATA (Per Barang)'!$A:$A,'REKAP (Per Barang)'!E$4,'DATA (Per Barang)'!$K:$K,'REKAP (Per Barang)'!$B19) -> 1 | F19: =COUNTIFS('Data (Per Faktur)'!$A:$A,'REKAP (Faktur)'!F$4,'Data (Per Faktur)'!$K:$K,'REKAP (Faktur)'!$B19) -> 0 | G19: =COUNTIFS('Data (Per Faktur)'!$A:$A,'REKAP (Faktur)'!G$4,'Data (Per Faktur)'!$K:$K,'REKAP (Faktur)'!$B19) -> 0 | H19: =COUNTIFS('Data (Per Faktur)'!$A:$A,'REKAP (Faktur)'!H$4,'Data (Per Faktur)'!$K:$K,'REKAP (Faktur)'!$B19) -> 0 | I19: =COUNTIFS('Data (Per Faktur)'!$A:$A,'REKAP (Faktur)'!I$4,'Data (Per Faktur)'!$K:$K,'REKAP (Faktur)'!$B19) -> 0 | J19: =COUNTIFS('Data (Per Faktur)'!$A:$A,'REKAP (Faktur)'!J$4,'Data (Per Faktur)'!$K:$K,'REKAP (Faktur)'!$B19) -> 0 | K19: =COUNTIFS('Data (Per Faktur)'!$A:$A,'REKAP (Faktur)'!K$4,'Data (Per Faktur)'!$K:$K,'REKAP (Faktur)'!$B19) -> 0 | L19: =COUNTIFS('Data (Per Faktur)'!$A:$A,'REKAP (Faktur)'!L$4,'Data (Per Faktur)'!$K:$K,'REKAP (Faktur)'!$B19) -> 0 | M19: =COUNTIFS('Data (Per Faktur)'!$A:$A,'REKAP (Faktur)'!M$4,'Data (Per Faktur)'!$K:$K,'REKAP (Faktur)'!$B19) -> 0 | N19: =COUNTIFS('DATA (Per Barang)'!$A:$A,'REKAP (Per Barang)'!N$4,'DATA (Per Barang)'!$K:$K,'REKAP (Per Barang)'!$B19) -> 0 | O19: =SUM(C19:N19) -> 1
B20: Salah Input Oleh Admin Keuangan | C20: =COUNTIFS('DATA (Per Barang)'!$A:$A,'REKAP (Per Barang)'!C$4,'DATA (Per Barang)'!$K:$K,'REKAP (Per Barang)'!$B20) -> 0 | D20: =COUNTIFS('DATA (Per Barang)'!$A:$A,'REKAP (Per Barang)'!D$4,'DATA (Per Barang)'!$K:$K,'REKAP (Per Barang)'!$B20) -> 0 | E20: =COUNTIFS('DATA (Per Barang)'!$A:$A,'REKAP (Per Barang)'!E$4,'DATA (Per Barang)'!$K:$K,'REKAP (Per Barang)'!$B20) -> 0 | F20: =COUNTIFS('Data (Per Faktur)'!$A:$A,'REKAP (Faktur)'!F$4,'Data (Per Faktur)'!$K:$K,'REKAP (Faktur)'!$B20) -> 0 | G20: =COUNTIFS('Data (Per Faktur)'!$A:$A,'REKAP (Faktur)'!G$4,'Data (Per Faktur)'!$K:$K,'REKAP (Faktur)'!$B20) -> 0 | H20: =COUNTIFS('Data (Per Faktur)'!$A:$A,'REKAP (Faktur)'!H$4,'Data (Per Faktur)'!$K:$K,'REKAP (Faktur)'!$B20) -> 0 | I20: =COUNTIFS('Data (Per Faktur)'!$A:$A,'REKAP (Faktur)'!I$4,'Data (Per Faktur)'!$K:$K,'REKAP (Faktur)'!$B20) -> 0 | J20: =COUNTIFS('Data (Per Faktur)'!$A:$A,'REKAP (Faktur)'!J$4,'Data (Per Faktur)'!$K:$K,'REKAP (Faktur)'!$B20) -> 0 | K20: =COUNTIFS('Data (Per Faktur)'!$A:$A,'REKAP (Faktur)'!K$4,'Data (Per Faktur)'!$K:$K,'REKAP (Faktur)'!$B20) -> 0 | L20: =COUNTIFS('Data (Per Faktur)'!$A:$A,'REKAP (Faktur)'!L$4,'Data (Per Faktur)'!$K:$K,'REKAP (Faktur)'!$B20) -> 0 | M20: =COUNTIFS('Data (Per Faktur)'!$A:$A,'REKAP (Faktur)'!M$4,'Data (Per Faktur)'!$K:$K,'REKAP (Faktur)'!$B20) -> 0 | N20: =COUNTIFS('DATA (Per Barang)'!$A:$A,'REKAP (Per Barang)'!N$4,'DATA (Per Barang)'!$K:$K,'REKAP (Per Barang)'!$B20) -> 0 | O20: =SUM(C20:N20) -> 0
B21: Salah naikkan barang | C21: =COUNTIFS('DATA (Per Barang)'!$A:$A,'REKAP (Per Barang)'!C$4,'DATA (Per Barang)'!$K:$K,'REKAP (Per Barang)'!$B21) -> 0 | D21: =COUNTIFS('DATA (Per Barang)'!$A:$A,'REKAP (Per Barang)'!D$4,'DATA (Per Barang)'!$K:$K,'REKAP (Per Barang)'!$B21) -> 0 | E21: =COUNTIFS('DATA (Per Barang)'!$A:$A,'REKAP (Per Barang)'!E$4,'DATA (Per Barang)'!$K:$K,'REKAP (Per Barang)'!$B21) -> 2 | F21: =COUNTIFS('Data (Per Faktur)'!$A:$A,'REKAP (Faktur)'!F$4,'Data (Per Faktur)'!$K:$K,'REKAP (Faktur)'!$B21) -> 0 | G21: =COUNTIFS('Data (Per Faktur)'!$A:$A,'REKAP (Faktur)'!G$4,'Data (Per Faktur)'!$K:$K,'REKAP (Faktur)'!$B21) -> 0 | H21: =COUNTIFS('Data (Per Faktur)'!$A:$A,'REKAP (Faktur)'!H$4,'Data (Per Faktur)'!$K:$K,'REKAP (Faktur)'!$B21) -> 0 | I21: =COUNTIFS('Data (Per Faktur)'!$A:$A,'REKAP (Faktur)'!I$4,'Data (Per Faktur)'!$K:$K,'REKAP (Faktur)'!$B21) -> 0 | J21: =COUNTIFS('Data (Per Faktur)'!$A:$A,'REKAP (Faktur)'!J$4,'Data (Per Faktur)'!$K:$K,'REKAP (Faktur)'!$B21) -> 0 | K21: =COUNTIFS('Data (Per Faktur)'!$A:$A,'REKAP (Faktur)'!K$4,'Data (Per Faktur)'!$K:$K,'REKAP (Faktur)'!$B21) -> 0 | L21: =COUNTIFS('Data (Per Faktur)'!$A:$A,'REKAP (Faktur)'!L$4,'Data (Per Faktur)'!$K:$K,'REKAP (Faktur)'!$B21) -> 0 | M21: =COUNTIFS('Data (Per Faktur)'!$A:$A,'REKAP (Faktur)'!M$4,'Data (Per Faktur)'!$K:$K,'REKAP (Faktur)'!$B21) -> 0 | N21: =COUNTIFS('DATA (Per Barang)'!$A:$A,'REKAP (Per Barang)'!N$4,'DATA (Per Barang)'!$K:$K,'REKAP (Per Barang)'!$B21) -> 0 | O21: =SUM(C21:N21) -> 2
B22: Stock di gudang kosong | C22: =COUNTIFS('DATA (Per Barang)'!$A:$A,'REKAP (Per Barang)'!C$4,'DATA (Per Barang)'!$K:$K,'REKAP (Per Barang)'!$B22) -> 0 | D22: =COUNTIFS('DATA (Per Barang)'!$A:$A,'REKAP (Per Barang)'!D$4,'DATA (Per Barang)'!$K:$K,'REKAP (Per Barang)'!$B22) -> 0 | E22: =COUNTIFS('DATA (Per Barang)'!$A:$A,'REKAP (Per Barang)'!E$4,'DATA (Per Barang)'!$K:$K,'REKAP (Per Barang)'!$B22) -> 0 | F22: =COUNTIFS('Data (Per Faktur)'!$A:$A,'REKAP (Faktur)'!F$4,'Data (Per Faktur)'!$K:$K,'REKAP (Faktur)'!$B22) -> 0 | G22: =COUNTIFS('Data (Per Faktur)'!$A:$A,'REKAP (Faktur)'!G$4,'Data (Per Faktur)'!$K:$K,'REKAP (Faktur)'!$B22) -> 0 | H22: =COUNTIFS('Data (Per Faktur)'!$A:$A,'REKAP (Faktur)'!H$4,'Data (Per Faktur)'!$K:$K,'REKAP (Faktur)'!$B22) -> 0 | I22: =COUNTIFS('Data (Per Faktur)'!$A:$A,'REKAP (Faktur)'!I$4,'Data (Per Faktur)'!$K:$K,'REKAP (Faktur)'!$B22) -> 0 | J22: =COUNTIFS('Data (Per Faktur)'!$A:$A,'REKAP (Faktur)'!J$4,'Data (Per Faktur)'!$K:$K,'REKAP (Faktur)'!$B22) -> 0 | K22: =COUNTIFS('Data (Per Faktur)'!$A:$A,'REKAP (Faktur)'!K$4,'Data (Per Faktur)'!$K:$K,'REKAP (Faktur)'!$B22) -> 0 | L22: =COUNTIFS('Data (Per Faktur)'!$A:$A,'REKAP (Faktur)'!L$4,'Data (Per Faktur)'!$K:$K,'REKAP (Faktur)'!$B22) -> 0 | M22: =COUNTIFS('Data (Per Faktur)'!$A:$A,'REKAP (Faktur)'!M$4,'Data (Per Faktur)'!$K:$K,'REKAP (Faktur)'!$B22) -> 0 | N22: =COUNTIFS('DATA (Per Barang)'!$A:$A,'REKAP (Per Barang)'!N$4,'DATA (Per Barang)'!$K:$K,'REKAP (Per Barang)'!$B22) -> 0 | O22: =SUM(C22:N22) -> 0
B23: Barang tidak dibawakan oleh Gudang | C23: =COUNTIFS('DATA (Per Barang)'!$A:$A,'REKAP (Per Barang)'!C$4,'DATA (Per Barang)'!$K:$K,'REKAP (Per Barang)'!$B23) -> 0 | D23: =COUNTIFS('DATA (Per Barang)'!$A:$A,'REKAP (Per Barang)'!D$4,'DATA (Per Barang)'!$K:$K,'REKAP (Per Barang)'!$B23) -> 0 | E23: =COUNTIFS('DATA (Per Barang)'!$A:$A,'REKAP (Per Barang)'!E$4,'DATA (Per Barang)'!$K:$K,'REKAP (Per Barang)'!$B23) -> 0 | F23: =COUNTIFS('Data (Per Faktur)'!$A:$A,'REKAP (Faktur)'!F$4,'Data (Per Faktur)'!$K:$K,'REKAP (Faktur)'!$B23) -> 0 | G23: =COUNTIFS('Data (Per Faktur)'!$A:$A,'REKAP (Faktur)'!G$4,'Data (Per Faktur)'!$K:$K,'REKAP (Faktur)'!$B23) -> 0 | H23: =COUNTIFS('Data (Per Faktur)'!$A:$A,'REKAP (Faktur)'!H$4,'Data (Per Faktur)'!$K:$K,'REKAP (Faktur)'!$B23) -> 0 | I23: =COUNTIFS('Data (Per Faktur)'!$A:$A,'REKAP (Faktur)'!I$4,'Data (Per Faktur)'!$K:$K,'REKAP (Faktur)'!$B23) -> 0 | J23: =COUNTIFS('Data (Per Faktur)'!$A:$A,'REKAP (Faktur)'!J$4,'Data (Per Faktur)'!$K:$K,'REKAP (Faktur)'!$B23) -> 0 | K23: =COUNTIFS('Data (Per Faktur)'!$A:$A,'REKAP (Faktur)'!K$4,'Data (Per Faktur)'!$K:$K,'REKAP (Faktur)'!$B23) -> 0 | L23: =COUNTIFS('Data (Per Faktur)'!$A:$A,'REKAP (Faktur)'!L$4,'Data (Per Faktur)'!$K:$K,'REKAP (Faktur)'!$B23) -> 0 | M23: =COUNTIFS('Data (Per Faktur)'!$A:$A,'REKAP (Faktur)'!M$4,'Data (Per Faktur)'!$K:$K,'REKAP (Faktur)'!$B23) -> 0 | N23: =COUNTIFS('DATA (Per Barang)'!$A:$A,'REKAP (Per Barang)'!N$4,'DATA (Per Barang)'!$K:$K,'REKAP (Per Barang)'!$B23) -> 0 | O23: =SUM(C23:N23) -> 0
B24: Gudang salah nurunkan barang | C24: =COUNTIFS('DATA (Per Barang)'!$A:$A,'REKAP (Per Barang)'!C$4,'DATA (Per Barang)'!$K:$K,'REKAP (Per Barang)'!$B24) -> 0 | D24: =COUNTIFS('DATA (Per Barang)'!$A:$A,'REKAP (Per Barang)'!D$4,'DATA (Per Barang)'!$K:$K,'REKAP (Per Barang)'!$B24) -> 0 | E24: =COUNTIFS('DATA (Per Barang)'!$A:$A,'REKAP (Per Barang)'!E$4,'DATA (Per Barang)'!$K:$K,'REKAP (Per Barang)'!$B24) -> 0 | F24: =COUNTIFS('Data (Per Faktur)'!$A:$A,'REKAP (Faktur)'!F$4,'Data (Per Faktur)'!$K:$K,'REKAP (Faktur)'!$B24) -> 0 | G24: =COUNTIFS('Data (Per Faktur)'!$A:$A,'REKAP (Faktur)'!G$4,'Data (Per Faktur)'!$K:$K,'REKAP (Faktur)'!$B24) -> 3 | H24: =COUNTIFS('Data (Per Faktur)'!$A:$A,'REKAP (Faktur)'!H$4,'Data (Per Faktur)'!$K:$K,'REKAP (Faktur)'!$B24) -> 0 | I24: =COUNTIFS('Data (Per Faktur)'!$A:$A,'REKAP (Faktur)'!I$4,'Data (Per Faktur)'!$K:$K,'REKAP (Faktur)'!$B24) -> 0 | J24: =COUNTIFS('Data (Per Faktur)'!$A:$A,'REKAP (Faktur)'!J$4,'Data (Per Faktur)'!$K:$K,'REKAP (Faktur)'!$B24) -> 0 | K24: =COUNTIFS('Data (Per Faktur)'!$A:$A,'REKAP (Faktur)'!K$4,'Data (Per Faktur)'!$K:$K,'REKAP (Faktur)'!$B24) -> 0 | L24: =COUNTIFS('Data (Per Faktur)'!$A:$A,'REKAP (Faktur)'!L$4,'Data (Per Faktur)'!$K:$K,'REKAP (Faktur)'!$B24) -> 0 | M24: =COUNTIFS('Data (Per Faktur)'!$A:$A,'REKAP (Faktur)'!M$4,'Data (Per Faktur)'!$K:$K,'REKAP (Faktur)'!$B24) -> 0 | N24: =COUNTIFS('DATA (Per Barang)'!$A:$A,'REKAP (Per Barang)'!N$4,'DATA (Per Barang)'!$K:$K,'REKAP (Per Barang)'!$B24) -> 0 | O24: =SUM(C24:N24) -> 3
B25: Salah Naik Barang | C25: =COUNTIFS('DATA (Per Barang)'!$A:$A,'REKAP (Per Barang)'!C$4,'DATA (Per Barang)'!$K:$K,'REKAP (Per Barang)'!$B25) -> 0 | D25: =COUNTIFS('DATA (Per Barang)'!$A:$A,'REKAP (Per Barang)'!D$4,'DATA (Per Barang)'!$K:$K,'REKAP (Per Barang)'!$B25) -> 0 | E25: =COUNTIFS('DATA (Per Barang)'!$A:$A,'REKAP (Per Barang)'!E$4,'DATA (Per Barang)'!$K:$K,'REKAP (Per Barang)'!$B25) -> 0 | F25: =COUNTIFS('Data (Per Faktur)'!$A:$A,'REKAP (Faktur)'!F$4,'Data (Per Faktur)'!$K:$K,'REKAP (Faktur)'!$B25) -> 0 | G25: =COUNTIFS('Data (Per Faktur)'!$A:$A,'REKAP (Faktur)'!G$4,'Data (Per Faktur)'!$K:$K,'REKAP (Faktur)'!$B25) -> 0 | H25: =COUNTIFS('Data (Per Faktur)'!$A:$A,'REKAP (Faktur)'!H$4,'Data (Per Faktur)'!$K:$K,'REKAP (Faktur)'!$B25) -> 0 | I25: =COUNTIFS('Data (Per Faktur)'!$A:$A,'REKAP (Faktur)'!I$4,'Data (Per Faktur)'!$K:$K,'REKAP (Faktur)'!$B25) -> 0 | J25: =COUNTIFS('Data (Per Faktur)'!$A:$A,'REKAP (Faktur)'!J$4,'Data (Per Faktur)'!$K:$K,'REKAP (Faktur)'!$B25) -> 0 | K25: =COUNTIFS('Data (Per Faktur)'!$A:$A,'REKAP (Faktur)'!K$4,'Data (Per Faktur)'!$K:$K,'REKAP (Faktur)'!$B25) -> 0 | L25: =COUNTIFS('Data (Per Faktur)'!$A:$A,'REKAP (Faktur)'!L$4,'Data (Per Faktur)'!$K:$K,'REKAP (Faktur)'!$B25) -> 0 | M25: =COUNTIFS('Data (Per Faktur)'!$A:$A,'REKAP (Faktur)'!M$4,'Data (Per Faktur)'!$K:$K,'REKAP (Faktur)'!$B25) -> 0 | N25: =COUNTIFS('DATA (Per Barang)'!$A:$A,'REKAP (Per Barang)'!N$4,'DATA (Per Barang)'!$K:$K,'REKAP (Per Barang)'!$B25) -> 0 | O25: =SUM(C25:N25) -> 0
B26: Sopir Salah Kirim | C26: =COUNTIFS('DATA (Per Barang)'!$A:$A,'REKAP (Per Barang)'!C$4,'DATA (Per Barang)'!$K:$K,'REKAP (Per Barang)'!$B26) -> 0 | D26: =COUNTIFS('DATA (Per Barang)'!$A:$A,'REKAP (Per Barang)'!D$4,'DATA (Per Barang)'!$K:$K,'REKAP (Per Barang)'!$B26) -> 0 | E26: =COUNTIFS('DATA (Per Barang)'!$A:$A,'REKAP (Per Barang)'!E$4,'DATA (Per Barang)'!$K:$K,'REKAP (Per Barang)'!$B26) -> 0 | F26: =COUNTIFS('Data (Per Faktur)'!$A:$A,'REKAP (Faktur)'!F$4,'Data (Per Faktur)'!$K:$K,'REKAP (Faktur)'!$B26) -> 0 | G26: =COUNTIFS('Data (Per Faktur)'!$A:$A,'REKAP (Faktur)'!G$4,'Data (Per Faktur)'!$K:$K,'REKAP (Faktur)'!$B26) -> 0 | H26: =COUNTIFS('Data (Per Faktur)'!$A:$A,'REKAP (Faktur)'!H$4,'Data (Per Faktur)'!$K:$K,'REKAP (Faktur)'!$B26) -> 0 | I26: =COUNTIFS('Data (Per Faktur)'!$A:$A,'REKAP (Faktur)'!I$4,'Data (Per Faktur)'!$K:$K,'REKAP (Faktur)'!$B26) -> 0 | J26: =COUNTIFS('Data (Per Faktur)'!$A:$A,'REKAP (Faktur)'!J$4,'Data (Per Faktur)'!$K:$K,'REKAP (Faktur)'!$B26) -> 0 | K26: =COUNTIFS('Data (Per Faktur)'!$A:$A,'REKAP (Faktur)'!K$4,'Data (Per Faktur)'!$K:$K,'REKAP (Faktur)'!$B26) -> 0 | L26: =COUNTIFS('Data (Per Faktur)'!$A:$A,'REKAP (Faktur)'!L$4,'Data (Per Faktur)'!$K:$K,'REKAP (Faktur)'!$B26) -> 0 | M26: =COUNTIFS('Data (Per Faktur)'!$A:$A,'REKAP (Faktur)'!M$4,'Data (Per Faktur)'!$K:$K,'REKAP (Faktur)'!$B26) -> 0 | N26: =COUNTIFS('DATA (Per Barang)'!$A:$A,'REKAP (Per Barang)'!N$4,'DATA (Per Barang)'!$K:$K,'REKAP (Per Barang)'!$B26) -> 0 | O26: =SUM(C26:N26) -> 0
... B28: Ketinggalan Kiriman | C28: =COUNTIFS('DATA (Per Barang)'!$A:$A,'REKAP (Per Barang)'!C$4,'DATA (Per Barang)'!$K:$K,'REKAP (Per Barang)'!$B28) -> 0 | D28: =COUNTIFS('DATA (Per Barang)'!$A:$A,'REKAP (Per Barang)'!D$4,'DATA (Per Barang)'!$K:$K,'REKAP (Per Barang)'!$B28) -> 0 | E28: =COUNTIFS('DATA (Per Barang)'!$A:$A,'REKAP (Per Barang)'!E$4,'DATA (Per Barang)'!$K:$K,'REKAP (Per Barang)'!$B28) -> 0 | F28: =COUNTIFS('Data (Per Faktur)'!$A:$A,'REKAP (Faktur)'!F$4,'Data (Per Faktur)'!$K:$K,'REKAP (Faktur)'!$B28) -> 0 | G28: =COUNTIFS('Data (Per Faktur)'!$A:$A,'REKAP (Faktur)'!G$4,'Data (Per Faktur)'!$K:$K,'REKAP (Faktur)'!$B28) -> 0 | H28: =COUNTIFS('Data (Per Faktur)'!$A:$A,'REKAP (Faktur)'!H$4,'Data (Per Faktur)'!$K:$K,'REKAP (Faktur)'!$B28) -> 0 | I28: =COUNTIFS('Data (Per Faktur)'!$A:$A,'REKAP (Faktur)'!I$4,'Data (Per Faktur)'!$K:$K,'REKAP (Faktur)'!$B28) -> 0 | J28: =COUNTIFS('Data (Per Faktur)'!$A:$A,'REKAP (Faktur)'!J$4,'Data (Per Faktur)'!$K:$K,'REKAP (Faktur)'!$B28) -> 0 | K28: =COUNTIFS('Data (Per Faktur)'!$A:$A,'REKAP (Faktur)'!K$4,'Data (Per Faktur)'!$K:$K,'REKAP (Faktur)'!$B28) -> 0 | L28: =COUNTIFS('Data (Per Faktur)'!$A:$A,'REKAP (Faktur)'!L$4,'Data (Per Faktur)'!$K:$K,'REKAP (Faktur)'!$B28) -> 0 | M28: =COUNTIFS('Data (Per Faktur)'!$A:$A,'REKAP (Faktur)'!M$4,'Data (Per Faktur)'!$K:$K,'REKAP (Faktur)'!$B28) -> 0 | N28: =COUNTIFS('DATA (Per Barang)'!$A:$A,'REKAP (Per Barang)'!N$4,'DATA (Per Barang)'!$K:$K,'REKAP (Per Barang)'!$B28) -> 0 | O28: =SUM(C28:N28) -> 0
B29: Salah Harga | C29: =COUNTIFS('DATA (Per Barang)'!$A:$A,'REKAP (Per Barang)'!C$4,'DATA (Per Barang)'!$K:$K,'REKAP (Per Barang)'!$B29) -> 0 | D29: =COUNTIFS('DATA (Per Barang)'!$A:$A,'REKAP (Per Barang)'!D$4,'DATA (Per Barang)'!$K:$K,'REKAP (Per Barang)'!$B29) -> 0 | E29: =COUNTIFS('DATA (Per Barang)'!$A:$A,'REKAP (Per Barang)'!E$4,'DATA (Per Barang)'!$K:$K,'REKAP (Per Barang)'!$B29) -> 0 | F29: =COUNTIFS('Data (Per Faktur)'!$A:$A,'REKAP (Faktur)'!F$4,'Data (Per Faktur)'!$K:$K,'REKAP (Faktur)'!$B29) -> 0 | G29: =COUNTIFS('Data (Per Faktur)'!$A:$A,'REKAP (Faktur)'!G$4,'Data (Per Faktur)'!$K:$K,'REKAP (Faktur)'!$B29) -> 0 | H29: =COUNTIFS('Data (Per Faktur)'!$A:$A,'REKAP (Faktur)'!H$4,'Data (Per Faktur)'!$K:$K,'REKAP (Faktur)'!$B29) -> 0 | I29: =COUNTIFS('Data (Per Faktur)'!$A:$A,'REKAP (Faktur)'!I$4,'Data (Per Faktur)'!$K:$K,'REKAP (Faktur)'!$B29) -> 0 | J29: =COUNTIFS('Data (Per Faktur)'!$A:$A,'REKAP (Faktur)'!J$4,'Data (Per Faktur)'!$K:$K,'REKAP (Faktur)'!$B29) -> 0 | K29: =COUNTIFS('Data (Per Faktur)'!$A:$A,'REKAP (Faktur)'!K$4,'Data (Per Faktur)'!$K:$K,'REKAP (Faktur)'!$B29) -> 0 | L29: =COUNTIFS('Data (Per Faktur)'!$A:$A,'REKAP (Faktur)'!L$4,'Data (Per Faktur)'!$K:$K,'REKAP (Faktur)'!$B29) -> 0 | M29: =COUNTIFS('Data (Per Faktur)'!$A:$A,'REKAP (Faktur)'!M$4,'Data (Per Faktur)'!$K:$K,'REKAP (Faktur)'!$B29) -> 0 | N29: =COUNTIFS('Data (Per Faktur)'!$A:$A,'REKAP (Faktur)'!N$4,'Data (Per Faktur)'!$K:$K,'REKAP (Faktur)'!$B29) -> 0 | O29: =SUM(C29:N29) -> 0
B30: Grand Total | C30: =SUM(C5:C29) -> 16 | D30: =SUM(D5:D29) -> 13 | E30: =SUM(E5:E29) -> 13 | F30: =SUM(F5:F29) -> 16 | G30: =SUM(G5:G29) -> 18 | H30: =SUM(H5:H29) -> 0 | I30: =SUM(I5:I29) -> 0 | J30: =SUM(J5:J29) -> 0 | ... O30: =SUM(O5:O29) -> 76
B33: REVISI FAKTUR BERDASARKAN SC (Salah Harga) | Q33: REVISI FAKTUR BERDASARKAN SC (Salah SO)
B34: Periode Januari - 30 Mei 2026 | Q34: Periode Januari - 30 Mei 2026
B35: SC | C35: Jan | D35: Feb | E35: Mar | F35: Apr | G35: Mei | H35: Jun | I35: Jul | J35: Agst | K35: Sept | L35: Okt | M35: Nov | N35: Des | O35: Total | Q35: SC | R35: Jan | S35: Feb | T35: Mar | U35: Apr | V35: Mei | W35: Jun | X35: Jul | Y35: Agst | Z35: Sept | AA35: Okt | AB35: Nov | AC35: Des | AD35: Total
B36: Ariyani | O36: =SUM(C36:N36) -> 0 | Q36: Ariyani | AD36: =SUM(R36:AC36) -> 0
B37: Online | O37: =SUM(C37:N37) -> 0 | Q37: Online | AD37: =SUM(R37:AC37) -> 0
B38: Faris | O38: =SUM(C38:N38) -> 0 | Q38: Faris | AD38: =SUM(R38:AC38) -> 0
B39: Syahra | O39: =SUM(C39:N39) -> 0 | Q39: Syahra | AD39: =SUM(R39:AC39) -> 0
B40: Reni | C40: 1 | O40: =SUM(C40:N40) -> 1 | Q40: Reni | AD40: =SUM(R40:AC40) -> 0
B41: Yuyun | F41: 1 | O41: =SUM(C41:N41) -> 1 | Q41: Yuyun | AD41: =SUM(R41:AC41) -> 0
B42: Zakia | C42: 1 | O42: =SUM(C42:N42) -> 1 | Q42: Zakia | R42: 1 | AD42: =SUM(R42:AC42) -> 1
B43: TOTAL | C43: =SUM(C36:C42) -> 2 | D43: =SUM(D36:D42) -> 0 | E43: =SUM(E36:E42) -> 0 | F43: =SUM(F36:F42) -> 1 | G43: =SUM(G36:G42) -> 0 | H43: =SUM(H36:H42) -> 0 | I43: =SUM(I36:I42) -> 0 | J43: =SUM(J36:J42) -> 0 | ... O43: =SUM(O36:O42) -> 3 | Q43: TOTAL | R43: =SUM(R36:R42) -> 1 | S43: =SUM(S36:S42) -> 0 | T43: =SUM(T36:T42) -> 0 | U43: =SUM(U36:U42) -> 0 | V43: =SUM(V36:V42) -> 0 | W43: =SUM(W36:W42) -> 0 | X43: =SUM(X36:X42) -> 0 | Y43: =SUM(Y36:Y42) -> 0 | ... AD43: =SUM(AD36:AD42) -> 1
B45: JUMLAH Per Barang yang Tertera di SO | Q45: JUMLAH Per Barang yang Tertera di SO
B46: SC | C46: Jan | D46: Feb | E46: Mar | F46: Apr | G46: Mei | H46: Jun | I46: Jul | J46: Agst | K46: Sept | L46: Okt | M46: Nov | N46: Des | O46: Total | Q46: SC | R46: Jan | S46: Feb | T46: Mar | U46: Apr | V46: Mei | W46: Jun | X46: Jul | Y46: Agst | Z46: Sept | AA46: Okt | AB46: Nov | AC46: Des | AD46: Total
B47: Ariyani | C47: 926 | D47: 824 | E47: 692 | F47: 871 | G47: 870 | O47: =SUM(C47:N47) -> 4183 | Q47: Ariyani | R47: 926 | S47: 824 | T47: 692 | U47: 871 | V47: 870 | AD47: =SUM(R47:AC47) -> 4183
B48: Online | C48: 252 | D48: 257 | E48: 174 | F48: 265 | G48: 149 | O48: =SUM(C48:N48) -> 1097 | Q48: Online | R48: 252 | S48: 257 | T48: 174 | U48: 265 | V48: 149 | AD48: =SUM(R48:AC48) -> 1097
B49: Faris | C49: 1773 | D49: 1641 | E49: 1303 | F49: 1635 | G49: 1509 | O49: =SUM(C49:N49) -> 7861 | Q49: Faris | R49: 1773 | S49: 1641 | T49: 1303 | U49: 1635 | V49: 1509 | AD49: =SUM(R49:AC49) -> 7861
B50: Syahra | C50: 644 | D50: 181 | E50: 448 | F50: 682 | G50: 684 | O50: =SUM(C50:N50) -> 2639 | Q50: Syahra | R50: 644 | S50: 181 | T50: 448 | U50: 682 | V50: 684 | AD50: =SUM(R50:AC50) -> 2639
B51: Reni | C51: 900 | D51: 1129 | E51: 847 | F51: 918 | G51: 787 | O51: =SUM(C51:N51) -> 4581 | Q51: Reni | R51: 900 | S51: 1129 | T51: 847 | U51: 918 | V51: 787 | AD51: =SUM(R51:AC51) -> 4581
B52: Yuyun | C52: 1442 | D52: 1122 | E52: 944 | F52: 1385 | G52: 1235 | O52: =SUM(C52:N52) -> 6128 | Q52: Yuyun | R52: 1442 | S52: 1122 | T52: 944 | U52: 1385 | V52: 1235 | AD52: =SUM(R52:AC52) -> 6128
B53: Zakia | C53: 1266 | D53: 1062 | E53: 848 | F53: 1146 | G53: 1028 | O53: =SUM(C53:N53) -> 5350 | Q53: Zakia | R53: 1266 | S53: 1062 | T53: 848 | U53: 1146 | V53: 1028 | AD53: =SUM(R53:AC53) -> 5350
B54: Purchasing | O54: =SUM(C54:N54) -> 0 | Q54: Supriyanto/Nadia | AD54: =SUM(R54:AC54) -> 0
B55: Others | C55: 153 | D55: 122 | E55: 69 | F55: 160 | G55: 132 | O55: =SUM(C55:N55) -> 636 | Q55: Others | R55: 153 | S55: 122 | T55: 69 | U55: 160 | V55: 132 | AD55: =SUM(R55:AC55) -> 636
B56: Non SC | O56: =SUM(C56:N56) -> 0 | Q56: Heru | AD56: =SUM(R56:AC56) -> 0
B57: Keuangan | O57: =SUM(C57:N57) -> 0 | Q57: Wira | AD57: =SUM(R57:AC57) -> 0
B58: MIA | C58: 60 | D58: 33 | E58: 65 | F58: 50 | G58: 45 | O58: =SUM(C58:N58) -> 253 | Q58: MIA | R58: 60 | S58: 33 | T58: 65 | U58: 50 | V58: 45 | AD58: =SUM(R58:AC58) -> 253
B59: TOTAL | C59: =SUM(C47:C58) -> 7416 | D59: =SUM(D47:D58) -> 6371 | E59: =SUM(E47:E58) -> 5390 | F59: =SUM(F47:F58) -> 7112 | G59: =SUM(G47:G58) -> 6439 | H59: =SUM(H47:H58) -> 0 | I59: =SUM(I47:I58) -> 0 | J59: =SUM(J47:J58) -> 0 | ... O59: =SUM(O47:O58) -> 32728 | Q59: TOTAL | R59: =SUM(R47:R58) -> 7416 | S59: =SUM(S47:S58) -> 6371 | T59: =SUM(T47:T58) -> 5390 | U59: =SUM(U47:U58) -> 7112 | V59: =SUM(V47:V58) -> 6439 | W59: =SUM(W47:W58) -> 0 | X59: =SUM(X47:X58) -> 0 | Y59: =SUM(Y47:Y58) -> 0 | ... AD59: =SUM(AD47:AD58) -> 32728
B60: % REVISI FAKTUR TERHADAP TOTAL BARANG | Q60: % REVISI FAKTUR TERHADAP TOTAL BARANG
B61: SC | C61: Jan | D61: Feb | E61: Mar | F61: Apr | G61: Mei | H61: Jun | I61: Jul | J61: Agst | K61: Sept | L61: Okt | M61: Nov | N61: Des | O61: Total | Q61: SC | R61: Jan | S61: Feb | T61: Mar | U61: Apr | V61: Mei | W61: Jun | X61: Jul | Y61: Agst | Z61: Sept | AA61: Okt | AB61: Nov | AC61: Des | AD61: Total
B62: Ariyani | C62: =+C36/C47 -> 0 | D62: =+D36/D47 -> 0 | E62: =+E36/E47 -> 0 | F62: =+F36/F47 -> 0 | G62: =+G36/G47 -> 0 | H62: =+H36/H47 -> #DIV/0! | I62: =+I36/I47 -> #DIV/0! | J62: =+J36/J47 -> #DIV/0! | ... O62: =+O36/O47 -> 0 | Q62: Ariyani | R62: =+R36/R47 -> 0 | S62: =+S36/S47 -> 0 | T62: =+T36/T47 -> 0 | U62: =+U36/U47 -> 0 | V62: =+V36/V47 -> 0 | W62: =+W36/W47 -> #DIV/0! | X62: =+X36/X47 -> #DIV/0! | Y62: =+Y36/Y47 -> #DIV/0! | ... AD62: =+AD36/AD47 -> 0
B63: Online | C63: =C37/C48 -> 0 | D63: =D37/D48 -> 0 | E63: =+E37/E48 -> 0 | F63: =F37/F48 -> 0 | G63: =G37/G48 -> 0 | H63: =H37/H48 -> #DIV/0! | I63: =I37/I48 -> #DIV/0! | J63: =J37/J48 -> #DIV/0! | K63: =K37/K48 -> #DIV/0! | L63: =L37/L48 -> #DIV/0! | M63: =M37/M48 -> #DIV/0! | ... O63: =O37/O48 -> 0 | Q63: Online | R63: =R37/R48 -> 0 | S63: =S37/S48 -> 0 | T63: =+T37/T48 -> 0 | U63: =U37/U48 -> 0 | V63: =V37/V48 -> 0 | W63: =W37/W48 -> #DIV/0! | X63: =X37/X48 -> #DIV/0! | Y63: =Y37/Y48 -> #DIV/0! | Z63: =Z37/Z48 -> #DIV/0! | AA63: =AA37/AA48 -> #DIV/0! | AB63: =AB37/AB48 -> #DIV/0! | ... AD63: =AD37/AD48 -> 0
B64: Faris | C64: =+C38/C49 -> 0 | D64: =+D38/D49 -> 0 | E64: =+E38/E49 -> 0 | F64: =+F38/F49 -> 0 | G64: =+G38/G49 -> 0 | H64: =+H38/H49 -> #DIV/0! | I64: =+I38/I49 -> #DIV/0! | J64: =+J38/J49 -> #DIV/0! | ... O64: =+O38/O49 -> 0 | Q64: Faris | R64: =+R38/R49 -> 0 | S64: =+S38/S49 -> 0 | T64: =+T38/T49 -> 0 | U64: =+U38/U49 -> 0 | V64: =+V38/V49 -> 0 | W64: =+W38/W49 -> #DIV/0! | X64: =+X38/X49 -> #DIV/0! | Y64: =+Y38/Y49 -> #DIV/0! | ... AD64: =+AD38/AD49 -> 0
B65: Syahra | C65: =+C39/C50 -> 0 | D65: =+D39/D50 -> 0 | E65: =+E39/E50 -> 0 | F65: =+F39/F50 -> 0 | G65: =+G39/G50 -> 0 | H65: =+H39/H50 -> #DIV/0! | I65: =+I39/I50 -> #DIV/0! | J65: =+J39/J50 -> #DIV/0! | ... O65: =+O39/O50 -> 0 | Q65: Syahra | R65: =+R39/R50 -> 0 | S65: =+S39/S50 -> 0 | T65: =+T39/T50 -> 0 | U65: =+U39/U50 -> 0 | V65: =+V39/V50 -> 0 | W65: =+W39/W50 -> #DIV/0! | X65: =+X39/X50 -> #DIV/0! | Y65: =+Y39/Y50 -> #DIV/0! | ... AD65: =+AD39/AD50 -> 0
B66: Reni | C66: =C40/C51 -> 0.0011111111 | D66: =D40/D51 -> 0 | E66: =+E40/E51 -> 0 | F66: =F40/F51 -> 0 | G66: =G40/G51 -> 0 | H66: =H40/H51 -> #DIV/0! | I66: =I40/I51 -> #DIV/0! | J66: =J40/J51 -> #DIV/0! | K66: =K40/K51 -> #DIV/0! | L66: =L40/L51 -> #DIV/0! | M66: =M40/M51 -> #DIV/0! | ... O66: =O40/O51 -> 0.00021829295 | Q66: Reni | R66: =R40/R51 -> 0 | S66: =S40/S51 -> 0 | T66: =+T40/T51 -> 0 | U66: =U40/U51 -> 0 | V66: =V40/V51 -> 0 | W66: =W40/W51 -> #DIV/0! | X66: =X40/X51 -> #DIV/0! | Y66: =Y40/Y51 -> #DIV/0! | Z66: =Z40/Z51 -> #DIV/0! | AA66: =AA40/AA51 -> #DIV/0! | AB66: =AB40/AB51 -> #DIV/0! | ... AD66: =AD40/AD51 -> 0
B67: Yuyun | C67: =C41/C52 -> 0 | D67: =D41/D52 -> 0 | E67: =+E41/E52 -> 0 | F67: =F41/F52 -> 0.00072202166 | G67: =G41/G52 -> 0 | H67: =H41/H52 -> #DIV/0! | I67: =I41/I52 -> #DIV/0! | J67: =J41/J52 -> #DIV/0! | K67: =K41/K52 -> #DIV/0! | L67: =L41/L52 -> #DIV/0! | M67: =M41/M52 -> #DIV/0! | ... O67: =O41/O52 -> 0.00016318538 | Q67: Yuyun | R67: =R41/R52 -> 0 | S67: =S41/S52 -> 0 | T67: =+T41/T52 -> 0 | U67: =U41/U52 -> 0 | V67: =V41/V52 -> 0 | W67: =W41/W52 -> #DIV/0! | X67: =X41/X52 -> #DIV/0! | Y67: =Y41/Y52 -> #DIV/0! | Z67: =Z41/Z52 -> #DIV/0! | AA67: =AA41/AA52 -> #DIV/0! | AB67: =AB41/AB52 -> #DIV/0! | ... AD67: =AD41/AD52 -> 0
B68: Zakia | C68: =C42/C53 -> 0.00078988942 | D68: =D42/D53 -> 0 | E68: =+E42/E53 -> 0 | F68: =F42/F53 -> 0 | G68: =G42/G53 -> 0 | H68: =H42/H53 -> #DIV/0! | I68: =I42/I53 -> #DIV/0! | J68: =J42/J53 -> #DIV/0! | K68: =K42/K53 -> #DIV/0! | L68: =L42/L53 -> #DIV/0! | M68: =M42/M53 -> #DIV/0! | ... O68: =O42/O53 -> 0.00018691589 | Q68: Zakia | R68: =R42/R53 -> 0.00078988942 | S68: =S42/S53 -> 0 | T68: =+T42/T53 -> 0 | U68: =U42/U53 -> 0 | V68: =V42/V53 -> 0 | W68: =W42/W53 -> #DIV/0! | X68: =X42/X53 -> #DIV/0! | Y68: =Y42/Y53 -> #DIV/0! | Z68: =Z42/Z53 -> #DIV/0! | AA68: =AA42/AA53 -> #DIV/0! | AB68: =AB42/AB53 -> #DIV/0! | ... AD68: =AD42/AD53 -> 0.00018691589
B69: TOTAL | C69: =C43/C59 -> 0.00026968716 | D69: =D43/D59 -> 0 | E69: =E43/E59 -> 0 | F69: =F43/F59 -> 0.00014060742 | G69: =G43/G59 -> 0 | H69: =H43/H59 -> #DIV/0! | I69: =I43/I59 -> #DIV/0! | J69: =J43/J59 -> #DIV/0! | ... O69: =O43/O59 -> 9.166463e-05 | Q69: TOTAL | R69: =R43/R59 -> 0.00013484358 | S69: =S43/S59 -> 0 | T69: =T43/T59 -> 0 | U69: =U43/U59 -> 0 | V69: =V43/V59 -> 0 | W69: =W43/W59 -> #DIV/0! | X69: =X43/X59 -> #DIV/0! | Y69: =Y43/Y59 -> #DIV/0! | ... AD69: =AD43/AD59 -> 3.0554877e-05
B70: Target 0 Salah Harga | Q70: Target 0 Salah SO
B76: REVISI FAKTUR BERDASARKAN ADMIN SC
B77: Periode Januari - 30 Mei 2026
B78: Adm. SC | C78: Jan | D78: Feb | E78: Mar | F78: Apr | G78: Mei | H78: Jun | I78: Jul | J78: Agst | K78: Sept | L78: Okt | M78: Nov | N78: Des | O78: Total
B79: Nina | F79: 1 | O79: =SUM(C79:N79) -> 1
B80: Nita | O80: =SUM(C80:N80) -> 0
B81: Nanda | O81: =SUM(C81:N81) -> 0
B82: Dwi | E82: 4 | O82: =SUM(C82:N82) -> 4
B83: Nonik | O83: =SUM(C83:N83) -> 0
B84: Grand Total | C84: =SUM(C79:C83) -> 0 | D84: =SUM(D79:D83) -> 0 | E84: =SUM(E79:E83) -> 4 | F84: =SUM(F79:F83) -> 1 | G84: =SUM(G79:G82) -> 0 | H84: =SUM(H79:H82) -> 0 | I84: =SUM(I79:I82) -> 0 | J84: =SUM(J79:J82) -> 0 | K84: =SUM(K79:K82) -> 0 | L84: =SUM(L79:L82) -> 0 | M84: =SUM(M79:M82) -> 0 | N84: =SUM(N79:N82) -> 0 | O84: =SUM(O79:O83) -> 5
B85: JUMLAH INPUT BARANG
B86: Adm. SC | C86: Jan | D86: Feb | E86: Mar | F86: Apr | G86: Mei | H86: Jun | I86: Jul | J86: Agst | K86: Sept | L86: Okt | M86: Nov | N86: Des | O86: Total | P86: Rata" Produksi Faktur per bulan
B87: Nina | C87: 3558 | D87: 3092 | E87: 3116 | F87: 3740 | G87: 3410 | O87: =SUM(C87:N87) -> 16916 | P87: =O87/1 -> 16916
B88: Nita | C88: 269 | D88: 207 | E88: 246 | F88: 228 | G88: 200 | O88: =SUM(C88:N88) -> 1150 | P88: =O88/1 -> 1150
B89: Nanda | C89: 3565 | D89: 3038 | E89: 325 | F89: 0 | G89: 0 | O89: =SUM(C89:N89) -> 6928 | P89: =O89/1 -> 6928
B90: Dwi | C90: 0 | D90: 0 | E90: 1692 | F90: 0 | G90: 0 | O90: =SUM(C90:N90) -> 1692 | P90: =O90/1 -> 1692
B91: Nonik | C91: 0 | D91: 0 | E91: 0 | F91: 3084 | G91: 2789 | O91: =SUM(C91:N91) -> 5873 | P91: =O91/1 -> 5873
B92: Keuangan | C92: 24 | D92: 34 | E92: 11 | F92: 60 | G92: 40 | O92: =SUM(C92:N92) -> 169 | P92: =O92/1 -> 169
B93: Grand | C93: =SUM(C87:C92) -> 7416 | D93: =SUM(D87:D92) -> 6371 | E93: =SUM(E87:E92) -> 5390 | F93: =SUM(F87:F92) -> 7112 | G93: =SUM(G87:G92) -> 6439 | H93: =SUM(H87:H92) -> 0 | I93: =SUM(I87:I92) -> 0 | J93: =SUM(J87:J92) -> 0 | ... O93: =SUM(O87:O92) -> 32728 | P93: =O93/2 -> 16364
B94: % REVISI FAKTUR TERHADAP TOTAL INPUT BARANG
B95: Adm. SC | C95: Jan | D95: Feb | E95: Mar | F95: Apr | G95: Mei | H95: Jun | I95: Jul | J95: Agst | K95: Sept | L95: Okt | M95: Nov | N95: Des | O95: Total
B96: Nia | C96: =#REF!/#REF! -> #REF! | D96: =+#REF!/#REF! -> #REF! | E96: =+#REF!/#REF! -> #REF! | F96: =+#REF!/#REF! -> #REF! | G96: =+#REF!/#REF! -> #REF! | H96: 0 | I96: =+#REF!/#REF! -> #REF! | J96: =+#REF!/#REF! -> #REF! | K96: =+#REF!/#REF! -> #REF! | L96: =+#REF!/#REF! -> #REF! | M96: 0 | N96: 0 | O96: =#REF!/#REF! -> #REF! | P96: Target 0 Salah Input Admin
B97: Nina | C97: =C79/C87 -> 0 | D97: =D79/D87 -> 0 | E97: =E79/E87 -> 0 | F97: =F79/F87 -> 0.00026737968 | G97: =G79/G87 -> 0 | H97: =H79/H87 -> #DIV/0! | I97: =I79/I87 -> #DIV/0! | J97: =J79/J87 -> #DIV/0! | ... O97: =O79/O87 -> 5.911563e-05
B98: Nita | C98: =C80/C88 -> 0 | D98: =D80/D88 -> 0 | E98: =E80/E88 -> 0 | F98: =F80/F88 -> 0 | G98: =G80/G88 -> 0 | H98: =H80/H88 -> #DIV/0! | I98: =I80/I88 -> #DIV/0! | J98: =J80/J88 -> #DIV/0! | ... O98: =O80/O88 -> 0
B99: Nanda | C99: =C81/C89 -> 0 | D99: =D81/D89 -> 0 | E99: =E81/E89 -> 0 | F99: 0 | G99: 0 | H99: =H81/H89 -> #DIV/0! | I99: =I81/I89 -> #DIV/0! | J99: =J81/J89 -> #DIV/0! | K99: =K81/K89 -> #DIV/0! | L99: =L81/L89 -> #DIV/0! | M99: =M81/M89 -> #DIV/0! | N99: =N81/N89 -> #DIV/0! | O99: =O81/O89 -> 0
B100: Dwi | C100: 0 | D100: 0 | E100: =E82/E90 -> 0.0023640662 | F100: 0 | G100: 0 | O100: =O82/O90 -> 0.0023640662
B101: Nonik | C101: 0 | D101: 0 | E101: 0 | F101: =F83/F91 -> 0 | G101: =G83/G91 -> 0 | O101: =O83/O91 -> 0
B102: Grand Total | C102: =+C84/C93 -> 0 | D102: =+D84/D93 -> 0 | E102: =+E84/E93 -> 0.00074211503 | F102: =+F84/F93 -> 0.00014060742 | G102: =+G84/G93 -> 0 | H102: =+H84/H93 -> #DIV/0! | I102: =+I84/I93 -> #DIV/0! | J102: =+J84/J93 -> #DIV/0! | ... O102: =+O84/O93 -> 0.00015277438

Sheet DATA (Per Barang)
A1: Bulan | B1: Tanggal Revisi | C1: Tanggal Faktur | D1: No. Faktur | E1: Admin SC | F1: SC | G1: Cust | H1: Keterangan | I1: Total | J1: Alasan | K1: Klasifikasi
A2: Januari | B2: 46027 | C2: 46007 | D2: B25016568 | E2: Nanda | F2: Sheila | G2: Nurhanifah | H2: Batal | I2: 2225000 | J2: Kios tidak transfer. | K2: Kios Batal TRF/ Tidak Tepat Janji
A3: Januari | B3: 46027 | C3: 46007 | D3: B25016590 | E3: Nanda | F3: Sheila | G3: Nurhanifah | H3: Batal | I3: 1407500 | J3: Kios tidak transfer. | K3: Kios Batal TRF/ Tidak Tepat Janji
A4: Januari | B4: 46028 | C4: 46025 | D4: D26000208 | E4: Nina | F4: Faris | G4: Akbar Tani, UD | H4: Karissnail 6 PL 20 X 500 gr (M2U)* (edit qty jadi 5 box 17 pack) | I4: 10419000 | J4: Retur, barang bocor | K4: Retur
A5: Januari | B5: 46028 | C5: 46013 | D5: A25002336 | E5: Nanda | F5: Sheila | G5: Online Shop Shopee | H5: Batal | I5: 944120 | J5: Retur, Alasan pembeli yg dikirim salah, padahal barang sudah sesuai pesanan | K5: Retur
A6: Januari | B6: 46030 | C6: 46030 | D6: D26000505 | E6: Nina | F6: Zakia | G6: Tenggulun Tani | H6: Antracol 70 WP 20 X 500 gr (edit harga 79.000) | I6: 33387500 | J6: SC salah harga (harga awal 78.000) | K6: Salah harga Oleh SC
A7: Januari | B7: 46031 | C7: 46024 | D7: A26000002 | E7: Nanda | F7: Sheila | G7: Online Shop Shopee | H7: Batal | I7: 57147 | J7: Shopee tidak dapat memproses krna alamat kirim terdampak banjir, info gudang belum kirim | K7: Lain - Lain (Acc oleh Direktur, Hpp berubah)
A8: Januari | B8: 46032 | C8: 46031 | D8: D26000595 | E8: Nina | F8: Reni | G8: Tani Sejati/Meggie | H8: Curacron 500 EC 40 X 250 ml (edit qty jadi 50box) | I8: 133000000 | J8: Kios merevisi qty order, karena expired pendek. | K8: Permintaan Cust (Ganti Kemasan, Ganti Identitas Pajak, Habis Musim, Ganti Qty)
A9: Januari | B9: 46034 | C9: 46029 | D9: A26000059 | E9: Nanda | F9: Sheila | G9: Online Shop Tik tok | H9: Batal | I9: 85250 | J9: Retur, Pembeli membatalkan pesanan sebelum barang dikirim oleh ekspedisi. | K9: Retur
A10: Januari | B10: 46034 | C10: 46028 | D10: B26000321 | E10: Nanda | F10: Faris | G10: Ahmad Mahsun Fuadi | H10: Batal | I10: 425000 | J10: Kios batal order karena barang belum dikirim, sedangkan hari ini rencana dibawa ke luar pulau. | K10: Pembatalan Order Oleh Kios
A11: Januari | B11: 46035 | C11: 46034 | D11: A26000086 | E11: Nanda | F11: Sheila | G11: Online Shop Shopee | H11: Batal | I11: 158020 | J11: Pembatalan otomatis dari shopee karena customer tidak melakukan pembayaran non COD. | K11: Pembatalan Order Oleh Kios
A12: Januari | B12: 46039 | C12: 46024 | D12: A26000028 | E12: Nanda | F12: Sheila | G12: Online Shop Tik tok | H12: Batal | I12: 70250 | J12: Retur, Pembeli membatalkan pesanan sebelum barang dikirim oleh ekspedisi. | K12: Retur
A13: Januari | B13: 46044 | C13: 46042 | D13: B26001039 | E13: Nanda | F13: Reni | G13: Karisma Bumi Indah/Fedo | H13: Piraklo 250 EC 40 X 250 ml* (coret) | I13: 75850000 | J13: retur, SC Double SO | K13: Salah SO Oleh SC
... A77: Mei | B77: 46168 | C77: 46165 | D77: D26008009 | E77: Nina | F77: Ariyani | G77: Hariyono Sby | H77: Batal | I77: 13200000 | J77: Kios Batal Order karena saat barang sampai disana cust bilang klo stok dia masih ada dan exp 11/26, Barang langsung dikirim ke Damai Samsuri | K77: Pembatalan Order Oleh Kios

Sheet Sheet1
B5: KET | C5: JAN S/D JULI | D5: ACTUAL AGU | E5: TARGET SEP | F5: TARGET OKT | G5: TARGET NOV | H5: TARGET DES | I5: TOTAL
B6: RETUR | C6: 2.0410742e+08 | D6: 16333333 | E6: 20000000 | F6: 20000000 | G6: 20000000 | H6: 20000000 | I6: =SUM(C6:H6) -> 3.0044075e+08
B7: Akm Ret | C7: 2.0410742e+08 | D7: =+C7+D6 -> 2.2044075e+08 | E7: =+D7+E6 -> 2.4044075e+08 | F7: =+E7+F6 -> 2.6044075e+08 | G7: =+F7+G6 -> 2.8044075e+08 | H7: =+G7+H6 -> 3.0044075e+08
B8: OMSET | C8: 6.8512185e+11 | D8: 1.2083392e+11 | E8: 124606187766 | F8: 128274928261 | G8: 109272641244 | H8: 96591319894 | I8: =SUM(C8:H8) -> 1.2647008e+12
B9: Akm Oms | C9: 6.8512185e+11 | D9: =+C9+D8 -> 8.0595577e+11 | E9: =+D9+E8 -> 9.3056196e+11 | F9: =+E9+F8 -> 1.0588369e+12 | G9: =+F9+G8 -> 1.1681095e+12 | H9: =+G9+H8 -> 1.2647008e+12
B10: % | C10: =+C6/C8 -> 0.00029791404 | D10: =+D7/D9 -> 0.0002735147 | E10: =+E7/E9 -> 0.00025838231 | F10: =+F7/F9 -> 0.00024596872 | G10: =+G7/G9 -> 0.00024008087 | H10: =+H7/H9 -> 0.00023755875 | I10: =I6/I8 -> 0.00023755875
B12: Target Retur 0.03%
B15: KET | C15: JAN S/D JULI | D15: ACTUAL AGU | E15: TARGET SEP | F15: TARGET OKT | G15: TARGET NOV | H15: TARGET DES | I15: TOTAL
B16: Salah SO | C16: 8 | D16: 0 | E16: 0 | F16: 0 | G16: 0 | H16: 0 | I16: =SUM(C16:H16) -> 8
B17: Akm Salah Harga | C17: 8 | D17: 8 | E17: 8 | F17: 8 | G17: 8 | H17: 8
B18: Salah Harga | C18: 7 | D18: 0 | E18: 1 | F18: 1 | G18: 1 | H18: 1 | I18: =SUM(C18:H18) -> 11
B19: Akm Salah Harga | C19: 7 | D19: =+C19+D18 -> 7 | E19: =+D19+E18 -> 8 | F19: =+E19+F18 -> 9 | G19: =+F19+G18 -> 10 | H19: =+G19+H18 -> 11
B20: Jumlah Faktur | C20: 46985 | D20: 6857 | E20: 5629 | F20: 7006 | G20: 6187 | H20: 6450 | I20: =SUM(C20:H20) -> 79114
B21: Akm Jumlah Fak | C21: 46985 | D21: =+C21+D20 -> 53842 | E21: =+D21+E20 -> 59471 | F21: =+E21+F20 -> 66477 | G21: =+F21+G20 -> 72664 | H21: =+G21+H20 -> 79114
B22: Salah SO (%) | C22: =+C17/C21 -> 0.00017026711 | D22: =+D17/D21 -> 0.00014858289 | E22: =+E17/E21 -> 0.00013451935 | F22: =+F17/F21 -> 0.00012034237 | G22: =+G17/G21 -> 0.00011009578 | H22: =+H17/H21 -> 0.0001011199 | I22: =+I16/I20 -> 0.0001011199
B23: Salah Harga (%) | C23: =+C19/C21 -> 0.00014898372 | D23: =+D19/D21 -> 0.00013001003 | E23: =+E19/E21 -> 0.00013451935 | F23: =+F19/F21 -> 0.00013538517 | G23: =+G19/G21 -> 0.00013761973 | H23: =+H19/H21 -> 0.00013903987 | I23: 0.00016661967
B25: Target Salah Harga 0.02%
B26: Target SO 0.01%

Sheet Update Revisi Faktur Harian
A1: No | B1: Tanggal Revisi | C1: Tanggal Faktur | D1: No. Faktur | E1: Adm SC | F1: SC | G1: Cust | H1: Keterangan | I1: Total | J1: Klasifikasi | K1: Berdasarkan Bukti
A2: 6 | B2: 44938 | C2: 44936 | D2: B23000256 | E2: Nia | F2: Zakia | G2: Sumber Makmur/Mahrus | H2: Manzate 82 WP 20 X 500 gr (edit harga jadi 47.000) | I2: 1880000 | J2: √ | K2: ACC Bu Anne (harga awal 48.000) | L2: Lain-lain
A3: 7 | B3: 44939 | C3: 44938 | D3: C23000237 | E3: Fani | F3: Elok | G3: Kumpul Tani/Hendro | H3: Android 72 EC 50 X 80 ml (edit harga jadi 55.000) | I3: 5770000 | J3: √ | K3: ACC Pak Agoes (harga awal 59.000) | L3: Lain-lain
A4: 3 | B4: 44937 | C4: 44937 | D4: D23000279 | E4: Nina | F4: Evi | G4: KIU Cabang | H4: Bionik 400 EC 20 X 500 ml (hapus VAT) | I4: 21813168 | J4: √ | K4: Admin salah input | L4: Admin SC
A5: 15 | B5: 44949 | C5: 44943 | D5: D23000391 | E5: Nina | F5: Yuyun | G5: Erfan SK | H5: Amabas 500 EC 16 X 1 ltr (edit harga jadi 67.600) | I5: 67600 | J5: √ | K5: barang bocor, petugas minta harga HPP, ACC Pak Supri (harga awal 74.000) | L5: Lain-lain
A6: 22 | B6: 44953 | C6: 44952 | D6: C23000595 | E6: Fani | F6: Riyan | G6: Nurkholil, UD | H6: ganti kontak person jadi Taufan Firmansyah | I6: 8160000 | J6: √ | K6: cust lama tanpa ID, kirim KTP berbeda dgn nama kontak person sebelumnya | L6: Cust
A7: 34 | B7: 44943 | C7: 44943 | D7: E23000478 | E7: Umi | F7: Nita | G7: Sahabat Tani, UD/Edy | H7: Batal | I7: 10080000 | J7: BATAL | K7: Double SO | L7: SC
A8: 10 | B8: 44944 | C8: 44943 | D8: D23000406 | E8: Nina | F8: Yuyun | G8: Hasil Usaha, UD | H8: Jagung NK 7328 20 X 1 kg (edit harga jadi 104.000) | I8: 18500000 | J8: √ | K8: harga di up (harga awal 103.500) | L8: Lain-lain
A9: 9 | B9: 44942 | C9: 44942 | D9: D23000376 | E9: Nina | F9: Yuyun | G9: Suwadi BCA | H9: Kac. Panj. Katrina 90 X 100 gr (edit harga jadi 20.000) | I9: 10470000 | J9: √ | K9: hpp berubah | L9: Lain-lain
A10: 25 | B10: 44956 | C10: 44956 | D10: B23000960 | E10: Nia | F10: Zakia | G10: Agro Tani Sejahtera/Ni Putu Esthi | H10: Regent Red 80 X 50 ml (edit harga jadi 19.000) | I10: 3727300 | J10: √ | K10: kenaikan harga PL (harga awal 18.500) | L10: Lain-lain
A11: 26 | B11: 44956 | C11: 44956 | D11: B23000960 | E11: Nia | F11: Zakia | G11: Agro Tani Sejahtera/Ni Putu Esthi | H11: Regent Red 48 X 100 ml (edit harga jadi 36.350) | I11: 3727300 | J11: √ | K11: kenaikan harga PL (harga awal 35.500) | L11: Lain-lain
A12: 24 | B12: 44956 | C12: 44954 | D12: D23000719 | E12: Nina | F12: Yuyun | G12: Sukses Makmur | H12: Melon Leoni F1 12 X 10 X 20 gr (edit harga jadi 162.500) | I12: 1050500 | J12: √ | K12: nego harga dengan cust (harga awal 165.000), Harga PL 160.000 | L12: Permintaan Cust
A13: 14 | B13: 44949 | C13: 44939 | D13: B23000357 | E13: Nia | F13: Zakia | G13: Rejeki Tani/Sulantrini | H13: Jagung Bisi 2 20 X 1 kg (edit harga jadi 78.000) | I13: 1560000 | J13: √ | K13: nego harga dengan cust (harga awal 80.000), Harga PL 78.000-80.000 | L13: Permintaan Cust
... A38: 33 | B38: 44936 | C38: 44921 | D38: B22009209 | E38: Riyan | F38: Nia | G38: Mitra Tani, UD/Gunawan | H38: batal | I38: 1545000 | J38: BATAL | K38: terlalu lama kirim | L38: Gudang
A39: 26 | B39: 44970 | C39: 44970 | D39: C23001070 | E39: Fani | F39: Umi | G39: Sahala/Syaiful | H39: Batal | I39: 9925000 | J39: admin salah input, Cust TL Pajak | K39: Admin salah input
A40: 23 | B40: 44967 | C40: 44963 | D40: C23000897 | E40: Fani | F40: Elok | G40: Mona Tani | H40: Ratol 80 P* 10 X 100 X 10 gr (edit qty jadi 47 pack) | I40: 5271750 | J40: barang robek, yg dikirim tgl 7 hanya 47pack | K40: Barang Rusak
A41: 46 | B41: 44980 | C41: 44972 | D41: D23001400 | E41: Nina | F41: Dannis | G41: Ratu Tani/Yusuf | H41: Curacron 500 EC 40 X 250 ml (edit qty jadi 34 box) | I41: 1117660000 | J41: barang atau kemasan bocor (yg dikirim tgl 20 hanya 34 box) | K41: Barang Rusak
A42: 3 | B42: 44959 | C42: 44959 | D42: D23000877 | E42: Nina | F42: Dannis | G42: Hadi Putra, UD | H42: Benang Pe mlg (edit harga jadi 39.500) | I42: 6997500 | J42: nego harga, cust minta batal order kalau tidak bisa nego (harga awal 40.500) PL 39.500 | K42: Harga tidak cocok
A43: 32 | B43: 44971 | C43: 44971 | D43: C23001154 | E43: Fani | F43: Riyan | G43: Gudang Sumber Waras/Ogy | H43: Batal | I43: 2700000 | J43: Cust sudah dapat dari kios lain, tidak cocok harga | K43: Harga tidak cocok
A44: 43 | B44: 44977 | C44: 44973 | D44: D23001534 | E44: Nina | F44: Evi | G44: Rizki Tani/Ratna | H44: batal | I44: 1488000000 | J44: kios tidak cocok harganya (harga dibawah/R2-238.000). | K44: Harga tidak cocok
A45: 25 | B45: 44968 | C45: 44964 | D45: D23001065 | E45: Nina | F45: Zakia | G45: Agro Tani Sejahtera/Ni Putu Esthi | H45: Virtako 300 SC 100 X 50 ml (coret) | I45: 5635000 | J45: kios membatalkan orderan. | K45: sudah dapat dari toko lain
A46: 30 | B46: 44971 | C46: 44971 | D46: C23001163 | E46: Fani | F46: Elok | G46: Agro Lestari/Eko | H46: Batal | I46: 33750000 | J46: ada perubahan program, kios membatalkan orderan. | K46: Toko tidak mau karna ada perubahan program
A47: 31 | B47: 44971 | C47: 44967 | D47: B23001299 | E47: Nia | F47: Yuyun | G47: Topo Yono | H47: Batal | I47: 3840000 | J47: Cust masuk RS dan barang tidak diambil. | K47: Kios Batal Order
A48: 33 | B48: 44971 | C48: 44970 | D48: D23001274 | E48: Nina | F48: Evi | G48: Sentra Agronusa Bhakti, PT | H48: Batal | I48: 11615000 | J48: kios membatalkan orderan. | K48: Dibatalkan dari toko,
A49: 39 | B49: 44973 | C49: 44960 | D49: E23001004 | E49: Nita | F49: Riyan | G49: Usaha Tani/Arbai | H49: batal | I49: 1990000 | J49: kios membatalkan orderan. | K49: Karna tidak dikirim dengan barang Loyant
A50: 45 | B50: 44979 | C50: 44978 | D50: D23001720 | E50: Nina | F50: Dannis | G50: Kawan Tani/Fathor | H50: Batal | I50: 160000000 | J50: kios membatalkan orderan (cust dapat harga lebih murah, info Gudang nota blm kirim, lgsg ganti cust Mitra Tani/Rudiyanto | K50: Kios Batal Order
... A69: 40 | B69: 44973 | C69: 44973 | D69: C23001220 | E69: Fani | F69: Umi | G69: Unggul Jaya/Sholekun | H69: edit nama cust jadi Barokah Tani, UD/Sutrisno | I69: 48000000 | J69: pembagian barang ke Barokah Tani, UD/Sutrisno | K69: Pembagian Barang ke kios Lain
A70: 1 | B70: 44958 | C70: 44957 | D70: T23000084 | F70: Elok | G70: Lestari Jaya | H70: Batal | I70: 1932500 | J70: Permintaan cust. | K70: Karna Pasar sepi
A71: 5 | B71: 44960 | C71: 44960 | D71: B23001130 | E71: Nia | F71: Yuyun | G71: Harry Santoso | H71: Jagung Manis Master Sweet 45 40 X 250 gr (coret) | I71: 24750000 | J71: Permintaan Cust (barang mendekati expired) | K71: Barang mendekati exp
A72: 6 | B72: 44960 | C72: 44959 | D72: E23000996 | E72: Nita | F72: Riyan | G72: Dakon Permai | H72: Nostro 440 EC 50 X 100 ml (edit qty jadi 1 box) | I72: 8960000 | J72: Permintaan Cust . | K72: Cust minta ganti kemasan
A73: 7 | B73: 44960 | C73: 44959 | D73: E23000996 | E73: Nita | F73: Riyan | G73: Dakon Permai | H73: Nostro 440 EC 20 X 500 ml (edit qty jadi 3 box) | I73: 8960000 | J73: Permintaan Cust . | K73: Cust minta ganti kemasan
A74: 8 | B74: 44961 | C74: 44958 | D74: E23000965 | E74: Nita | F74: Umi | G74: Sumber Makmur/Masrokib | H74: Batal | I74: 1600000 | J74: Permintaan cust (habis musim). | K74: Habis musim
A75: 14 | B75: 44965 | C75: 44964 | D75: E23001126 | E75: Nita | F75: Riyan | G75: Yayuk Muzayanah | H75: Pointer 276 SL 20 X 1 ltr New (coret) | I75: 1950000 | J75: Cust tidak bisa jual pointer, order ganti passoxone dan fosfat. | K75: Permintaan Cust | L75: Ganti Barang
A76: 15 | B76: 44965 | C76: 44964 | D76: E23001126 | E76: Nita | F76: Riyan | G76: Yayuk Muzayanah | H76: ganti barang jadi Pupuk Fosfat 50 kg MPS qty 5 zak, harga 150.000 | I76: 1950000 | J76: Cust tidak bisa jual pointer, order ganti passoxone dan fosfat. | K76: Permintaan Cust | L76: Ganti Barang
A77: 16 | B77: 44965 | C77: 44964 | D77: E23001126 | E77: Nita | F77: Riyan | G77: Yayuk Muzayanah | H77: ganti barang jadi Passxone 276 SL 20 X 1 ltr qty 1 box, harga 60.000 | I77: 1950000 | J77: Cust tidak bisa jual pointer, order ganti passoxone dan fosfat. | K77: Permintaan Cust | L77: Ganti Barang
A78: 29 | B78: 44970 | C78: 44968 | D78: D23001241 | E78: Nina | F78: Zakia | G78: Koko Tani | H78: Dellacid 525 EC 20 x 1 ltr (edit jadi Dellacid 525 EC 40 x 200 ml, qty 2 box, harga 35.500) | I78: 7140000 | J78: Permintaan cust. | K78: ganti kemasan
A79: 37 | B79: 44972 | C79: 44951 | D79: B23000805 | E79: Nia | F79: Evi | G79: Herry Djuwarsa/Deka Agro | H79: edit nama cust jadi Herry Djuwarsa | I79: 215500000 | J79: Permintaan cust untuk ubah faktur pajak | K79: Ganti Nama sesuai permintaan toko
A80: 38 | B80: 44972 | C80: 44970 | D80: C23001103 | E80: Fani | F80: Umi | G80: Subur Makmur/Kasim | H80: Batal | I80: 4077600 | J80: Salah SO. | K80: Salah SO
A81: 21 | B81: 44965 | C81: 44965 | D81: D23001098 | E81: Nina | F81: Dannis | G81: Puma Tani | H81: Sprayer Elektrik Joeragan 16 L Battery (edit harga jadi 410.000) | I81: 820000 | J81: SC salah harga (harga awal 395.00) SC tidak liat PL | K81: SC Salah Harga
A82: 22 | B82: 44965 | C82: 44965 | D82: D23001115 | E82: Nina | F82: Zakia | G82: Alam Tani/Wayan | H82: Trisula 450 SL 20 X 500 ml (edit harga jadi 32.500) | I82: 4120000 | J82: SC salah harga (harga awal 52.000) | K82: SC Salah Harga
A83: 44 | B83: 44977 | C83: 44977 | D83: C23001323 | E83: Fani | F83: Elok | G83: Dino Vita, Toko | H83: Karissnail 6 PL 20 X 500 gr (M2U) (edit harga jadi 57.000) | I83: 2280000 | J83: SC salah harga (harga awal 25.000) | K83: SC Salah Harga
A84: 11 | B84: 44964 | C84: 44957 | D84: E23000896 | E84: Nita | F84: Riyan | G84: Barokah Tani/Achmad Rofi'i | H84: NPK 16.16.16+2 MPS 6 X 5 kg (coret) | I84: 2440000 | J84: terlalu lama kirim (info mas feri jg blm kirim). | K84: terlalu lama kirim | L84: ada bukti chat Riyan, belum ada konfirmasi dari distribusi
A85: 12 | B85: 44964 | C85: 44957 | D85: E23000896 | E85: Nita | F85: Riyan | G85: Barokah Tani/Achmad Rofi'i | H85: NPK 16.16.16+2 MPS 50 kg (coret) | I85: 2440000 | J85: terlalu lama kirim (info mas feri jg blm kirim). | K85: terlalu lama kirim | L85: ada bukti chat Riyan, belum ada konfirmasi dari distribusi
A86: 13 | B86: 44964 | C86: 44957 | D86: E23000896 | E86: Nita | F86: Riyan | G86: Barokah Tani/Achmad Rofi'i | H86: Pointer 276 SL 20 X 1 ltr New (edit qty 2 box, edit harga jadi 61.000) | I86: 2440000 | J86: terlalu lama kirim (info mas feri jg blm kirim). | K86: terlalu lama kirim | L86: ada bukti chat Riyan, belum ada konfirmasi dari distribusi
A87: 42 | B87: 44977 | C87: 44966 | D87: E23001237 | E87: Nita | F87: Umi | G87: Sumber Tani/Agus Widjaja | H87: Insure Max 510 FS 100 X 25 ml (edit qty jadi 25 box) | I87: 127580000 | J87: kios salah order (kios takut turun harga)-
A88: 48 | B88: 44982 | C88: 44974 | D88: C23001257 | E88: Fani | F88: Elok | G88: Fortuna Tani/Arif Al Farisi | H88: Manohara 20 X 1 kg (coret) | I88: 2440000 | J88: kios membatalkan orderan manohara.
A89: 25 | B89: 44987 | C89: 44970 | D89: A23000231 | E89: Mitra | F89: Faisal | G89: Aditya Kaharisma Wijaya | H89: Batal | J89: Retur | K89: Retur, cust tidak mau membayar
A90: 1 | B90: 44988 | C90: 44985 | D90: D23002023 | E90: Nina | F90: Evi | G90: Nuansa Tani | H90: Termikon 15 EC 50 X 100 ml (edit qty jadi 16 box) | J90: Barang Rusak | K90: Barang/kemasan rusak (ada bukti foto barang bocor sblm kirim).
A91: 26 | B91: 44988 | C91: 44982 | D91: B23001612 | E91: Nia | F91: Yuyun | G91: Bima Tani Jaya/Kevin Pratama | H91: Score 250 EC 50 X 80 ml (coret) | J91: Retur | K91: retur, harga barang tidak sesuai atau kemahalan
A92: 27 | B92: 44988 | C92: 44982 | D92: B23001612 | E92: Nia | F92: Yuyun | G92: Bima Tani Jaya/Kevin Pratama | H92: Score 250 EC 40 X 250 ml (coret) | J92: Retur | K92: retur, harga barang tidak sesuai atau kemahalan
A93: 8 | B93: 44989 | C93: 44987 | D93: N23000033 | E93: Nina | F93: Dannis | G93: Barokah Jaya Tani/Sabri | H93: Batal | J93: Pembatalan Order oleh Kios | K93: Kios membatalkan orderan(batal karena madura mulai banyak ulat).
A94: 29 | B94: 44989 | C94: 44989 | D94: A23000331 | E94: Mitra | F94: Faisal | G94: Anindita/Surya | H94: Alexis 70 WP 30 X 400 gr (edit qty jadi 15 btl) | J94: Salah SO. | K94: Salah SO.
A95: 18 | B95: 44991 | C95: 44981 | D95: C23001499 | E95: Fani | F95: Umi | G95: Sumber Tani Makmur, CV/Muslim | H95: Batal | J95: Permintaan Cust | K95: permintaan cust (bukti dilampirkan di nota batal).
A96: 20 | B96: 44991 | C96: 44971 | D96: D23001347 | E96: Nina | F96: Evi | G96: Sarana Jiva Nusantara, PT | H96: edit nama toko dan kontak person jadi Jiva Agriculture Indonesia, PT | J96: Permintaan Cust | K96: permintaan cust, info mbak Dewi karena Sarana Jiva per 2023 pindah JAI
A97: 9 | B97: 44992 | C97: 44987 | D97: B23001712 | E97: Nia | F97: Riyan | G97: Sahabat Tani Timur, CV | H97: Batal | J97: Pembayaran Tidak sesuai | K97: Kios tidak komit (kios tidak dapat dihubungi dan tidak komit BG)
A98: 11 | B98: 44992 | C98: 44989 | D98: D23002239 | E98: Nina | F98: Dannis | G98: Fais Tani/Sutiyono | H98: Castora 40 SP 10 X 10 X 100 gr (coret) | J98: Permintaan Cust | K98: Kios salah order.
A99: 12 | B99: 44992 | C99: 44989 | D99: D23002239 | E99: Nina | F99: Dannis | G99: Fais Tani/Sutiyono | H99: tambah Castora 40 SP 50 X 200 gr 3box harga 39.500 | J99: Permintaan Cust | K99: Kios salah order.
A100: 13 | B100: 44992 | C100: 44989 | D100: D23002239 | E100: Nina | F100: Dannis | G100: Fais Tani/Sutiyono | H100: tambah Castora 40 SP 24 X 400 gr 3box harga 74.000 | J100: Permintaan Cust | K100: Kios salah order.
... A117: 6 | B117: 45003 | C117: 45003 | D117: D23002845 | E117: Nina | F117: Evi | G117: Surya, UD/Suryawan | H117: Agil 100 EC 40 X 250 ml (edit harga jadi 35.000) | J117: Lain-lain | K117: atas perintah Bu Anne (harga awal 75.000)
B118: 45008 | C118: 45008 | D118: D23002998 | E118: Nina | F118: Evi | G118: Hermada Tangguh Agro Lestari, PT | H118: Agridex 715 EC 12 X 1 ltr (edit qty jadi 50 box) | J118: Lain-lain | K118: ACC Bu Anne setelah tutupan
B119: 45008 | C119: 45005 | D119: D23002869 | E119: Nina | F119: Zakia | G119: Podo Tani/Supri | H119: Jagung Bisi 220 20 X 1 kg (edit qty jadi 4 box, 5 pack) | J119: Lain-lain | K119: ketentuan dari pabrik (BISI). Petugas terlambat memberi info
B120: 45008 | C120: 45006 | D120: B23002392 | E120: Nia | F120: Zakia | G120: Kawan Tani/Bahrul, H | H120: Jagung Bisi 220 20 X 1 kg (edit qty jad 4 box) | J120: Lain-lain | K120: ketentuan dari pabrik (BISI). Petugas terlambat memberi info
B121: 45008 | C121: 45006 | D121: B23002401 | E121: Nia | F121: Zakia | G121: Tani Sukses/Muklis, H | H121: Jagung Bisi 220 20 X 1 kg (edit qty jad 4 box) | J121: Lain-lain | K121: ketentuan dari pabrik (BISI). Petugas terlambat memberi info
B122: 45008 | C122: 45006 | D122: B23002402 | E122: Nia | F122: Zakia | G122: Sedulur Tani/Eko Galih | H122: Jagung Bisi 220 20 X 1 kg (edit qty jad 4 box) | J122: Lain-lain | K122: ketentuan dari pabrik (BISI). Petugas terlambat memberi info
B123: 45008 | C123: 45006 | D123: B23002390 | E123: Nia | F123: Zakia | G123: Rudi Tani/Rudi | H123: Jagung Bisi 220 20 X 1 kg (edit qty jadi 2 box) | J123: Lain-lain | K123: ketentuan dari pabrik (BISI). Petugas terlambat memberi info
B124: 45008 | C124: 45002 | D124: D23002798 | E124: Nina | F124: Dannis | G124: Al Hikmah | H124: Batal | J124: Pembatalan Order oleh Kios | K124: Kios Minta cepat kirim, tapi belum ada jadwal kirim ke madura.
B125: 45008 | C125: 45008 | D125: C23002208 | E125: Fani | F125: Yuyun | G125: Rizki, UD/Kusnyoto | H125: Jagung Pertiwi 3 20 X 1 kg (edit qty jadi 5 box) | J125: Permintaan Cust | K125: Kios dapat dari tempat lain
A128: 1 | B128: 45017 | C128: 45016 | D128: B23002854 | E128: Nia | F128: Riyan | G128: Dewi Tani/Gunasri | H128: Tali Gawar 989 40 X 600 gr (EDIT QTY JADI 1 BOX) | I128: 1140000 | J128: √ | K128: Permintaan cust | L128: Permintaan cust
A129: 2 | B129: 45017 | C129: 45017 | D129: C23002411 | E129: Fani | F129: Yuyun | G129: Harry Santoso | H129: pindah ke tgl 31/3/23 krn barang akan dimasukkan program maret acc pak agoes) | I129: 24600000 | J129: √ | K129: pindah ke tgl 31/3/23 krn barang akan dimasukkan program maret acc pak agoes) | L129: Lain-lain
A130: 3 | B130: 45017 | C130: 45017 | D130: C23002412 | E130: Fani | F130: Yuyun | G130: Harry Santoso | H130: pindah ke tgl 31/3/23 krn barang akan dimasukkan program maret acc pak agoes) | I130: 405900000 | J130: √ | K130: pindah ke tgl 31/3/23 krn barang akan dimasukkan program maret acc pak agoes) | L130: Lain-lain
A131: 4 | B131: 45019 | C131: 45006 | D131: B23002392 | E131: Nia | F131: Zakia | G131: Kawan Tani/Bahrul, H | H131: Jagung Bisi 220 20 X 1 kg (edit harga jadi 65.000) | I131: 13000000 | J131: √ | K131: krn ketentuan dari bisi qty di kurangi, jadi harga diubah sesuai qty | L131: Lain-lain
A132: 5 | B132: 45019 | C132: 45006 | D132: B23002401 | E132: Nia | F132: Zakia | G132: Tani Sukses/Muklis, H | H132: Jagung Bisi 220 20 X 1 kg (edit harga jadi 65.000) | I132: 5200000 | J132: √ | K132: krn ketentuan dari bisi qty di kurangi, jadi harga diubah sesuai qty | L132: Lain-lain
A133: 6 | B133: 45022 | C133: 45022 | D133: C23002514 | E133: Fani | F133: Yuyun | G133: Helmi Sarwoko | H133: Previcur N 722SL 100 X 100 ml dan score 80 coret | I133: 597500 | J133: √ | K133: Permintaan Cust | L133: Permintaan Cust
A134: 7 | B134: 45022 | C134: 45022 | D134: C23002485 | E134: Fani | F134: Yuyun | G134: Tani Makmur 2 | H134: Ti-Gold 10 WP 10 X 20 X 25 gr (edit harga jadi 15.500) | I134: 31925000 | J134: √ | K134: ACC bu Anne | L134: Lain-lain
A135: 8 | B135: 45026 | C135: 45024 | D135: D23003688 | E135: Nina | F135: Evi | G135: Mohan Putra Mandiri | H135: Jagung NK 212 20 X 1 kg (coret krn dapat harga lebih murah) | I135: 309000000 | J135: √ | K135: Permintaan kios bukti chat wa mb nina | L135: Permintaan Cust
A136: 9 | B136: 45026 | C136: 45022 | D136: B23003099 | E136: Nia | F136: Zakia | G136: Sari Pertiwi, UD | H136: Bactocyn 150 AL 50 X 200 ml (coret) | I136: 1700000 | J136: √ | K136: Permintaan cust buti wa mb zakia | L136: Permintaan Cust
A137: 10 | B137: 45026 | C137: 45022 | D137: D23003632 | E137: Nina | F137: Evi | G137: Rizki Tani/Ratna | H137: tidak jadi batal tapi di ganti qty jadi 100 box | I137: 160000000 | J137: √ | K137: permintaan cust bukti di wa mb nina | L137: Permintaan Cust
A138: 11 | B138: 45026 | C138: 45026 | D138: D23003798 | E138: Nina | F138: Evi | G138: Nugroho Kradenan, UD | H138: edit cust jadi barokah tani/sukardi | I138: 120000000 | J138: √ | K138: permintaan cust bukti di wa mb nina | L138: Pembatalan Order Oleh Kios
A139: 12 | B139: 45027 | C139: 45022 | D139: C23002501 | E139: Fani | F139: Yuyun | G139: Sumber Rejeki/Iwan | H139: Sofia 200/70/30 OD 32 X 250 ml (edit qty jadi 10 btl | I139: 36595000 | J139: √ | K139: Retur permintaan cust bukti wa mb yuyun | L139: Retur
... A163: 14 | B163: 45045 | C163: 45033 | D163: B23003509 | E163: Nia | F163: Riyan | G163: Tani Jaya/Irawan | H163: Batal Order Permintaan Cust | I163: 3375000 | J163: Batal Order Permintaan Cust | K163: Pembatalan Order Oleh Kios | L163: Pembatalan Order Oleh Kios
A164: 1 | B164: 45052 | C164: 45051 | D164: C23002917 | E164: Fani | F164: Elok | G164: Sumber Maju/Agus | H164: Terong Hijo 12 X 15 X 10 gr (Kode Barang A, CORET pindah ke nota M22 ) (sebelum Tutupan) | K164: Admin Salah Input | L164: Admin Salah Input
A165: 2 | B165: 45051 | C165: 45051 | D165: C23002952 | E165: Fani | F165: Elok | G165: Sari Bumi/Alvin | H165: Gandasil B/K 24 X 500 gr (coret yg harga 35.250) awalnya admin salah input, dan mau di ganti tapi barangnya tinggal 18 pack, cust minta 1 box) | K165: Admin Salah Input | L165: Admin Salah Input
A166: 3 | B166: 45059 | C166: 45059 | D166: D23004862 | E166: Nina | F166: Zakia | G166: Tunggal Sumber Rejeki | H166: Abojo 60 WP 100 X 100 gr (edit kms 50 gr ) | K166: Admin salah input | L166: Admin Salah Input
A167: 4 | B167: 45055 | C167: 45052 | D167: B23004052 | E167: Nia | F167: Zakia | G167: Makmur Tani/ Ni Made Muliati | H167: KNO3 Merah P Tani 15 X 2 kg (EDIT QTY JADI 4 BOX) | K167: Zak bocor | L167: Barang Rusak
A168: 5 | B168: 45057 | C168: 45055 | D168: B23004176 | E168: Nia | F168: Umi | G168: Mulyo Tani/Danang | H168: Batal tdk ACC PENGAJUAN PLAFON | K168: Batal tdk ACC PENGAJUAN PLAFON | L168: Lain-lain
A169: 6 | B169: 45054 | C169: 45052 | D169: C23002985 | E169: Fani | F169: Umi | G169: Barokah Tani/Nur Hisan | H169: Batal krn pengajuan plafon tidak ACC | L169: Lain-lain
A170: 7 | B170: 45055 | C170: 45055 | D170: C23003091 | E170: Fani | F170: Elok | G170: Mira Tani 3/Tri | H170: Paratop 276 SL 20 X 1 ltr (CORET) | K170: nyukupkan ACC Plafon 10 JT | L170: Lain-lain
A171: 8 | B171: 45061 | C171: 45061 | D171: C23003319 | E171: Fani | F171: Umi | G171: Sumber Tani Makmur, UD/Suyitno, H | H171: Batal pembagian Barang | L171: Pembagian Barang
A172: 9 | B172: 45061 | C172: 45061 | D172: Z23000913 | E172: Fani | F172: Umi | G172: Sahala/Syaiful | H172: Batal pembagian Barang | L172: Pembagian Barang
A173: 10 | B173: 45050 | C173: 45050 | D173: D23004506 | E173: Nina | F173: Elok | G173: Kumpul Tani 2/Heru | H173: Biggrow 20 WP 4 X 75 X 5 gr (coret orangnya salah order maunya yg forte dan akhirnya barang di oper ke kumpul tani/hendro) orangnya tlp | L173: Pembatalan Order Oleh Kios
A174: 11 | B174: 45051 | C174: 45050 | D174: B23003954 | E174: Nia | F174: Zakia | G174: Delima, Toko/Nurhasan | H174: EM-4 Ternak (LC) 15 X 1 ltr (EDIT BARANG JADI EM TANI | K174: Cust Minta Ganti barang | L174: Permintaan Cust
A175: 12 | B175: 45059 | C175: 45051 | D175: C23002932 | E175: Fani | F175: Riyan | G175: Kadhang Tani/Suwarno | H175: Batal permintaan cust | L175: Permintaan Cust
A176: 13 | B176: 45055 | C176: 45054 | D176: C23003008 | E176: Fani | F176: Umi | G176: Sumber Tani, UD/Basuni | H176: Throne 250 EC 20 X 500 ml (edit kms yg 250 qty 32 box @114.500 + kms 100 ml qty 11 box @50.000 | L176: Permintaan Cust
A177: 14 | B177: 45058 | C177: 45057 | D177: C23003204 | E177: Fani | F177: Elok | G177: Wes Joyo/Hermas | H177: tambah barang Bravoxone 276 SL 20 X 1 ltr (Label Kuda) qty 1 box harga 55.000 | K177: Permintaan Cust minta kms baru dan lama, bukti di wa mb elok | L177: Permintaan Cust
A178: 15 | B178: 45050 | C178: 45044 | D178: B23003670 | E178: Nia | F178: Zakia | G178: Sumber Makmur/Mahrus | H178: Gamectin 30 EC 100 X 100 ml (coret retur) | K178: Retur | L178: Retur
A179: 16 | B179: 45057 | C179: 45050 | D179: B23003918 | E179: Nia | F179: Elok | G179: Lestari Jaya | H179: Batal krn retur | K179: Batal krn retur | L179: Retur
A180: 17 | B180: 45058 | C180: 45029 | D180: D23003960 | E180: Nina | F180: Dannis | G180: Ingatan, UD/Fathurrahman | H180: Paratop 276 SL 20 X 1 ltr (CORET KRN RETUR) | K180: Retur | L180: Retur
A181: 18 | B181: 45051 | C181: 45051 | D181: C23002941 | E181: Fani | F181: Elok | G181: Mitra Tani/Eko Susanto | H181: Atonik 6.0 L 50 X 100 ml (edit harga jadi 12.500) | K181: SC SALAH HARGA | L181: SC Salah Harga
A182: 19 | B182: 45057 | C182: 45056 | D182: C23003109 | E182: Fani | F182: Riyan | G182: Andalas Farm, UD | H182: Batal Tdk cocok harga | K182: Batal Tdk cocok harga | L182: Tidak Cocok Harga
A183: 20 | B183: 45054 | C183: 45052 | D183: D23004601 | E183: Nina | F183: Evi | G183: Tani Sejati/Meggie | H183: Baycarb 500 EC 20 X 500 ml (CORET) | K183: Tidak cocok harga | L183: Tidak Cocok Harga
...

Sheet Rincian November
A1: No | B1: Tanggal Revisi | C1: Tanggal Faktur | D1: No. Faktur | E1: Adm SC | F1: SC | G1: Cust | H1: Keterangan | I1: Total | J1: Klasifikasi | K1: Berdasarkan Bukti | L1: Klasifikasi
A2: 1 | B2: 45232 | C2: 45227 | D2: D23009824 | E2: Nina | F2: Evi | G2: Petrus Mulianto | H2: Batal | I2: 16200000 | K2: Kios tidak komit, batal transfer, susah dihubungi. | L2: kios batal transfer/tidak tepat janji
A3: 2 | B3: 45231 | C3: 45231 | D3: D23009942 | E3: Nina | F3: Evi | G3: Herry Djuwarsa | H3: Abenz 22 EC 100 X 100 ml (edit harga jadi 66.000) | I3: 305000000 | K3: Revisi harga dari P. Agoes | L3: Lain-lain
A4: 3 | B4: 45241 | C4: 45238 | D4: D23010039 | E4: Nina | F4: Evi | G4: Tani Agung/Robert | H4: Batal | I4: 16250000 | K4: kios awal ganti order barang Neocron, paket convey lgsg dioper ke rizki tani/ratna nota tgl 9 | L4: Permintaan cust
A5: 4 | B5: 45243 | C5: 45211 | D5: D23009260 | E5: Nina | F5: Evi | G5: Karya Tani Makmur/Irwanto | H5: Padi Pahisa 01 20 X 1 kg (edit qty jadi 2box) | I5: 3600000 | K5: Retur, Daya tumbuh bermasalah, retur ke pabrik | L5: Retur
A7: No | B7: Tanggal Revisi | C7: Tanggal Faktur | D7: No. Faktur | E7: Adm SC | F7: SC | G7: Cust | H7: Keterangan | I7: Total | J7: Klasifikasi | K7: Berdasarkan Bukti | L7: Klasifikasi
A8: 1 | B8: 45246 | C8: 45245 | D8: D23010221 | E8: Nina | F8: Hendra | G8: Kharisma Eka Putra, CV | H8: Amco Up 486 SL 20 X 1 ltr (edit harga jadi 43.000) | I8: 43000000 | K8: ACC Pak Agoes, harga KEP diturunkan (harga awal 50.000) | L8: Lain-lain
A10: No | B10: Tanggal Revisi | C10: Tanggal Faktur | D10: No. Faktur | E10: Adm SC | F10: SC | G10: Cust | H10: Keterangan | I10: Total | J10: Klasifikasi | K10: Berdasarkan Bukti | L10: Klasifikasi
A11: 1 | B11: 45237 | C11: 45237 | D11: C23007391 | E11: Fani | F11: Riyan | G11: Makmur Abadi | H11: Padi Q-989 Ciherang 4 X 5 kg* (edit qty jadi 2 box) | I11: 1360000 | K11: kios salah order. | L11: Permintaan Cust
A12: 2 | B12: 45239 | C12: 45239 | D12: C23007481 | E12: Fani | F12: Riyan | G12: Murah Jaya Wardani, CV | H12: Jagung NK 7328 20 X 1 kg (edit barang jadi Jagung NK 212 20 X 1 kg, qty 25box, harga 82.000) | I12: 41000000 | K12: Cust ganti order barang lain | L12: Permintaan Cust
A14: No | B14: Tanggal Revisi | C14: Tanggal Faktur | D14: No. Faktur | E14: Adm SC | F14: SC | G14: Cust | H14: Keterangan | I14: Total | J14: Klasifikasi | K14: Berdasarkan Bukti | L14: Klasifikasi
A15: 1 | B15: 45240 | C15: 45240 | D15: C23007513 | E15: Fani | F15: Umi | G15: Sari Puja/Wayan Deresta | H15: Powercall Cair 20 X 1 ltr* (edit harga sblm tutupan 36.500) | I15: 1351000 | K15: kios nego harga, barang sudah kirim (harga awal 37.500) | L15: Kios tidak cocok harga
A16: 2 | B16: 45243 | C16: 45239 | D16: C23007457 | E16: Fani | F16: Umi | G16: Setia Jaya, UD/Saiful | H16: Abacell 18 EC 10 X 1 ltr (coret) | I16: 41540000 | K16: Retur, kios tidak cocok harga, harga kemahalan (ACC P. Agoes) | L16: Lain-lain
A17: 3 | C17: 45245 | D17: C23007658 | E17: Fani | F17: Umi | G17: Nara Kisma/Satrio | H17: Batal | I17: 5482500 | K17: SE double order, Oper ke toko Dino Vita, nota tgl 18/11/23 C23007804 | L17: Lain-lain
A18: 4 | B18: 45251 | C18: 45251 | D18: C23007941 | E18: Fani | F18: Umi | G18: Setia Tani/Hendrayani | H18: Batal | I18: 32800000 | K18: Pembagian barang, di oper ke Mutiara Tani, UD/Abdurrahman krna tidak mau PO barang laintgl besok 22/11/23 | L18: Pembagian barang
A19: 5 | B19: 45234 | C19: 45234 | D19: Z23002045 | E19: Fani | F19: Umi | G19: Mutiara Tani, UD/Abdur Rahman | H19: Jagung NK 7328 20 X 1 kg (edit qty jadi 40box) | I19: 84000000 | K19: Pembagian barang | L19: Pembagian barang ke Kumpul Tani/hendro
A20: 6 | B20: 45254 | C20: 45254 | D20: C23008096 | E20: Fani | F20: Umi | G20: Tawaf, Toko | H20: Batal | I20: 35875000 | K20: kios membatalkan orderan. | L20: Pembatalan order oleh kios
A21: 7 | B21: 45241 | C21: 45223 | D21: C23007067 | E21: Fani | F21: Umi | G21: Bimo Rukun Tani II | H21: Andri Eka Ardika (edit kontak person jadi Cindo Agro, CV) | I21: 100000000 | K21: ganti kontak person info tgl 26/5/23, 2nota sebelumnya di okt diganti ke nama kontak person baru | L21: Permintaan Cust
A22: 8 | B22: 45253 | C22: 45251 | D22: C23007906 | E22: Fani | F22: Umi | G22: Tani Makmur/Ashuri | H22: Tangki TOP AGRI Single Fungsi 16 ltr baterai* (edit qty jadi 10 pack) | I22: 4550000 | K22: Permintaan cust (belum kirim di dataku) | L22: Permintaan cust
A23: 9 | B23: 45251 | C23: 45251 | D23: C23007919 | E23: Fani | F23: Umi | G23: Sukma Tani | H23: Lem Ajaib 50 X 50 ml* (coret) | I23: 34750000 | K23: stok dikios ternyata masih ada. | L23: Permintaan cust
A24: 10 | B24: 45252 | C24: 45252 | D24: C23007977 | E24: Fani | F24: Umi | G24: Sumber Rejeki, UD/Sigit | H24: Batal | I24: 3000000 | K24: Permintaan toko, kirim tgl 15/12 mendekati gathering | L24: Permintaan Cust
A25: 11 | B25: 45244 | C25: 45225 | D25: E23005823 | E25: Nita | F25: Umi | G25: Rejeki Tani/Sulantrini | H25: GG Akar 50 X 100 ml (M2U)* (coret) | I25: 21642500 | K25: Retur, kios & SE salah PO | L25: Retur, kios & SE salah PO
A26: 12 | B26: 45244 | C26: 45240 | D26: C23007504 | E26: Fani | F26: Umi | G26: Perdana Jaya/Zainud | H26: Batal | I26: 6420000 | K26: Retur, kios tidak order | L26: Salah SO
A27: 13 | B27: 45244 | C27: 45240 | D27: C23007538 | E27: Fani | F27: Umi | G27: Perdana Jaya/Zainud | H27: Batal | I27: 6250000 | K27: Retur, kios tidak order | L27: Salah SO
A28: 14 | B28: 45244 | C28: 45240 | D28: C23007539 | E28: Fani | F28: Umi | G28: Perdana Jaya/Zainud | H28: Batal | I28: 1175000 | K28: Retur, kios tidak order | L28: Salah SO
A30: No | B30: Tanggal Revisi | C30: Tanggal Faktur | D30: No. Faktur | E30: Adm SC | F30: SC | G30: Cust | H30: Keterangan | I30: Total | J30: Klasifikasi | K30: Berdasarkan Bukti | L30: Klasifikasi
A31: 1 | B31: 45233 | C31: 45233 | D31: E23006017 | E31: Nita | F31: Yuyun | G31: Permata, UD/Badar | H31: Batal | I31: 2150000 | K31: kios double order ke SC n ke SE, sdh order ke SC tgl 30. | L31: Double Order
A32: 2 | B32: 45234 | C32: 45233 | D32: E23005989 | E32: Nita | F32: Yuyun | G32: Tani Sejati/Eni | H32: Batal | I32: 132000 | K32: Retur, kios batal order saat dikirim. (ada bukti orderannya) | L32: Pembatalan Order
A33: 3 | B33: 45239 | C33: 45236 | D33: E23006043 | E33: Nita | F33: Yuyun | G33: H Bahri | H33: Jagung ADV 132 20 X 1 kg (coret) | I33: 60000000 | K33: Retur, kios batal sepihak | L33: Pembatalan Order
A34: 4 | B34: 45251 | C34: 45251 | D34: E23006442 | E34: Nita | F34: Yuyun | G34: Dulur Tani/Miftahur | H34: Batal | I34: 1260000 | K34: kios membatalkan orderan karna harga tidak cocok | L34: Pembatalan order oleh kios
A35: 5 | B35: 45252 | C35: 45252 | D35: E23006444 | E35: Nita | F35: Yuyun | G35: Makmur/Heru | H35: Decis 2.5 EC 100 X 100 ml (edit harga jadi 27.250, harga awal 22.500) | I35: 990250 | K35: SC salah harga | L35: Salah harga oleh SC
A36: 6 | B36: 45246 | C36: 45246 | D36: E23006282 | E36: Nita | F36: Yuyun | G36: Berkah Kayra/Nuyun | H36: Qiuvita Hijau 32.11.11 100 X 100 gr* (edit harga 13.500, harga awal 13.000) | I36: 1799000 | K36: SC salah harga | L36: Slah harga oleh SC
A38: No | B38: Tanggal Revisi | C38: Tanggal Faktur | D38: No. Faktur | E38: Adm SC | F38: SC | G38: Cust | H38: Keterangan | I38: Total | J38: Klasifikasi | K38: Berdasarkan Bukti | L38: Klasifikasi
A39: 1 | B39: 45248 | C39: 45245 | D39: B23008695 | E39: Nia | F39: Zakia | G39: Berkah Tani/Luluk | H39: Asia Top 288 SL 4 X 5 ltr* (edit harga jadi 220.000) | I39: 9295000 | K39: ACC Pak Agoes (harga awal 225.000) | L39: Lain-lain
A40: 2 | B40: 45252 | C40: 45252 | D40: B23008904 | E40: Nia | F40: Zakia | G40: Inti Tani/Hermin | H40: Atonik 6.0 L 15 X 500 ml (edit qty jadi 25 box) | I40: 20625000 | K40: Pembagian barang ke Karya tani/Agus | L40: Pembagian barang
A41: 3 | B41: 45248 | C41: 45246 | D41: B23008732 | E41: Nia | F41: Zakia | G41: Barokah Tani, UD/Sutrisno | H41: Neocron 80 OL 20 X 500 ml* (edit harga jadi 160.000) | I41: 184500000 | K41: kios tidak jadi ikut program, minta kembali harga net (harga awal 165.000). | L41: Permintaan Cust
A42: 4 | B42: 45252 | C42: 45251 | D42: B23008868 | E42: Nia | F42: Zakia | G42: Sampurna Tani | H42: Metsulindo Plus 80 WP 8 X 25 X 40 gr* (edit qty jadi 1 box) | I42: 1800000 | K42: kios mengurangi qty yg di order. | L42: Permintaan Cust
A43: 5 | B43: 45254 | C43: 45252 | D43: B23008896 | E43: Nia | F43: Zakia | G43: D Live Tani | H43: Damazeb 80 WP Blue 20 X 800 gr* (edit harga jadi 65.000) | I43: 6500000 | K43: harga nett tidak ikut program, kios tidak jadi ikut program(harga awal 72.000) | L43: Permintaan Cust
A44: 6 | B44: 45254 | C44: 45253 | D44: B23008915 | E44: Nia | F44: Zakia | G44: Anugrah Tani/Agung | H44: Neocron 80 OL 20 X 250 ml* (edit harga jadi 86.500 harga awal 85.500) | I44: 51320000 | K44: SC salah harga (barang sdh kirim) | L44: Salah harga oleh SC
A45: 7 | C45: 45243 | D45: D23010156 | E45: Nina | F45: Zakia | G45: Benih Jaya | H45: Atonik 6.0 L 30 X 250 ml (coret) | I45: 4620000 | K45: Retur, SC salah tulis kemasan (kios minta kemasan 100ml) | L45: SC salah SO
A47: ADMIN SALAH INPUT
A48: No. Urut | B48: Tanggal Revisi | C48: Tanggal Faktur | D48: No. Faktur | E48: Admin SC | F48: SC | G48: Cust | H48: Keterangan | I48: Total | J48: √ | K48: Alasan
A49: 1 | B49: 45248 | C49: 45246 | D49: C23007704 | E49: Fani | F49: Umi | G49: Manggala | H49: Tali Kapas Cap Kelud 15 X 900 gr (Putih)* (edit qty jadi 1 zak) | I49: 1575000 | K49: Admin salah input | L49: Salah input oleh admin SC
A50: 2 | B50: 45246 | C50: 45246 | D50: C23007734 | E50: Fani | F50: Umi | G50: Sumber Tani/Sandra | H50: Bayam Belang 2 kg (edit barang jadi Bayam Belang 35 X 500 gr) | I50: 1140000 | K50: Admin salah input | L50: Salah input oleh Admin SC
A51: 3 | B51: 45243 | C51: 45243 | D51: T23000954 | E51: Fani | F51: Umi | G51: Setia Tani/Hendrayani | H51: edit nama toko jadi Setia Hati, Toko | I51: 247500 | K51: Admin SC salah input | L51: Salah input oleh admin SC
A52: 4 | B52: 45251 | C52: 45251 | D52: E23006419 | E52: Nita | F52: Yuyun | G52: Tretan Tani/Anam | H52: Mulsa Hanoman 60 cm X 18 kg (Roll)* (edit harga jadi 621.000, harga awal 34.500) | I52: 4804500 | K52: Admin salah input, barang sdh kirim | L52: Salah input oleh admin SC
A54: Admin Keuangan salah Input
A55: No. Urut | B55: Tanggal Revisi | C55: Tanggal Faktur | D55: No. Faktur | E55: Admin SC | F55: SC | G55: Cust | H55: Keterangan | I55: Total | J55: √ | K55: Alasan
A56: 1 | B56: 45244 | C56: 45244 | D56: C23007602 | E56: Sukma | F56: Umi | G56: Setia Jaya, UD/Saiful | H56: Akrostar 40 WP 60 X 40 gr (edit harga jadi 36.500) | I56: 10950000 | K56: Master barang di zahir awalnya terisi 50 pack 1 box, jd saat print preview munculnya 43.800 krna total nota 10.950.000 dibagi 50pack x 5box, admin penj ikuti print preview tidak liat SO, barang belum kirim | L56: Salah input oleh Admin Keuangan | M56: Membuat SOP terkait Revisi Faktur Penjualan
A57: 2 | B57: 45234 | C57: 45234 | D57: Z230006 | E57: Ahmad | F57: Umi | G57: Mutiara Tani, UD/Abdur Rahman | H57: Marshal 200 SC 24 X 500 ml (edit barang jadi Marshal 200 EC 24 X 500 ml) | I57: 4518000 | K57: Admin pajak salah input | L57: Salah input oleh Admin Keuangan | M57: Membuat SOP terkait Input Penjualan BPK, tgl 30/11/2023 draft SOP Selesai, Minggu pertama Desember pengajuan ke Bu Diana
